Workbook

Sheet Ringkasan
A1: JastipKita — Model Bisnis & Proyeksi Keuangan 24 Bulan
A2: Untuk Direksi & Dewan Komisaris. Pra-launch: seluruh integrasi MOCK/SANDBOX, belum ada transaksi nyata. Bukan nasihat keuangan/investasi; angka berstatus ASUMSI wajib diganti data beta.
A3: ="Skenario aktif (ubah di Asumsi!D4): "&Asumsi!$D$4 -> Skenario aktif (ubah di Asumsi!D4): Dasar
A4: Soft launch (Bulan 1): | C4: =Asumsi!$G$10 -> 46419 | D4: ="Bulan 0 = pra-peluncuran (biaya sekali + "&Asumsi!$G$11&" bulan biaya tim & infra)" -> Bulan 0 = pra-peluncuran (biaya sekali + 3 bulan biaya tim & infra)
B6: KPI | C6: Satuan | D6: Konservatif | E6: Dasar | F6: Optimis | G6: Skenario aktif | H6: Definisi / catatan
A7: Volume
B8: Transaksi selesai — Tahun 1 | C8: transaksi | D8: ='Proyeksi 24 Bulan'!$AB$38 -> 649.033 | E8: ='Proyeksi 24 Bulan'!$AB$101 -> 1581.9758 | F8: ='Proyeksi 24 Bulan'!$AB$164 -> 3445.195 | G8: =CHOOSE(Asumsi!$D$5,D8,E8,F8) -> 1581.9758 | H8: B1–B12, status COMPLETED
B9: Transaksi selesai — Tahun 2 | C9: transaksi | D9: ='Proyeksi 24 Bulan'!$AC$38 -> 1621.4578 | E9: ='Proyeksi 24 Bulan'!$AC$101 -> 5230.5395 | F9: ='Proyeksi 24 Bulan'!$AC$164 -> 11620.519 | G9: =CHOOSE(Asumsi!$D$5,D9,E9,F9) -> 5230.5395 | H9: B13–B24
B10: Transaksi selesai — Bulan 24 | C10: trx/bulan | D10: ='Proyeksi 24 Bulan'!$AA$38 -> 178.16361 | E10: ='Proyeksi 24 Bulan'!$AA$101 -> 589.45116 | F10: ='Proyeksi 24 Bulan'!$AA$164 -> 1424.8058 | G10: =CHOOSE(Asumsi!$D$5,D10,E10,F10) -> 589.45116 | H10: run-rate akhir periode
B11: Traveler aktif — Bulan 24 | C11: orang | D11: ='Proyeksi 24 Bulan'!$AA$21 -> 77.462439 | E11: ='Proyeksi 24 Bulan'!$AA$84 -> 263.63022 | F11: ='Proyeksi 24 Bulan'!$AA$147 -> 983.66545 | G11: =CHOOSE(Asumsi!$D$5,D11,E11,F11) -> 263.63022 | H11: traveler dengan trip aktif
B12: Basis pembeli — Bulan 24 | C12: orang | D12: ='Proyeksi 24 Bulan'!$AA$36 -> 966.71415 | E12: ='Proyeksi 24 Bulan'!$AA$99 -> 2811.658 | F12: ='Proyeksi 24 Bulan'!$AA$162 -> 6302.4713 | G12: =CHOOSE(Asumsi!$D$5,D12,E12,F12) -> 2811.658 | H12: setelah churn
B13: Fill rate (likuiditas) — Tahun 2 | C13: % | D13: ='Proyeksi 24 Bulan'!$AC$35 -> 0.71805297 | E13: ='Proyeksi 24 Bulan'!$AC$98 -> 0.98504664 | F13: ='Proyeksi 24 Bulan'!$AC$161 -> 1 | G13: =CHOOSE(Asumsi!$D$5,D13,E13,F13) -> 0.98504664 | H13: transaksi dibayar ÷ permintaan
B14: Sisi pembatas — Bulan 24 | C14: teks | D14: ='Proyeksi 24 Bulan'!$AA$39 -> Pasokan | E14: ='Proyeksi 24 Bulan'!$AA$102 -> Permintaan | F14: ='Proyeksi 24 Bulan'!$AA$165 -> Permintaan | G14: =CHOOSE(Asumsi!$D$5,D14,E14,F14) -> Permintaan | H14: Pasokan = traveler kurang; Permintaan = pembeli kurang
A15: Nilai & pendapatan (Rp juta)
B16: GMV — Tahun 1 | C16: Rp juta | D16: ='Proyeksi 24 Bulan'!$AB$41/1000000 -> 1420.2904 | E16: ='Proyeksi 24 Bulan'!$AB$104/1000000 -> 4619.5808 | F16: ='Proyeksi 24 Bulan'!$AB$167/1000000 -> 12588.696 | G16: =CHOOSE(Asumsi!$D$5,D16,E16,F16) -> 4619.5808 | H16: Σ TOTAL transaksi selesai (launch-plan §8), sebelum promo & credit
B17: GMV — Tahun 2 | C17: Rp juta | D17: ='Proyeksi 24 Bulan'!$AC$41/1000000 -> 3548.2647 | E17: ='Proyeksi 24 Bulan'!$AC$104/1000000 -> 15273.874 | F17: ='Proyeksi 24 Bulan'!$AC$167/1000000 -> 42461.217 | G17: =CHOOSE(Asumsi!$D$5,D17,E17,F17) -> 15273.874
B18: GMV run-rate tahunan — Bulan 24 | C18: Rp juta | D18: ='Proyeksi 24 Bulan'!$AA$41*12/1000000 -> 4678.5429 | E18: ='Proyeksi 24 Bulan'!$AA$104*12/1000000 -> 20655.314 | F18: ='Proyeksi 24 Bulan'!$AA$167*12/1000000 -> 62474.652 | G18: =CHOOSE(Asumsi!$D$5,D18,E18,F18) -> 20655.314 | H18: GMV bulan 24 × 12
B19: Take rate bruto — Tahun 2 | C19: % | D19: ='Proyeksi 24 Bulan'!$AC$48 -> 0.044554774 | E19: ='Proyeksi 24 Bulan'!$AC$111 -> 0.04451851 | F19: ='Proyeksi 24 Bulan'!$AC$174 -> 0.044471977 | G19: =CHOOSE(Asumsi!$D$5,D19,E19,F19) -> 0.04451851 | H19: (platform + protection fee) ÷ GMV
B20: Take rate bersih — Tahun 2 | C20: % | D20: ='Proyeksi 24 Bulan'!$AC$49 -> 0.041946504 | E20: ='Proyeksi 24 Bulan'!$AC$112 -> 0.042086535 | F20: ='Proyeksi 24 Bulan'!$AC$175 -> 0.042131851 | G20: =CHOOSE(Asumsi!$D$5,D20,E20,F20) -> 0.042086535 | H20: setelah promo & credit referral
B21: Pendapatan bersih — Tahun 1 | C21: Rp juta | D21: ='Proyeksi 24 Bulan'!$AB$47/1000000 -> 58.087935 | E21: ='Proyeksi 24 Bulan'!$AB$110/1000000 -> 191.71895 | F21: ='Proyeksi 24 Bulan'!$AB$173/1000000 -> 525.97632 | G21: =CHOOSE(Asumsi!$D$5,D21,E21,F21) -> 191.71895 | H21: bea, pajak impor, PPN, harga barang & traveler fee = pass-through
B22: Pendapatan bersih — Tahun 2 | C22: Rp juta | D22: ='Proyeksi 24 Bulan'!$AC$47/1000000 -> 148.8373 | E22: ='Proyeksi 24 Bulan'!$AC$110/1000000 -> 642.82445 | F22: ='Proyeksi 24 Bulan'!$AC$173/1000000 -> 1788.9697 | G22: =CHOOSE(Asumsi!$D$5,D22,E22,F22) -> 642.82445
A23: Unit economics per transaksi representatif (Rp)
B24: Nilai barang rata-rata | C24: Rp | D24: ='Unit Economics'!$C$8 -> 1500000 | E24: ='Unit Economics'!$D$8 -> 2000000 | F24: ='Unit Economics'!$E$8 -> 2500000 | G24: =CHOOSE(Asumsi!$D$5,D24,E24,F24) -> 2000000 | H24: ASUMSI skenario
B25: TOTAL dibayar pembeli (11 baris) | C25: Rp | D25: ='Unit Economics'!$C$18 -> 2188317.7 | E25: ='Unit Economics'!$D$18 -> 2920133.6 | F25: ='Unit Economics'!$E$18 -> 3653986.4 | G25: =CHOOSE(Asumsi!$D$5,D25,E25,F25) -> 2920133.6 | H25: Unit Economics baris 11
B26: Pendapatan bruto platform | C26: Rp | D26: ='Unit Economics'!$C$47 -> 97500 | E26: ='Unit Economics'!$D$47 -> 130000 | F26: ='Unit Economics'!$E$47 -> 162500 | G26: =CHOOSE(Asumsi!$D$5,D26,E26,F26) -> 130000 | H26: platform fee 5% + protection 1,5% (clamp config)
B27: Subsidi kanal pembayaran | C27: Rp | D27: ='Unit Economics'!$C$35 -> 14637.8 | E27: ='Unit Economics'!$D$35 -> 16233.3 | F27: ='Unit Economics'!$E$35 -> 16528.14 | G27: =CHOOSE(Asumsi!$D$5,D27,E27,F27) -> 16233.3 | H27: biaya Xendit publik − biaya dibebankan (launch-checklist B4)
B28: Margin kontribusi per transaksi | C28: Rp | D28: ='Unit Economics'!$C$57 -> 19350.475 | E28: ='Unit Economics'!$D$57 -> 77258.008 | F28: ='Unit Economics'!$E$57 -> 110884.07 | G28: =CHOOSE(Asumsi!$D$5,D28,E28,F28) -> 77258.008 | H28: setelah promo, referral, subsidi, payout, klaim, CS, chargeback, batal
B29: Margin kontribusi ÷ pendapatan bersih | C29: % | D29: ='Unit Economics'!$C$59 -> 0.21080723 | E29: ='Unit Economics'!$D$59 -> 0.62863362 | F29: ='Unit Economics'!$E$59 -> 0.72026397 | G29: =CHOOSE(Asumsi!$D$5,D29,E29,F29) -> 0.62863362
B30: BEP transaksi/bulan (biaya tetap + marketing) | C30: trx/bulan | D30: =IF('Unit Economics'!$C$57>0,ROUNDUP(('Proyeksi 24 Bulan'!$AC$71-'Proyeksi 24 Bulan'!$AC$69)/12/'Unit Economics'!$C$57,0),"CM ≤ 0") -> 8470 | E30: =IF('Unit Economics'!$D$57>0,ROUNDUP(('Proyeksi 24 Bulan'!$AC$134-'Proyeksi 24 Bulan'!$AC$132)/12/'Unit Economics'!$D$57,0),"CM ≤ 0") -> 2122 | F30: =IF('Unit Economics'!$E$57>0,ROUNDUP(('Proyeksi 24 Bulan'!$AC$197-'Proyeksi 24 Bulan'!$AC$195)/12/'Unit Economics'!$E$57,0),"CM ≤ 0") -> 1479 | G30: =CHOOSE(Asumsi!$D$5,D30,E30,F30) -> 2122 | H30: rata-rata biaya Th2 (tanpa biaya sekali) ÷ margin kontribusi per transaksi
B31: BEP transaksi/bulan (hanya biaya tetap) | C31: trx/bulan | D31: =IF('Unit Economics'!$C$57>0,ROUNDUP(('Proyeksi 24 Bulan'!$AC$71-'Proyeksi 24 Bulan'!$AC$69-'Proyeksi 24 Bulan'!$AC$63)/12/'Unit Economics'!$C$57,0),"CM ≤ 0") -> 6661 | E31: =IF('Unit Economics'!$D$57>0,ROUNDUP(('Proyeksi 24 Bulan'!$AC$134-'Proyeksi 24 Bulan'!$AC$132-'Proyeksi 24 Bulan'!$AC$126)/12/'Unit Economics'!$D$57,0),"CM ≤ 0") -> 1669 | F31: =IF('Unit Economics'!$E$57>0,ROUNDUP(('Proyeksi 24 Bulan'!$AC$197-'Proyeksi 24 Bulan'!$AC$195-'Proyeksi 24 Bulan'!$AC$189)/12/'Unit Economics'!$E$57,0),"CM ≤ 0") -> 1163 | G31: =CHOOSE(Asumsi!$D$5,D31,E31,F31) -> 1669 | H31: tanpa marketing
B32: Transaksi Bulan 24 ÷ BEP (biaya tetap + marketing) | C32: % | D32: =IF(ISNUMBER(D30),'Proyeksi 24 Bulan'!$AA$38/D30,0) -> 0.021034665 | E32: =IF(ISNUMBER(E30),'Proyeksi 24 Bulan'!$AA$101/E30,0) -> 0.27778094 | F32: =IF(ISNUMBER(F30),'Proyeksi 24 Bulan'!$AA$164/F30,0) -> 0.96335755 | G32: =CHOOSE(Asumsi!$D$5,D32,E32,F32) -> 0.27778094 | H32: ≥ 100% = volume sudah menutup biaya
B33: Status CAC vs LTV 12 bulan | C33: teks | D33: ='Unit Economics'!$C$72 -> Melewati guardrail | E33: ='Unit Economics'!$D$72 -> Melewati guardrail | F33: ='Unit Economics'!$E$72 -> Melewati guardrail | G33: =CHOOSE(Asumsi!$D$5,D33,E33,F33) -> Melewati guardrail | H33: guardrail config: CAC ≤ 0,33 × LTV
A34: Laba & kas (Rp juta)
B35: Margin kontribusi — Tahun 1 | C35: Rp juta | D35: ='Proyeksi 24 Bulan'!$AB$60/1000000 -> -16.083381 | E35: ='Proyeksi 24 Bulan'!$AB$123/1000000 -> 89.376021 | F35: ='Proyeksi 24 Bulan'!$AB$186/1000000 -> 338.29874 | G35: =CHOOSE(Asumsi!$D$5,D35,E35,F35) -> 89.376021
B36: Margin kontribusi — Tahun 2 | C36: Rp juta | D36: ='Proyeksi 24 Bulan'!$AC$60/1000000 -> -17.358281 | E36: ='Proyeksi 24 Bulan'!$AC$123/1000000 -> 336.27401 | F36: ='Proyeksi 24 Bulan'!$AC$186/1000000 -> 1170.2409 | G36: =CHOOSE(Asumsi!$D$5,D36,E36,F36) -> 336.27401
B37: EBITDA — Bulan 0 (pra-peluncuran) | C37: Rp juta | D37: ='Proyeksi 24 Bulan'!$C$73/1000000 -> -474.72608 | E37: ='Proyeksi 24 Bulan'!$C$136/1000000 -> -474.28625 | F37: ='Proyeksi 24 Bulan'!$C$199/1000000 -> -474.08853 | G37: =CHOOSE(Asumsi!$D$5,D37,E37,F37) -> -474.28625 | H37: biaya sekali + tim & infra pra-launch
B38: EBITDA — Tahun 1 | C38: Rp juta | D38: ='Proyeksi 24 Bulan'!$AB$73/1000000 -> -1406.7523 | E38: ='Proyeksi 24 Bulan'!$AB$136/1000000 -> -1301.2929 | F38: ='Proyeksi 24 Bulan'!$AB$199/1000000 -> -1052.3702 | G38: =CHOOSE(Asumsi!$D$5,D38,E38,F38) -> -1301.2929 | H38: pra-pajak
B39: EBITDA — Tahun 2 | C39: Rp juta | D39: ='Proyeksi 24 Bulan'!$AC$73/1000000 -> -2019.0272 | E39: ='Proyeksi 24 Bulan'!$AC$136/1000000 -> -1665.3949 | F39: ='Proyeksi 24 Bulan'!$AC$199/1000000 -> -831.428 | G39: =CHOOSE(Asumsi!$D$5,D39,E39,F39) -> -1665.3949
B40: EBITDA — Bulan 24 | C40: Rp juta | D40: ='Proyeksi 24 Bulan'!$AA$73/1000000 -> -166.62315 | E40: ='Proyeksi 24 Bulan'!$AA$136/1000000 -> -127.4246 | F40: ='Proyeksi 24 Bulan'!$AA$199/1000000 -> -22.977487 | G40: =CHOOSE(Asumsi!$D$5,D40,E40,F40) -> -127.4246
B41: Puncak kebutuhan kas (peak cash burn) | C41: Rp juta | D41: =MAX(0,-MIN('Proyeksi 24 Bulan'!$C$76:$AA$76))/1000000 -> 3916.8524 | E41: =MAX(0,-MIN('Proyeksi 24 Bulan'!$C$139:$AA$139))/1000000 -> 3513.2508 | F41: =MAX(0,-MIN('Proyeksi 24 Bulan'!$C$202:$AA$202))/1000000 -> 2576.6759 | G41: =CHOOSE(Asumsi!$D$5,D41,E41,F41) -> 3513.2508 | H41: titik terendah kas kumulatif B0–B24 (sebelum buffer)
B42: Bulan puncak kebutuhan kas | C42: bulan ke- | D42: =INDEX('Proyeksi 24 Bulan'!$C$5:$AA$5,MATCH(MIN('Proyeksi 24 Bulan'!$C$76:$AA$76),'Proyeksi 24 Bulan'!$C$76:$AA$76,0)) -> 24 | E42: =INDEX('Proyeksi 24 Bulan'!$C$5:$AA$5,MATCH(MIN('Proyeksi 24 Bulan'!$C$139:$AA$139),'Proyeksi 24 Bulan'!$C$139:$AA$139,0)) -> 24 | F42: =INDEX('Proyeksi 24 Bulan'!$C$5:$AA$5,MATCH(MIN('Proyeksi 24 Bulan'!$C$202:$AA$202),'Proyeksi 24 Bulan'!$C$202:$AA$202,0)) -> 24 | G42: =CHOOSE(Asumsi!$D$5,D42,E42,F42) -> 24 | H42: 24 = kas masih turun di akhir periode
B43: Bulan BEP pertama (EBITDA bulanan ≥ 0) | C43: bulan ke- | D43: =IF(MIN('Proyeksi 24 Bulan'!$D$77:$AA$77)>24,"Belum ≤ B24",MIN('Proyeksi 24 Bulan'!$D$77:$AA$77)) -> Belum ≤ B24 | E43: =IF(MIN('Proyeksi 24 Bulan'!$D$140:$AA$140)>24,"Belum ≤ B24",MIN('Proyeksi 24 Bulan'!$D$140:$AA$140)) -> Belum ≤ B24 | F43: =IF(MIN('Proyeksi 24 Bulan'!$D$203:$AA$203)>24,"Belum ≤ B24",MIN('Proyeksi 24 Bulan'!$D$203:$AA$203)) -> Belum ≤ B24 | G43: =CHOOSE(Asumsi!$D$5,D43,E43,F43) -> Belum ≤ B24
B44: Periode BEP pertama | C44: bulan | D44: =IF(MIN('Proyeksi 24 Bulan'!$D$77:$AA$77)>24,"-",EDATE(Asumsi!$D$10,MIN('Proyeksi 24 Bulan'!$D$77:$AA$77)-1)) -> - | E44: =IF(MIN('Proyeksi 24 Bulan'!$D$140:$AA$140)>24,"-",EDATE(Asumsi!$E$10,MIN('Proyeksi 24 Bulan'!$D$140:$AA$140)-1)) -> - | F44: =IF(MIN('Proyeksi 24 Bulan'!$D$203:$AA$203)>24,"-",EDATE(Asumsi!$F$10,MIN('Proyeksi 24 Bulan'!$D$203:$AA$203)-1)) -> - | G44: =CHOOSE(Asumsi!$D$5,D44,E44,F44) -> -
B45: Kas kumulatif akhir Bulan 24 | C45: Rp juta | D45: ='Proyeksi 24 Bulan'!$AA$76/1000000 -> -3916.8524 | E45: ='Proyeksi 24 Bulan'!$AA$139/1000000 -> -3513.2508 | F45: ='Proyeksi 24 Bulan'!$AA$202/1000000 -> -2576.6759 | G45: =CHOOSE(Asumsi!$D$5,D45,E45,F45) -> -3513.2508 | H45: negatif = total dana yang sudah terpakai
A47: Temuan utama (angka dihitung ulang otomatis dari tabel di atas)
B48: ="1. Kebutuhan dana puncak (sebelum buffer): Konservatif Rp"&FIXED(D41,0)&" jt ("&IF(D42=24,"masih turun di B24","titik terendah bulan "&D42)&") · Dasar Rp"&FIXED(E41,0)&" jt ("&IF(E42=24,"masih turun di B24","titik terendah bulan "&E42)&") · Optimis Rp"&FIXED(F41,0)&" jt ("&IF(F42=24,"masih turun di B24","titik terendah bulan "&F42)&")." -> 1. Kebutuhan dana puncak (sebelum buffer): Konservatif Rp3,917 jt (masih turun di B24) · Dasar Rp3,513 jt (masih turun di B24) · Optimis Rp2,577 jt (masih turun di B24).
B49: ="2. EBITDA bulanan ≥ 0 pertama kali: Konservatif "&D43&" · Dasar "&E43&" · Optimis "&F43&". EBITDA Bulan 24: Konservatif "&IF(D40<0,"−Rp"&FIXED(-D40,0),"Rp"&FIXED(D40,0))&" jt · Dasar "&IF(E40<0,"−Rp"&FIXED(-E40,0),"Rp"&FIXED(E40,0))&" jt · Optimis "&IF(F40<0,"−Rp"&FIXED(-F40,0),"Rp"&FIXED(F40,0))&" jt." -> 2. EBITDA bulanan ≥ 0 pertama kali: Konservatif Belum ≤ B24 · Dasar Belum ≤ B24 · Optimis Belum ≤ B24. EBITDA Bulan 24: Konservatif −Rp167 jt · Dasar −Rp127 jt · Optimis −Rp23 jt.
B50: ="3. Margin kontribusi per transaksi (Dasar) Rp"&FIXED(E28,0)&" → perlu ±"&FIXED(E30,0)&" transaksi selesai/bulan untuk menutup biaya tetap + marketing Th2; volume Bulan 24 = "&FIXED(E10,0)&" transaksi ("&TEXT(E32,"0%")&" dari BEP)." -> 3. Margin kontribusi per transaksi (Dasar) Rp77,258 → perlu ±2,122 transaksi selesai/bulan untuk menutup biaya tetap + marketing Th2; volume Bulan 24 = 589 transaksi (28% dari BEP).
B51: ="4. Subsidi kanal bayar rata-rata Rp"&FIXED(E27,0)&"/transaksi (Dasar) = "&TEXT(E27/E26,"0%")&" pendapatan bruto. VA: dibebankan Rp"&FIXED('Unit Economics'!$D$21,0)&" vs biaya Xendit Rp"&FIXED('Unit Economics'!$D$22,0)&" (launch-checklist B4). E-wallet: dibebankan Rp"&FIXED('Unit Economics'!$D$27,0)&" vs biaya Rp"&FIXED('Unit Economics'!$D$28,0)&" per transaksi — config 1,5% di bawah tarif publik (≥2% + Rp4.000 + PPN). Lihat Sensitivitas tabel 2c." -> 4. Subsidi kanal bayar rata-rata Rp16,233/transaksi (Dasar) = 12% pendapatan bruto. VA: dibebankan Rp4,500 vs biaya Xendit Rp14,430 (launch-checklist B4). E-wallet: dibebankan Rp44,122 vs biaya Rp102,389 per transaksi — config 1,5% di bawah tarif publik (≥2% + Rp4.000 + PPN). Lihat Sensitivitas tabel 2c.
B52: ="5. Sisi pembatas Bulan 24 — Konservatif: "&D14&", Dasar: "&E14&", Optimis: "&F14&". Fill rate Th2: Konservatif "&TEXT(D13,"0%")&", Dasar "&TEXT(E13,"0%")&". Akuisisi pembeli tanpa pasokan traveler hanya membakar CAC." -> 5. Sisi pembatas Bulan 24 — Konservatif: Pasokan, Dasar: Permintaan, Optimis: Permintaan. Fill rate Th2: Konservatif 72%, Dasar 99%. Akuisisi pembeli tanpa pasokan traveler hanya membakar CAC.
B53: ="6. CAC blended + OTP (Dasar) Rp"&FIXED('Unit Economics'!$D$70,0)&" vs LTV 12 bulan Rp"&FIXED('Unit Economics'!$D$68,0)&" (rasio "&FIXED('Unit Economics'!$D$71,2)&"; guardrail config ≤ 0,33). Akuisisi berbayar belum balik modal dalam 12 bulan; biaya efektif referral ±Rp"&FIXED((Asumsi!$E$91+Asumsi!$E$92)*Asumsi!$E$97,0)&" per referral berkualifikasi jauh lebih murah." -> 6. CAC blended + OTP (Dasar) Rp265,817 vs LTV 12 bulan Rp130,598 (rasio 2.04; guardrail config ≤ 0,33). Akuisisi berbayar belum balik modal dalam 12 bulan; biaya efektif referral ±Rp35,000 per referral berkualifikasi jauh lebih murah.
B54: ="7. Yang rusak duluan: (a) bila biaya payout Xendit ternyata 1% + Rp4.000 (asumsi Konservatif), biaya payout per transaksi = Rp"&FIXED(-'Unit Economics'!$C$52,0)&" vs Rp"&FIXED(-'Unit Economics'!$D$52,0)&" (Dasar) — margin kontribusi Konservatif tinggal Rp"&FIXED(D28,0)&"; (b) likuiditas traveler di luar musim liburan; (c) setiap bulan tunda soft launch (PT/PSE/Xendit/merek) menambah ±Rp"&FIXED(('Proyeksi 24 Bulan'!$AB$134-'Proyeksi 24 Bulan'!$AB$126-'Proyeksi 24 Bulan'!$AB$131)/12/1000000,0)&" jt biaya tetap ke kebutuhan dana." -> 7. Yang rusak duluan: (a) bila biaya payout Xendit ternyata 1% + Rp4.000 (asumsi Konservatif), biaya payout per transaksi = Rp27,362 vs Rp4,995 (Dasar) — margin kontribusi Konservatif tinggal Rp19,350; (b) likuiditas traveler di luar musim liburan; (c) setiap bulan tunda soft launch (PT/PSE/Xendit/merek) menambah ±Rp96 jt biaya tetap ke kebutuhan dana.
B55: 8. Pendapatan platform hanya platform fee + protection fee. Harga barang, traveler fee, bea masuk & pajak impor (±27,6% nilai barang), PPN layanan dan biaya kanal bayar adalah pass-through; markup kurs bukan pendapatan.
B56: 9. Asumsi dengan dampak terbesar: pasokan traveler (traveler baru & pesanan per traveler), CAC, biaya SDM, rata-rata nilai barang, dan biaya payout Xendit — semuanya belum didukung data. Ganti dengan data beta 1A/1B sebelum keputusan pendanaan.
A58: Kas kumulatif per skenario (Rp juta) — sumber grafik
B59: Bulan ke- | C59: ='Proyeksi 24 Bulan'!C$5 -> 0 | D59: ='Proyeksi 24 Bulan'!D$5 -> 1 | E59: ='Proyeksi 24 Bulan'!E$5 -> 2 | F59: ='Proyeksi 24 Bulan'!F$5 -> 3 | G59: ='Proyeksi 24 Bulan'!G$5 -> 4 | H59: ='Proyeksi 24 Bulan'!H$5 -> 5 | I59: ='Proyeksi 24 Bulan'!I$5 -> 6 | J59: ='Proyeksi 24 Bulan'!J$5 -> 7 | ... AA59: ='Proyeksi 24 Bulan'!AA$5 -> 24
B60: Konservatif | C60: ='Proyeksi 24 Bulan'!C76/1000000 -> -474.72608 | D60: ='Proyeksi 24 Bulan'!D76/1000000 -> -577.91852 | E60: ='Proyeksi 24 Bulan'!E76/1000000 -> -679.91315 | F60: ='Proyeksi 24 Bulan'!F76/1000000 -> -781.86472 | G60: ='Proyeksi 24 Bulan'!G76/1000000 -> -905.13406 | H60: ='Proyeksi 24 Bulan'!H76/1000000 -> -1028.3711 | I60: ='Proyeksi 24 Bulan'!I76/1000000 -> -1151.5811 | J60: ='Proyeksi 24 Bulan'!J76/1000000 -> -1274.7681 | ... AA60: ='Proyeksi 24 Bulan'!AA76/1000000 -> -3916.8524
B61: Dasar | C61: ='Proyeksi 24 Bulan'!C139/1000000 -> -474.28625 | D61: ='Proyeksi 24 Bulan'!D139/1000000 -> -577.61846 | E61: ='Proyeksi 24 Bulan'!E139/1000000 -> -677.76458 | F61: ='Proyeksi 24 Bulan'!F139/1000000 -> -776.96965 | G61: ='Proyeksi 24 Bulan'!G139/1000000 -> -896.46626 | H61: ='Proyeksi 24 Bulan'!H139/1000000 -> -1014.9531 | I61: ='Proyeksi 24 Bulan'!I139/1000000 -> -1132.3909 | J61: ='Proyeksi 24 Bulan'!J139/1000000 -> -1248.7297 | ... AA61: ='Proyeksi 24 Bulan'!AA139/1000000 -> -3513.2508
B62: Optimis | C62: ='Proyeksi 24 Bulan'!C202/1000000 -> -474.08853 | D62: ='Proyeksi 24 Bulan'!D202/1000000 -> -578.96518 | E62: ='Proyeksi 24 Bulan'!E202/1000000 -> -674.65568 | F62: ='Proyeksi 24 Bulan'!F202/1000000 -> -768.64711 | G62: ='Proyeksi 24 Bulan'!G202/1000000 -> -886.51328 | H62: ='Proyeksi 24 Bulan'!H202/1000000 -> -991.12329 | I62: ='Proyeksi 24 Bulan'!I202/1000000 -> -1090.4101 | J62: ='Proyeksi 24 Bulan'!J202/1000000 -> -1186.6803 | ... AA62: ='Proyeksi 24 Bulan'!AA202/1000000 -> -2576.6759
B82: Catatan keterbatasan data: tidak ada data pasar jastip yang kredibel (research 04); volume, CAC, churn, biaya SDM, biaya sekali dan sebagian tarif (payout Xendit, bauran kanal, loss ratio) adalah ASUMSI; tarif Xendit = harga publik 2026-10-04, bukan kontrak; tarif bea/pajak = seed DRAFT (PMK 34/2025) sampai diverifikasi konsultan; model pra-pajak (PPh Badan tidak dimodelkan). Rincian di sheet Sumber.

Sheet Asumsi
A1: Asumsi & Input Model — JastipKita
A2: Semua angka model berasal dari sel di sheet ini. Kolom Konservatif/Dasar/Optimis dapat diubah; kolom Aktif mengikuti pemilih skenario.
B4: Pemilih skenario aktif → | D4: Dasar | F4: Legenda: | G4: Biru = input | H4: Hitam = rumus
B5: Indeks skenario aktif (1/2/3) | D5: =MATCH(D4,$D$8:$F$8,0) -> 2 | G5: Hijau = tautan antar-sheet | H5: Kuning = asumsi kunci / pemilih
B6: Status: SUMBER = dari repo/URL (lihat sheet Sumber) · ASUMSI = belum ada data · USULAN = proposal launch plan yang belum disetujui owner · CEK = pemeriksaan otomatis.
A8: ID | B8: Parameter | C8: Satuan | D8: Konservatif | E8: Dasar | F8: Optimis | G8: Aktif | H8: Status | I8: Sumber / catatan
A9: 1. Pengaturan model
A10: P001 | B10: Bulan pertama soft launch (Bulan 1) | C10: tanggal | D10: 46419 | E10: 46419 | F10: 46419 | G10: =INDEX(D10:F10,$D$5) -> 46419 | H10: ASUMSI | I10: launch-plan §1/§9: soft launch = minggu ke-7 setelah dogfood. Semua gerbang P0 masih BELUM per 2026-09-28 (launch-checklist) → diasumsikan PT/NIB, PSE, kontrak Xendit & beta selesai ±4 bulan.
A11: P002 | B11: Bulan biaya pra-peluncuran yang dibebankan di Bulan 0 | C11: bulan | D11: 3 | E11: 3 | F11: 3 | G11: =INDEX(D11:F11,$D$5) -> 3 | H11: ASUMSI | I11: SDM inti + infrastruktur beta (fase 0–1B launch plan) sebelum Bulan 1.
A12: P003 | B12: Kurs USD/IDR untuk biaya dalam USD | C12: Rp/USD | D12: 17917 | E12: 17917 | F12: 17917 | G12: =INDEX(D12:F12,$D$5) -> 17917 | H12: SUMBER | I12: JISDOR 25–27 Sep 2026 — docs/research/01-customs-tax-indonesia.md §4.
A13: P004 | B13: Lag penerimaan fee platform (0 = bulan yang sama, 1 = bulan berikutnya) | C13: bulan | D13: 1 | E13: 1 | F13: 1 | G13: =INDEX(D13:F13,$D$5) -> 1 | H13: ASUMSI | I13: Fee diambil saat release setelah BUYER_CONFIRMED (research 02 §5/§10; ledger COMPLETION_RELEASE di docs/04-payments-ledger.md). Siklus trip + serah terima ±2–5 minggu.
A14: 2. Konfigurasi harga platform — packages/core/src/config/business-config.defaults.json (v1)
A15: P005 | B15: Platform fee — tarif | C15: % nilai barang | D15: 0.05 | E15: 0.05 | F15: 0.05 | G15: =INDEX(D15:F15,$D$5) -> 0.05 | H15: SUMBER | I15: pricing.platform_fee.rateBps = 500.
A16: P006 | B16: Platform fee — minimum | C16: Rp | D16: 10000 | E16: 10000 | F16: 10000 | G16: =INDEX(D16:F16,$D$5) -> 10000 | H16: SUMBER | I16: pricing.platform_fee.minIdr.
A17: P007 | B17: Platform fee — maksimum | C17: Rp | D17: 750000 | E17: 750000 | F17: 750000 | G17: =INDEX(D17:F17,$D$5) -> 750000 | H17: SUMBER | I17: pricing.platform_fee.maxIdr.
A18: P008 | B18: JastipKita Protection — tarif | C18: % nilai barang | D18: 0.015 | E18: 0.015 | F18: 0.015 | G18: =INDEX(D18:F18,$D$5) -> 0.015 | H18: SUMBER | I18: pricing.protection_fee.rateBps = 150. Belum ada mitra asuransi (INSURANCE_PROVIDER=mock; launch-checklist L9).
A19: P009 | B19: Protection fee — minimum | C19: Rp | D19: 5000 | E19: 5000 | F19: 5000 | G19: =INDEX(D19:F19,$D$5) -> 5000 | H19: SUMBER | I19: pricing.protection_fee.minIdr.
A20: P010 | B20: Protection fee — maksimum | C20: Rp | D20: 300000 | E20: 300000 | F20: 300000 | G20: =INDEX(D20:F20,$D$5) -> 300000 | H20: SUMBER | I20: pricing.protection_fee.maxIdr.
A21: P011 | B21: PPN atas layanan — tarif | C21: % | D21: 0.12 | E21: 0.12 | F21: 0.12 | G21: =INDEX(D21:F21,$D$5) -> 0.12 | H21: SUMBER | I21: pricing.service_tax.rate (berlaku atas PLATFORM_FEE + PROTECTION_FEE).
A22: P012 | B22: PPN atas layanan — faktor DPP (11/12) | C22: faktor | D22: 0.916667 | E22: 0.916667 | F22: 0.916667 | G22: =INDEX(D22:F22,$D$5) -> 0.916667 | H22: SUMBER | I22: pricing.service_tax.dppFactor; PMK 131/2024.
A23: P013 | B23: PPN layanan dipungut? (1 = ya/PKP, 0 = tidak) | C23: 1/0 | D23: 1 | E23: 1 | F23: 1 | G23: =INDEX(D23:F23,$D$5) -> 1 | H23: SUMBER | I23: Config enabled=true. Hanya boleh dipungut bila PT sudah PKP (launch-checklist L8); wajib PKP bila omzet > Rp4,8 M/tahun (research 05 §4). Pass-through — tidak mengubah pendapatan bersih.
A24: P014 | B24: Traveler fee — minimum | C24: Rp | D24: 25000 | E24: 25000 | F24: 25000 | G24: =INDEX(D24:F24,$D$5) -> 25000 | H24: SUMBER | I24: pricing.traveler_fee_bounds.minIdr.
A25: P015 | B25: Traveler fee — maksimum (% nilai barang) | C25: % | D25: 0.3 | E25: 0.3 | F25: 0.3 | G25: =INDEX(D25:F25,$D$5) -> 0.3 | H25: SUMBER | I25: pricing.traveler_fee_bounds.maxRateBps = 3000.
A26: P016 | B26: Nilai barang minimum per transaksi | C26: Rp | D26: 100000 | E26: 100000 | F26: 100000 | G26: =INDEX(D26:F26,$D$5) -> 100000 | H26: SUMBER | I26: pricing.minimum_transaction.minItemValueIdr.
A27: P017 | B27: Markup kurs (informasi — BUKAN pendapatan) | C27: % | D27: 0.015 | E27: 0.015 | F27: 0.015 | G27: =INDEX(D27:F27,$D$5) -> 0.015 | H27: SUMBER | I27: pricing.fx_markup.defaultBps = 150 (KRW 200). Selisih dana barang dikembalikan ke pembeli saat COMPLETION_RELEASE (docs/04-payments-ledger.md §3) → tidak dihitung sebagai pendapatan.
A28: 3. Biaya pembayaran yang DIBEBANKAN ke pembeli — config pricing.payment_fees (bearer BUYER, gross-up di pricing/index.ts)
A29: P018 | B29: VA — biaya tetap dibebankan | C29: Rp | D29: 4500 | E29: 4500 | F29: 4500 | G29: =INDEX(D29:F29,$D$5) -> 4500 | H29: SUMBER | I29: pricing.payment_fees.channels.VA.fixedIdr (bertanda asumsi di config sampai kontrak Xendit).
A30: P019 | B30: VA — tarif persen dibebankan | C30: % | D30: 0 | E30: 0 | F30: 0 | G30: =INDEX(D30:F30,$D$5) -> 0 | H30: SUMBER | I30: VA.rateBps = 0.
A31: P020 | B31: QRIS — biaya tetap dibebankan | C31: Rp | D31: 0 | E31: 0 | F31: 0 | G31: =INDEX(D31:F31,$D$5) -> 0 | H31: SUMBER | I31: QRIS.fixedIdr = 0.
A32: P021 | B32: QRIS — tarif persen dibebankan | C32: % | D32: 0.007 | E32: 0.007 | F32: 0.007 | G32: =INDEX(D32:F32,$D$5) -> 0.007 | H32: SUMBER | I32: QRIS.rateBps = 70.
A33: P022 | B33: E-wallet — biaya tetap dibebankan | C33: Rp | D33: 0 | E33: 0 | F33: 0 | G33: =INDEX(D33:F33,$D$5) -> 0 | H33: SUMBER | I33: EWALLET.fixedIdr = 0.
A34: P023 | B34: E-wallet — tarif persen dibebankan | C34: % | D34: 0.015 | E34: 0.015 | F34: 0.015 | G34: =INDEX(D34:F34,$D$5) -> 0.015 | H34: SUMBER | I34: EWALLET.rateBps = 150.
A35: P024 | B35: Kartu — biaya tetap dibebankan | C35: Rp | D35: 2000 | E35: 2000 | F35: 2000 | G35: =INDEX(D35:F35,$D$5) -> 2000 | H35: SUMBER | I35: CARD.fixedIdr = 2000.
A36: P025 | B36: Kartu — tarif persen dibebankan | C36: % | D36: 0.029 | E36: 0.029 | F36: 0.029 | G36: =INDEX(D36:F36,$D$5) -> 0.029 | H36: SUMBER | I36: CARD.rateBps = 290.
A37: 4. Biaya Xendit — tarif publik (bukan kontrak). research 02 §8 (2026-09-27) + xendit.co/en-id/pricing diverifikasi ulang 2026-10-04
A38: P026 | B38: VA — fee metode | C38: Rp | D38: 9000 | E38: 9000 | F38: 9000 | G38: =INDEX(D38:F38,$D$5) -> 9000 | H38: SUMBER | I38: Xendit pricing: VA Rp9.000 + processing Rp4.000 (exclusive of taxes).
A39: P027 | B39: Processing fee Xendit per transaksi (semua metode & payout) | C39: Rp | D39: 4000 | E39: 4000 | F39: 4000 | G39: =INDEX(D39:F39,$D$5) -> 4000 | H39: SUMBER | I39: Xendit pricing (2026-10-04).
A40: P028 | B40: QRIS — fee metode (sudah termasuk PPN) | C40: % | D40: 0.007 | E40: 0.007 | F40: 0.007 | G40: =INDEX(D40:F40,$D$5) -> 0.007 | H40: SUMBER | I40: Xendit pricing: 0,70% inclusive of VAT + Rp4.000.
A41: P029 | B41: E-wallet — fee metode (rata-rata tertimbang) | C41: % | D41: 0.035 | E41: 0.03 | F41: 0.025 | G41: =INDEX(D41:F41,$D$5) -> 0.03 | H41: ASUMSI | I41: Dalam rentang publik: OVO 3,00–5,50%, DANA 2,00–3,50% (berubah dari 3,00–3,50% di research 02), ShopeePay 2,50–3,60%, GoPay 3,00–5,00% + Rp4.000.
A42: P030 | B42: Kartu — fee persen | C42: % | D42: 0.029 | E42: 0.029 | F42: 0.029 | G42: =INDEX(D42:F42,$D$5) -> 0.029 | H42: SUMBER | I42: Visa/MC/JCB 2,90% + Rp2.000 + Rp4.000.
A43: P031 | B43: Kartu — fee tetap | C43: Rp | D43: 2000 | E43: 2000 | F43: 2000 | G43: =INDEX(D43:F43,$D$5) -> 2000 | H43: SUMBER | I43: Xendit pricing.
A44: P032 | B44: PPN atas fee Xendit (efektif) | C44: % | D44: 0.11 | E44: 0.11 | F44: 0.11 | G44: =INDEX(D44:F44,$D$5) -> 0.11 | H44: SUMBER | I44: Tarif Xendit 'exclusive of taxes'; 12% × DPP 11/12 = 11% (contoh hitung research 02 §8). Diperlakukan sebagai biaya (asumsi: pajak masukan tidak dikreditkan).
A45: P033 | B45: Payout ke traveler/refund — komponen tetap | C45: Rp | D45: 4000 | E45: 4500 | F45: 4500 | G45: =INDEX(D45:F45,$D$5) -> 4500 | H45: ASUMSI | I45: Konservatif = tarif publik (processing Rp4.000 + 1%, min Rp2.500; NEEDS_VERIFICATION). Dasar/Optimis = launch-plan §4 ASUMSI ±Rp5.000 termasuk PPN.
A46: P034 | B46: Payout — komponen persen atas nilai yang dibayarkan | C46: % | D46: 0.01 | E46: 0 | F46: 0 | G46: =INDEX(D46:F46,$D$5) -> 0 | H46: ASUMSI | I46: Publik: 1,00% (min Rp2.500) — struktur tidak lazim, NEEDS_VERIFICATION (research 02 §8). Config money.policy.payoutFeeIdr = 0 → ditanggung platform.
A47: P035 | B47: Payout — minimum komponen persen | C47: Rp | D47: 2500 | E47: 2500 | F47: 2500 | G47: =INDEX(D47:F47,$D$5) -> 2500 | H47: SUMBER | I47: Xendit pricing (2026-10-04).
A48: P036 | B48: Batas nominal QRIS per transaksi | C48: Rp | D48: 10000000 | E48: 10000000 | F48: 10000000 | G48: =INDEX(D48:F48,$D$5) -> 10000000 | H48: SUMBER | I48: research 02 §1.3 (docs.xendit.co/docs/qris.md).
A49: P037 | B49: Biaya chargeback kartu | C49: USD | D49: 25 | E49: 25 | F49: 25 | G49: =INDEX(D49:F49,$D$5) -> 25 | H49: SUMBER | I49: research 02 §8.
A50: P038 | B50: Tingkat chargeback (porsi transaksi kartu) | C50: % | D50: 0.01 | E50: 0.005 | F50: 0.003 | G50: =INDEX(D50:F50,$D$5) -> 0.005 | H50: ASUMSI | I50: Tidak ada data; tinjau setelah 90 hari.
A51: 5. Bauran kanal pembayaran (ASUMSI — tidak ada data; total harus 100%)
A52: P039 | B52: Porsi Virtual Account | C52: % | D52: 0.6 | E52: 0.5 | F52: 0.4 | G52: =INDEX(D52:F52,$D$5) -> 0.5 | H52: ASUMSI | I52: VA termurah untuk tiket besar tetapi tidak bisa refund (research 02 §4/§8).
A53: P040 | B53: Porsi QRIS | C53: % | D53: 0.2 | E53: 0.25 | F53: 0.3 | G53: =INDEX(D53:F53,$D$5) -> 0.25 | H53: ASUMSI | I53: QRIS maks Rp10 jt/transaksi.
A54: P041 | B54: Porsi e-wallet | C54: % | D54: 0.12 | E54: 0.15 | F54: 0.18 | G54: =INDEX(D54:F54,$D$5) -> 0.15 | H54: ASUMSI
A55: P042 | B55: Porsi kartu | C55: % | D55: 0.08 | E55: 0.1 | F55: 0.12 | G55: =INDEX(D55:F55,$D$5) -> 0.1 | H55: ASUMSI
A56: P043 | B56: Cek: total bauran | C56: % | D56: =SUM(D52:D55) -> 1 | E56: =SUM(E52:E55) -> 1 | F56: =SUM(F52:F55) -> 1 | G56: =INDEX(D56:F56,$D$5) -> 1 | H56: CEK | I56: Harus 100%.
A57: 6. Transaksi representatif & pajak impor (pass-through)
A58: P044 | B58: Rata-rata nilai barang per transaksi (sudah dalam IDR kurs quote) | C58: Rp | D58: 1500000 | E58: 2000000 | F58: 2500000 | G58: =INDEX(D58:F58,$D$5) -> 2000000 | H58: ASUMSI | I58: Tidak ada data pasar kredibel (research 04). launch-plan §4 memakai Rp1 jt / 2,5 jt / 5 jt sebagai ilustrasi; skincare/snack rendah, fashion/elektronik tinggi.
A59: P045 | B59: Traveler fee (% nilai barang) | C59: % | D59: 0.1 | E59: 0.1 | F59: 0.1 | G59: =INDEX(D59:F59,$D$5) -> 0.1 | H59: ASUMSI | I59: launch-plan §4; research 04 §1.2: lazim 5–15%. Dibatasi config min Rp25.000 & maks 30%.
A60: P046 | B60: Bea masuk barang jastip (non-pribadi) | C60: % | D60: 0.1 | E60: 0.1 | F60: 0.1 | G60: =INDEX(D60:F60,$D$5) -> 0.1 | H60: SUMBER | I60: PMK 34/2025 Pasal 24(3): 10% flat atas seluruh nilai pabean, tanpa pembebasan USD 500; seed 0100 ID_PAX_NON_PERSONAL v1 (DRAFT sampai diverifikasi konsultan — L7).
A61: P047 | B61: PPN impor — tarif | C61: % | D61: 0.12 | E61: 0.12 | F61: 0.12 | G61: =INDEX(D61:F61,$D$5) -> 0.12 | H61: SUMBER | I61: PMK 131/2024 Pasal 3 (non-mewah).
A62: P048 | B62: PPN impor — faktor DPP | C62: faktor | D62: 0.916667 | E62: 0.916667 | F62: 0.916667 | G62: =INDEX(D62:F62,$D$5) -> 0.916667 | H62: SUMBER | I62: Seed 0100 vat_dpp_factor (11/12).
A63: P049 | B63: PPh 22 impor (dengan NPWP) | C63: % | D63: 0.05 | E63: 0.05 | F63: 0.05 | G63: =INDEX(D63:F63,$D$5) -> 0.05 | H63: SUMBER | I63: PMK 34/2025 Pasal 24(3). Tanpa NPWP 10% = NEEDS_VERIFICATION (research 01 §3.3). Pembulatan CEIL_1000 semua komponen (seed).
A64: 7. Biaya variabel & promo (ASUMSI)
A65: P050 | B65: Transaksi batal setelah bayar (porsi transaksi dibayar) | C65: % | D65: 0.08 | E65: 0.05 | F65: 0.04 | G65: =INDEX(D65:F65,$D$5) -> 0.05 | H65: ASUMSI | I65: launch-plan §4: 5%; gerbang soft launch refund rate < 8%. Transaksi batal = pendapatan 0, biaya Xendit hangus + refund.
A66: P051 | B66: Loss ratio klaim JastipKita Protection | C66: % protection fee | D66: 0.6 | E66: 0.4 | F66: 0.3 | G66: =INDEX(D66:F66,$D$5) -> 0.4 | H66: ASUMSI | I66: launch-plan §4: 40%. Tanpa data klaim; mitra asuransi belum ada (L9).
A67: P052 | B67: CS & operasional per transaksi selesai | C67: Rp | D67: 12500 | E67: 10000 | F67: 8000 | G67: =INDEX(D67:F67,$D$5) -> 10000 | H67: ASUMSI | I67: launch-plan §4: Rp10.000. Menutup agen CS tambahan di atas tim inti.
A68: P053 | B68: Porsi transaksi dengan platform fee gratis — Bulan 1–6 | C68: % | D68: 0.15 | E68: 0.12 | F68: 0.1 | G68: =INDEX(D68:F68,$D$5) -> 0.12 | H68: ASUMSI | I68: Program 'Jastiper Pro': promo platform fee 3 transaksi pertama (launch-plan §2). Kontra-pendapatan.
A69: P054 | B69: Porsi transaksi dengan platform fee gratis — Bulan 7–24 | C69: % | D69: 0.05 | E69: 0.04 | F69: 0.03 | G69: =INDEX(D69:F69,$D$5) -> 0.04 | H69: ASUMSI | I69: Idem, setelah gelombang awal.
A70: P055 | B70: Harga SMS OTP ke Indonesia | C70: USD/SMS | D70: 0.4414 | E70: 0.4414 | F70: 0.4414 | G70: =INDEX(D70:F70,$D$5) -> 0.4414 | H70: SUMBER | I70: twilio.com/en-us/sms/pricing/id (diakses 2026-10-04). OTP masih MOCK (STATUS §2).
A71: P056 | B71: SMS OTP per pembeli baru bertransaksi | C71: SMS | D71: 3 | E71: 2 | F71: 1.5 | G71: =INDEX(D71:F71,$D$5) -> 2 | H71: ASUMSI | I71: Verifikasi HP (KYC 2) wajib sebelum checkout + kirim ulang + pendaftar yang tidak bertransaksi. Kanal WhatsApp/e-mail bisa lebih murah.
A72: P057 | B72: Biaya e-KYC per traveler baru | C72: Rp | D72: 10000 | E72: 10000 | F72: 10000 | G72: =INDEX(D72:F72,$D$5) -> 10000 | H72: ASUMSI | I72: Vendor e-KYC belum dipilih (STATUS §2); saat ini review manual.
A73: 8. Pasokan traveler (ASUMSI — kendala utama marketplace; launch-plan §2)
A74: P058 | B74: Traveler terverifikasi saat Bulan 0 (peserta beta) | C74: orang | D74: 20 | E74: 20 | F74: 20 | G74: =INDEX(D74:F74,$D$5) -> 20 | H74: ASUMSI | I74: launch-plan fase 1A: 20 traveler (JP, SG).
A75: P059 | B75: Traveler terverifikasi baru — Bulan 1 | C75: orang/bulan | D75: 10 | E75: 15 | F75: 25 | G75: =INDEX(D75:F75,$D$5) -> 15 | H75: ASUMSI | I75: PPI, diaspora, Jastiper Pro (launch-plan §2); target 60 traveler aktif di minggu 10.
A76: P060 | B76: Pertumbuhan traveler baru per bulan | C76: %/bulan | D76: 0.04 | E76: 0.08 | F76: 0.12 | G76: =INDEX(D76:F76,$D$5) -> 0.08 | H76: ASUMSI
A77: P061 | B77: Churn basis traveler per bulan | C77: %/bulan | D77: 0.05 | E77: 0.04 | F77: 0.03 | G77: =INDEX(D77:F77,$D$5) -> 0.04 | H77: ASUMSI
A78: P062 | B78: Porsi traveler yang punya trip aktif dalam sebulan | C78: % | D78: 0.3 | E78: 0.35 | F78: 0.4 | G78: =INDEX(D78:F78,$D$5) -> 0.35 | H78: ASUMSI | I78: Pasokan musiman (launch-plan §11).
A79: P063 | B79: Pesanan per traveler aktif per bulan | C79: pesanan | D79: 2.5 | E79: 3 | F79: 4 | G79: =INDEX(D79:F79,$D$5) -> 3 | H79: ASUMSI | I79: launch-plan: ≥150 transaksi selesai di soft launch dengan ±60 traveler aktif → ±2,5.
A80: 9. Permintaan pembeli (ASUMSI)
A81: P064 | B81: Basis pembeli saat Bulan 0 (peserta beta) | C81: orang | D81: 50 | E81: 50 | F81: 50 | G81: =INDEX(D81:F81,$D$5) -> 50 | H81: ASUMSI | I81: launch-plan fase 1A: 50 penitip undangan.
A82: P065 | B82: Pembeli baru organik — Bulan 1 | C82: orang/bulan | D82: 20 | E82: 30 | F82: 40 | G82: =INDEX(D82:F82,$D$5) -> 30 | H82: ASUMSI | I82: launch-plan §10 (anggaran Rp0): 20–40 pembeli baru bertransaksi/bulan.
A83: P066 | B83: Pertumbuhan pembeli organik per bulan (SEO, konten, word of mouth) | C83: %/bulan | D83: 0.05 | E83: 0.08 | F83: 0.11 | G83: =INDEX(D83:F83,$D$5) -> 0.08 | H83: ASUMSI
A84: P067 | B84: Anggaran marketing kas — Bulan 1–3 | C84: Rp/bulan | D84: 5000000 | E84: 5000000 | F84: 5000000 | G84: =INDEX(D84:F84,$D$5) -> 5000000 | H84: USULAN | I84: launch-plan §10 skenario Rp5 juta (perlu persetujuan owner). Sama di semua skenario.
A85: P068 | B85: Anggaran marketing kas — Bulan 4–12 | C85: Rp/bulan | D85: 25000000 | E85: 25000000 | F85: 25000000 | G85: =INDEX(D85:F85,$D$5) -> 25000000 | H85: USULAN | I85: launch-plan §10 skenario Rp25 juta; iklan berbayar hanya setelah prasyarat atribusi §7.
A86: P069 | B86: Anggaran marketing kas — Bulan 13–24 | C86: Rp/bulan | D86: 35000000 | E86: 35000000 | F86: 35000000 | G86: =INDEX(D86:F86,$D$5) -> 35000000 | H86: ASUMSI | I86: Tidak ada di launch plan; ditetapkan untuk Tahun 2.
A87: P070 | B87: CAC blended per pembeli baru dari marketing | C87: Rp | D87: 350000 | E87: 250000 | F87: 180000 | G87: =INDEX(D87:F87,$D$5) -> 250000 | H87: ASUMSI | I87: Turunan launch-plan §10: Rp5 jt → +20–40 pembeli (Rp125–250 rb); Rp25 jt → +60–110 (Rp227–417 rb); iklan berbayar ±Rp266.667 (§6).
A88: P071 | B88: Churn basis pembeli per bulan | C88: %/bulan | D88: 0.1 | E88: 0.08 | F88: 0.06 | G88: =INDEX(D88:F88,$D$5) -> 0.08 | H88: ASUMSI
A89: P072 | B89: Peluang pembeli retensi bertransaksi lagi dalam sebulan | C89: %/bulan | D89: 0.08 | E89: 0.1 | F89: 0.12 | G89: =INDEX(D89:F89,$D$5) -> 0.1 | H89: ASUMSI | I89: Setara ±1,5 / 1,7 / 1,9 transaksi per pembeli baru dalam 12 bulan (launch-plan LTV: 2 transaksi/tahun).
A90: 10. Referral — config referral.buyer / referral.traveler + ASUMSI pemakaian
A91: P073 | B91: Credit perujuk (pembeli) | C91: Rp | D91: 25000 | E91: 25000 | F91: 25000 | G91: =INDEX(D91:F91,$D$5) -> 25000 | H91: SUMBER | I91: referral.buyer.referrerCreditIdr; tidak bisa dicairkan, berlaku 90 hari.
A92: P074 | B92: Credit teman yang dirujuk | C92: Rp | D92: 25000 | E92: 25000 | F92: 25000 | G92: =INDEX(D92:F92,$D$5) -> 25000 | H92: SUMBER | I92: referral.buyer.refereeCreditIdr.
A93: P075 | B93: Syarat transaksi pertama teman (informasi) | C93: Rp | D93: 500000 | E93: 500000 | F93: 500000 | G93: =INDEX(D93:F93,$D$5) -> 500000 | H93: SUMBER | I93: referral.buyer.minFirstTransactionIdr; status COMPLETED.
A94: P076 | B94: Cap credit per perujuk per bulan | C94: Rp | D94: 250000 | E94: 250000 | F94: 250000 | G94: =INDEX(D94:F94,$D$5) -> 250000 | H94: SUMBER | I94: referral.buyer.monthlyCapIdr (dan referral.traveler.monthlyCapIdr).
A95: P077 | B95: Pembeli baru via referral per pembeli retensi per bulan | C95: % | D95: 0.015 | E95: 0.025 | F95: 0.035 | G95: =INDEX(D95:F95,$D$5) -> 0.025 | H95: ASUMSI
A96: P078 | B96: Porsi referral yang memenuhi syarat (≥ Rp500 rb & COMPLETED) | C96: % | D96: 0.65 | E96: 0.75 | F96: 0.8 | G96: =INDEX(D96:F96,$D$5) -> 0.75 | H96: ASUMSI | I96: Hanya referral berkualifikasi yang memicu credit.
A97: P079 | B97: Tingkat pemakaian credit pembeli | C97: % | D97: 0.7 | E97: 0.7 | F97: 0.7 | G97: =INDEX(D97:F97,$D$5) -> 0.7 | H97: ASUMSI | I97: launch-plan §5.
A98: P080 | B98: Referral berkualifikasi per perujuk aktif per bulan | C98: referral | D98: 1.2 | E98: 1.2 | F98: 1.2 | G98: =INDEX(D98:F98,$D$5) -> 1.2 | H98: ASUMSI | I98: Dipakai menegakkan cap per perujuk (cap/credit = 10 referral/bulan).
A99: P081 | B99: Credit perujuk traveler | C99: Rp | D99: 50000 | E99: 50000 | F99: 50000 | G99: =INDEX(D99:F99,$D$5) -> 50000 | H99: SUMBER | I99: referral.traveler.referrerCreditIdr; setelah traveler baru menyelesaikan 2 transaksi.
A100: P082 | B100: Porsi traveler baru yang datang via referral | C100: % | D100: 0.2 | E100: 0.3 | F100: 0.4 | G100: =INDEX(D100:F100,$D$5) -> 0.3 | H100: ASUMSI
A101: P083 | B101: Porsi traveler referral yang mencapai 2 transaksi selesai | C101: % | D101: 0.6 | E101: 0.6 | F101: 0.6 | G101: =INDEX(D101:F101,$D$5) -> 0.6 | H101: ASUMSI | I101: referral.traveler.requiredCompletedTransactions = 2.
A102: P084 | B102: Tingkat pemakaian credit traveler | C102: % | D102: 0.5 | E102: 0.5 | F102: 0.5 | G102: =INDEX(D102:F102,$D$5) -> 0.5 | H102: ASUMSI | I102: Credit tidak bisa dicairkan; dipakai bila traveler juga menitip.
...

Sheet Unit Economics
A1: Unit Economics — satu transaksi melalui 11 baris harga
A2: Kolom C–E: transaksi representatif tiap skenario (asumsi skenario masing-masing). Kolom F–H: tiga ukuran keranjang dengan asumsi skenario aktif. Rumus mengikuti packages/core/src/pricing (clamp, gross-up kanal bayar, PPN DPP 11/12, CEIL_1000 bea).
A3: ="Skenario aktif: "&Asumsi!$D$4 -> Skenario aktif: Dasar
B4: Baris / komponen | C4: Konservatif (rep.) | D4: Dasar (rep.) | E4: Optimis (rep.) | F4: Aktif — Rp1 jt | G4: Aktif — Rp2,5 jt | H4: Aktif — Rp5 jt | I4: Bucket ledger | J4: Sifat bagi platform / catatan
B5: Indeks skenario (1 K · 2 D · 3 O) | C5: 1 | D5: 2 | E5: 3 | F5: =Asumsi!$D$5 -> 2 | G5: =Asumsi!$D$5 -> 2 | H5: =Asumsi!$D$5 -> 2
B6: Nilai barang (Rp) | C6: =INDEX(Asumsi!$D$58:$F$58,C$5) -> 1500000 | D6: =INDEX(Asumsi!$D$58:$F$58,D$5) -> 2000000 | E6: =INDEX(Asumsi!$D$58:$F$58,E$5) -> 2500000 | F6: 1000000 | G6: 2500000 | H6: 5000000
A7: A. Rincian 11 baris harga per transaksi (dibayar pembeli) — urutan docs/00-domain-model.md §10
B8: 1. ITEM_PRICE — Harga Barang | C8: =C6 -> 1500000 | D8: =D6 -> 2000000 | E8: =E6 -> 2500000 | F8: =F6 -> 1000000 | G8: =G6 -> 2500000 | H8: =H6 -> 5000000 | I8: PRODUCT_FUND | J8: Pass-through → traveler (penggantian harga beli)
B9: 2. TRAVELER_FEE — Traveler Fee | C9: =MAX(C81,MIN(ROUND(C8*C80,0),ROUNDDOWN(C8*C82,0))) -> 150000 | D9: =MAX(D81,MIN(ROUND(D8*D80,0),ROUNDDOWN(D8*D82,0))) -> 200000 | E9: =MAX(E81,MIN(ROUND(E8*E80,0),ROUNDDOWN(E8*E82,0))) -> 250000 | F9: =MAX(F81,MIN(ROUND(F8*F80,0),ROUNDDOWN(F8*F82,0))) -> 100000 | G9: =MAX(G81,MIN(ROUND(G8*G80,0),ROUNDDOWN(G8*G82,0))) -> 250000 | H9: =MAX(H81,MIN(ROUND(H8*H80,0),ROUNDDOWN(H8*H82,0))) -> 500000 | I9: TRAVELER_EARNING | J9: Pass-through → penghasilan traveler
B10: 3. CUSTOMS_DUTY — Bea Masuk (estimasi) | C10: =CEILING(C8*C83,1000) -> 150000 | D10: =CEILING(D8*D83,1000) -> 200000 | E10: =CEILING(E8*E83,1000) -> 250000 | F10: =CEILING(F8*F83,1000) -> 100000 | G10: =CEILING(G8*G83,1000) -> 250000 | H10: =CEILING(H8*H83,1000) -> 500000 | I10: CUSTOMS_RESERVE | J10: Pass-through → DJBC (dibayar traveler)
B11: 4. IMPORT_TAX — PPN impor + PPh 22 (estimasi) | C11: =CEILING((C8+C10)*C84*C85,1000)+CEILING((C8+C10)*C86,1000) -> 265000 | D11: =CEILING((D8+D10)*D84*D85,1000)+CEILING((D8+D10)*D86,1000) -> 353000 | E11: =CEILING((E8+E10)*E84*E85,1000)+CEILING((E8+E10)*E86,1000) -> 441000 | F11: =CEILING((F8+F10)*F84*F85,1000)+CEILING((F8+F10)*F86,1000) -> 177000 | G11: =CEILING((G8+G10)*G84*G85,1000)+CEILING((G8+G10)*G86,1000) -> 441000 | H11: =CEILING((H8+H10)*H84*H85,1000)+CEILING((H8+H10)*H86,1000) -> 881000 | I11: CUSTOMS_RESERVE | J11: Pass-through → DJBC (dibayar traveler)
B12: 5. PROTECTION_FEE — JastipKita Protection | C12: =MIN(C89,MAX(C88,ROUND(C8*C87,0))) -> 22500 | D12: =MIN(D89,MAX(D88,ROUND(D8*D87,0))) -> 30000 | E12: =MIN(E89,MAX(E88,ROUND(E8*E87,0))) -> 37500 | F12: =MIN(F89,MAX(F88,ROUND(F8*F87,0))) -> 15000 | G12: =MIN(G89,MAX(G88,ROUND(G8*G87,0))) -> 37500 | H12: =MIN(H89,MAX(H88,ROUND(H8*H87,0))) -> 75000 | I12: PLATFORM_REVENUE | J12: Pendapatan platform (menanggung klaim)
B13: 6. PLATFORM_FEE — Platform Fee | C13: =MIN(C92,MAX(C91,ROUND(C8*C90,0))) -> 75000 | D13: =MIN(D92,MAX(D91,ROUND(D8*D90,0))) -> 100000 | E13: =MIN(E92,MAX(E91,ROUND(E8*E90,0))) -> 125000 | F13: =MIN(F92,MAX(F91,ROUND(F8*F90,0))) -> 50000 | G13: =MIN(G92,MAX(G91,ROUND(G8*G90,0))) -> 125000 | H13: =MIN(H92,MAX(H91,ROUND(H8*H90,0))) -> 250000 | I13: PLATFORM_REVENUE | J13: Pendapatan platform
B14: 7. SERVICE_TAX — PPN atas layanan | C14: =C95*ROUND((C12+C13)*C94*C93,0) -> 10725 | D14: =D95*ROUND((D12+D13)*D94*D93,0) -> 14300 | E14: =E95*ROUND((E12+E13)*E94*E93,0) -> 17875 | F14: =F95*ROUND((F12+F13)*F94*F93,0) -> 7150 | G14: =G95*ROUND((G12+G13)*G94*G93,0) -> 17875 | H14: =H95*ROUND((H12+H13)*H94*H93,0) -> 35750 | I14: TAX_PAYABLE | J14: Pass-through → kas negara (hanya bila PKP)
B15: 8. PAYMENT_FEE — rata-rata tertimbang bauran kanal | C15: =C33 -> 15092.68 | D15: =D33 -> 22833.65 | E15: =E33 -> 32611.38 | F15: =F33 -> 12648.45 | G15: =G33 -> 27926.15 | H15: =H33 -> 53388.95 | I15: PAYMENT_FEE | J15: Pass-through → Xendit (kekurangan disubsidi platform)
B16: 9. DISCOUNT — Diskon promo (negatif) | C16: 0 | D16: 0 | E16: 0 | F16: 0 | G16: 0 | H16: 0 | I16: PROMOTION_CREDIT | J16: Transaksi representatif tanpa promo; promo dihitung teramortisasi di bagian C
B17: 10. REFERRAL_CREDIT — JastipKita Credit (negatif) | C17: 0 | D17: 0 | E17: 0 | F17: 0 | G17: 0 | H17: 0 | I17: PROMOTION_CREDIT | J17: Idem — credit referral teramortisasi di bagian C
B18: 11. TOTAL — Total Landed Cost (= GMV per transaksi) | C18: =SUM(C8:C14)+C15+C16+C17 -> 2188317.7 | D18: =SUM(D8:D14)+D15+D16+D17 -> 2920133.6 | E18: =SUM(E8:E14)+E15+E16+E17 -> 3653986.4 | F18: =SUM(F8:F14)+F15+F16+F17 -> 1461798.4 | G18: =SUM(G8:G14)+G15+G16+G17 -> 3649301.1 | H18: =SUM(H8:H14)+H15+H16+H17 -> 7295139 | I18: — | J18: Kas dibayar pembeli
A19: A2. Biaya kanal pembayaran — dibebankan ke pembeli (config) vs biaya Xendit (tarif publik); lihat launch-checklist B4
B20: Dasar sebelum biaya bayar (P = baris 1–7 + 9 + 10) | C20: =SUM(C8:C14)+C16+C17 -> 2173225 | D20: =SUM(D8:D14)+D16+D17 -> 2897300 | E20: =SUM(E8:E14)+E16+E17 -> 3621375 | F20: =SUM(F8:F14)+F16+F17 -> 1449150 | G20: =SUM(G8:G14)+G16+G17 -> 3621375 | H20: =SUM(H8:H14)+H16+H17 -> 7241750
B21: VA — dibebankan ke pembeli | C21: =IF(C20>0,ROUNDUP(ROUND((C20+C96)/(1-C97),6),0)-C20,0) -> 4500 | D21: =IF(D20>0,ROUNDUP(ROUND((D20+D96)/(1-D97),6),0)-D20,0) -> 4500 | E21: =IF(E20>0,ROUNDUP(ROUND((E20+E96)/(1-E97),6),0)-E20,0) -> 4500 | F21: =IF(F20>0,ROUNDUP(ROUND((F20+F96)/(1-F97),6),0)-F20,0) -> 4500 | G21: =IF(G20>0,ROUNDUP(ROUND((G20+G96)/(1-G97),6),0)-G20,0) -> 4500 | H21: =IF(H20>0,ROUNDUP(ROUND((H20+H96)/(1-H97),6),0)-H20,0) -> 4500 | J21: config VA Rp4.500
B22: VA — biaya Xendit ((Rp9.000 + Rp4.000) × 1,11) | C22: =ROUND((C104+C105)*(1+C110),0) -> 14430 | D22: =ROUND((D104+D105)*(1+D110),0) -> 14430 | E22: =ROUND((E104+E105)*(1+E110),0) -> 14430 | F22: =ROUND((F104+F105)*(1+F110),0) -> 14430 | G22: =ROUND((G104+G105)*(1+G110),0) -> 14430 | H22: =ROUND((H104+H105)*(1+H110),0) -> 14430 | J22: tarif publik
B23: VA — subsidi platform | C23: =C22-C21 -> 9930 | D23: =D22-D21 -> 9930 | E23: =E22-E21 -> 9930 | F23: =F22-F21 -> 9930 | G23: =G22-G21 -> 9930 | H23: =H22-H21 -> 9930 | J23: B4: ±Rp9.930
B24: QRIS — dibebankan ke pembeli | C24: =IF(C20>0,ROUNDUP(ROUND((C20+C98)/(1-C99),6),0)-C20,0) -> 15320 | D24: =IF(D20>0,ROUNDUP(ROUND((D20+D98)/(1-D99),6),0)-D20,0) -> 20425 | E24: =IF(E20>0,ROUNDUP(ROUND((E20+E98)/(1-E99),6),0)-E20,0) -> 25529 | F24: =IF(F20>0,ROUNDUP(ROUND((F20+F98)/(1-F99),6),0)-F20,0) -> 10216 | G24: =IF(G20>0,ROUNDUP(ROUND((G20+G98)/(1-G99),6),0)-G20,0) -> 25529 | H24: =IF(H20>0,ROUNDUP(ROUND((H20+H98)/(1-H99),6),0)-H20,0) -> 51050 | J24: config 0,70% gross-up
B25: QRIS — biaya Xendit (0,70% incl. PPN + Rp4.000 × 1,11) | C25: =ROUND((C20+C24)*C106+C105*(1+C110),0) -> 19760 | D25: =ROUND((D20+D24)*D106+D105*(1+D110),0) -> 24864 | E25: =ROUND((E20+E24)*E106+E105*(1+E110),0) -> 29968 | F25: =ROUND((F20+F24)*F106+F105*(1+F110),0) -> 14656 | G25: =ROUND((G20+G24)*G106+G105*(1+G110),0) -> 29968 | H25: =ROUND((H20+H24)*H106+H105*(1+H110),0) -> 55490
B26: QRIS — subsidi platform | C26: =C25-C24 -> 4440 | D26: =D25-D24 -> 4439 | E26: =E25-E24 -> 4439 | F26: =F25-F24 -> 4440 | G26: =G25-G24 -> 4439 | H26: =H25-H24 -> 4440
B27: E-wallet — dibebankan ke pembeli | C27: =IF(C20>0,ROUNDUP(ROUND((C20+C100)/(1-C101),6),0)-C20,0) -> 33095 | D27: =IF(D20>0,ROUNDUP(ROUND((D20+D100)/(1-D101),6),0)-D20,0) -> 44122 | E27: =IF(E20>0,ROUNDUP(ROUND((E20+E100)/(1-E101),6),0)-E20,0) -> 55148 | F27: =IF(F20>0,ROUNDUP(ROUND((F20+F100)/(1-F101),6),0)-F20,0) -> 22069 | G27: =IF(G20>0,ROUNDUP(ROUND((G20+G100)/(1-G101),6),0)-G20,0) -> 55148 | H27: =IF(H20>0,ROUNDUP(ROUND((H20+H100)/(1-H101),6),0)-H20,0) -> 110281 | J27: config 1,50% gross-up
B28: E-wallet — biaya Xendit ((tarif × TOTAL + Rp4.000) × 1,11) | C28: =ROUND(((C20+C27)*C107+C105)*(1+C110),0) -> 90156 | D28: =ROUND(((D20+D27)*D107+D105)*(1+D110),0) -> 102389 | E28: =ROUND(((E20+E27)*E107+E105)*(1+E110),0) -> 106464 | F28: =ROUND(((F20+F27)*F107+F105)*(1+F110),0) -> 53432 | G28: =ROUND(((G20+G27)*G107+G105)*(1+G110),0) -> 126868 | H28: =ROUND(((H20+H27)*H107+H105)*(1+H110),0) -> 249263
B29: E-wallet — subsidi platform | C29: =C28-C27 -> 57061 | D29: =D28-D27 -> 58267 | E29: =E28-E27 -> 51316 | F29: =F28-F27 -> 31363 | G29: =G28-G27 -> 71720 | H29: =H28-H27 -> 138982
B30: Kartu — dibebankan ke pembeli | C30: =IF(C20>0,ROUNDUP(ROUND((C20+C102)/(1-C103),6),0)-C20,0) -> 66966 | D30: =IF(D20>0,ROUNDUP(ROUND((D20+D102)/(1-D103),6),0)-D20,0) -> 88591 | E30: =IF(E20>0,ROUNDUP(ROUND((E20+E102)/(1-E103),6),0)-E20,0) -> 110217 | F30: =IF(F20>0,ROUNDUP(ROUND((F20+F102)/(1-F103),6),0)-F20,0) -> 45341 | G30: =IF(G20>0,ROUNDUP(ROUND((G20+G102)/(1-G103),6),0)-G20,0) -> 110217 | H30: =IF(H20>0,ROUNDUP(ROUND((H20+H102)/(1-H103),6),0)-H20,0) -> 218343 | J30: config Rp2.000 + 2,90% gross-up
B31: Kartu — biaya Xendit ((2,90% × TOTAL + Rp2.000 + Rp4.000) × 1,11) | C31: =ROUND(((C20+C30)*C108+C109+C105)*(1+C110),0) -> 78772 | D31: =ROUND(((D20+D30)*D108+D109+D105)*(1+D110),0) -> 102776 | E31: =ROUND(((E20+E30)*E108+E109+E105)*(1+E110),0) -> 126780 | F31: =ROUND(((F20+F30)*F108+F109+F105)*(1+F110),0) -> 54768 | G31: =ROUND(((G20+G30)*G108+G109+G105)*(1+G110),0) -> 126780 | H31: =ROUND(((H20+H30)*H108+H109+H105)*(1+H110),0) -> 246800
B32: Kartu — subsidi platform | C32: =C31-C30 -> 11806 | D32: =D31-D30 -> 14185 | E32: =E31-E30 -> 16563 | F32: =F31-F30 -> 9427 | G32: =G31-G30 -> 16563 | H32: =H31-H30 -> 28457
B33: Rata-rata dibebankan ke pembeli (bauran) | C33: =C114*C21+C115*C24+C116*C27+C117*C30 -> 15092.68 | D33: =D114*D21+D115*D24+D116*D27+D117*D30 -> 22833.65 | E33: =E114*E21+E115*E24+E116*E27+E117*E30 -> 32611.38 | F33: =F114*F21+F115*F24+F116*F27+F117*F30 -> 12648.45 | G33: =G114*G21+G115*G24+G116*G27+G117*G30 -> 27926.15 | H33: =H114*H21+H115*H24+H116*H27+H117*H30 -> 53388.95
B34: Rata-rata biaya Xendit (bauran) | C34: =C114*C22+C115*C25+C116*C28+C117*C31 -> 29730.48 | D34: =D114*D22+D115*D25+D116*D28+D117*D31 -> 39066.95 | E34: =E114*E22+E115*E25+E116*E28+E117*E31 -> 49139.52 | F34: =F114*F22+F115*F25+F116*F28+F117*F31 -> 24370.6 | G34: =G114*G22+G115*G25+G116*G28+G117*G31 -> 46415.2 | H34: =H114*H22+H115*H25+H116*H28+H117*H31 -> 83156.95
B35: Rata-rata subsidi platform per transaksi (bauran) | C35: =C34-C33 -> 14637.8 | D35: =D34-D33 -> 16233.3 | E35: =E34-E33 -> 16528.14 | F35: =F34-F33 -> 11722.15 | G35: =G34-G33 -> 18489.05 | H35: =H34-H33 -> 29768
A36: B. Alokasi dana — siapa menerima apa (ledger COMPLETION_RELEASE, docs/04-payments-ledger.md)
B37: Traveler — penggantian harga barang (pass-through) | C37: =C8 -> 1500000 | D37: =D8 -> 2000000 | E37: =E8 -> 2500000 | F37: =F8 -> 1000000 | G37: =G8 -> 2500000 | H37: =H8 -> 5000000
B38: Traveler — traveler fee (penghasilan traveler) | C38: =C9 -> 150000 | D38: =D9 -> 200000 | E38: =E9 -> 250000 | F38: =F9 -> 100000 | G38: =G9 -> 250000 | H38: =H9 -> 500000
B39: DJBC — bea masuk + pajak impor via traveler (pass-through) | C39: =C10+C11 -> 415000 | D39: =D10+D11 -> 553000 | E39: =E10+E11 -> 691000 | F39: =F10+F11 -> 277000 | G39: =G10+G11 -> 691000 | H39: =H10+H11 -> 1381000
B40: Negara — PPN atas layanan (pass-through) | C40: =C14 -> 10725 | D40: =D14 -> 14300 | E40: =E14 -> 17875 | F40: =F14 -> 7150 | G40: =G14 -> 17875 | H40: =H14 -> 35750
B41: Xendit — biaya pembayaran yang dibayar pembeli | C41: =C15 -> 15092.68 | D41: =D15 -> 22833.65 | E41: =E15 -> 32611.38 | F41: =F15 -> 12648.45 | G41: =G15 -> 27926.15 | H41: =H15 -> 53388.95
B42: Anggaran promosi — diskon & credit (dibiayai platform) | C42: =C16+C17 -> 0 | D42: =D16+D17 -> 0 | E42: =E16+E17 -> 0 | F42: =F16+F17 -> 0 | G42: =G16+G17 -> 0 | H42: =H16+H17 -> 0
B43: JastipKita — pendapatan bruto (platform + protection) | C43: =C12+C13 -> 97500 | D43: =D12+D13 -> 130000 | E43: =E12+E13 -> 162500 | F43: =F12+F13 -> 65000 | G43: =G12+G13 -> 162500 | H43: =H12+H13 -> 325000
B44: Cek: Σ alokasi − TOTAL (harus 0) | C44: =SUM(C37:C43)-C18 -> 0 | D44: =SUM(D37:D43)-D18 -> 0 | E44: =SUM(E37:E43)-E18 -> 0 | F44: =SUM(F37:F43)-F18 -> 0 | G44: =SUM(G37:G43)-G18 -> 0 | H44: =SUM(H37:H43)-H18 -> 0
B45: Porsi pass-through dalam TOTAL | C45: =IF(C18>0,(C37+C38+C39+C40+C41)/C18,0) -> 0.95544523 | D45: =IF(D18>0,(D37+D38+D39+D40+D41)/D18,0) -> 0.95548149 | E45: =IF(E18>0,(E37+E38+E39+E40+E41)/E18,0) -> 0.95552802 | F45: =IF(F18>0,(F37+F38+F39+F40+F41)/F18,0) -> 0.95553423 | G45: =IF(G18>0,(G37+G38+G39+G40+G41)/G18,0) -> 0.95547093 | H45: =IF(H18>0,(H37+H38+H39+H40+H41)/H18,0) -> 0.95544979
A46: C. Ekonomi platform per transaksi selesai
B47: Pendapatan bruto (platform + protection fee) | C47: =C12+C13 -> 97500 | D47: =D12+D13 -> 130000 | E47: =E12+E13 -> 162500 | F47: =F12+F13 -> 65000 | G47: =G12+G13 -> 162500 | H47: =H12+H13 -> 325000
B48: (−) Promo platform fee gratis, teramortisasi | C48: =-ROUND(C124*C13,0) -> -3750 | D48: =-ROUND(D124*D13,0) -> -4000 | E48: =-ROUND(E124*E13,0) -> -3750 | F48: =-ROUND(F124*F13,0) -> -2000 | G48: =-ROUND(G124*G13,0) -> -5000 | H48: =-ROUND(H124*H13,0) -> -10000 | J48: porsi B7–24 × platform fee
B49: (−) Credit referral ditebus, teramortisasi | C49: =-C125 -> -1957.7248 | D49: =-D125 -> -3101.6922 | E49: =-E125 -> -4800.7909 | F49: =-F125 -> -3101.6922 | G49: =-G125 -> -3101.6922 | H49: =-H125 -> -3101.6922 | J49: rata-rata Th2 dari Proyeksi (cap config ditegakkan)
B50: Pendapatan bersih per transaksi | C50: =SUM(C47:C49) -> 91792.275 | D50: =SUM(D47:D49) -> 122898.31 | E50: =SUM(E47:E49) -> 153949.21 | F50: =SUM(F47:F49) -> 59898.308 | G50: =SUM(G47:G49) -> 154398.31 | H50: =SUM(H47:H49) -> 311898.31
B51: (−) Subsidi kanal pembayaran (bauran) | C51: =-C35 -> -14637.8 | D51: =-D35 -> -16233.3 | E51: =-E35 -> -16528.14 | F51: =-F35 -> -11722.15 | G51: =-G35 -> -18489.05 | H51: =-H35 -> -29768
B52: (−) Biaya payout ke traveler | C52: =-ROUND((C111+IF(C112>0,MAX(C113,(C8+C9+C10+C11)*C112),0))*(1+C110),0) -> -27362 | D52: =-ROUND((D111+IF(D112>0,MAX(D113,(D8+D9+D10+D11)*D112),0))*(1+D110),0) -> -4995 | E52: =-ROUND((E111+IF(E112>0,MAX(E113,(E8+E9+E10+E11)*E112),0))*(1+E110),0) -> -4995 | F52: =-ROUND((F111+IF(F112>0,MAX(F113,(F8+F9+F10+F11)*F112),0))*(1+F110),0) -> -4995 | G52: =-ROUND((G111+IF(G112>0,MAX(G113,(G8+G9+G10+G11)*G112),0))*(1+G110),0) -> -4995 | H52: =-ROUND((H111+IF(H112>0,MAX(H113,(H8+H9+H10+H11)*H112),0))*(1+H110),0) -> -4995 | J52: config payoutFeeIdr = 0 → ditanggung platform
B53: (−) Klaim JastipKita Protection | C53: =-ROUND(C118*C12,0) -> -13500 | D53: =-ROUND(D118*D12,0) -> -12000 | E53: =-ROUND(E118*E12,0) -> -11250 | F53: =-ROUND(F118*F12,0) -> -6000 | G53: =-ROUND(G118*G12,0) -> -15000 | H53: =-ROUND(H118*H12,0) -> -30000 | J53: loss ratio × protection fee
B54: (−) CS & operasional | C54: =-C119 -> -12500 | D54: =-D119 -> -10000 | E54: =-E119 -> -8000 | F54: =-F119 -> -10000 | G54: =-G119 -> -10000 | H54: =-H119 -> -10000
B55: (−) Chargeback kartu | C55: =-ROUND(C117*C121*C122*C123,0) -> -358 | D55: =-ROUND(D117*D121*D122*D123,0) -> -224 | E55: =-ROUND(E117*E121*E122*E123,0) -> -161 | F55: =-ROUND(F117*F121*F122*F123,0) -> -224 | G55: =-ROUND(G117*G121*G122*G123,0) -> -224 | H55: =-ROUND(H117*H121*H122*H123,0) -> -224
B56: (−) Biaya transaksi batal, teramortisasi | C56: =-ROUND(C120/(1-C120)*C63,0) -> -4084 | D56: =-ROUND(D120/(1-D120)*D63,0) -> -2188 | E56: =-ROUND(E120/(1-E120)*E63,0) -> -2131 | F56: =-ROUND(F120/(1-F120)*F63,0) -> -1414 | G56: =-ROUND(G120/(1-G120)*G63,0) -> -2574 | H56: =-ROUND(H120/(1-H120)*H63,0) -> -4508 | J56: batal ÷ selesai × biaya per batal
B57: Margin kontribusi per transaksi selesai | C57: =SUM(C50:C56) -> 19350.475 | D57: =SUM(D50:D56) -> 77258.008 | E57: =SUM(E50:E56) -> 110884.07 | F57: =SUM(F50:F56) -> 25543.158 | G57: =SUM(G50:G56) -> 103116.26 | H57: =SUM(H50:H56) -> 232403.31
B58: Biaya variabel per transaksi (subsidi s.d. batal) | C58: =-SUM(C51:C56) -> 72441.8 | D58: =-SUM(D51:D56) -> 45640.3 | E58: =-SUM(E51:E56) -> 43065.14 | F58: =-SUM(F51:F56) -> 34355.15 | G58: =-SUM(G51:G56) -> 51282.05 | H58: =-SUM(H51:H56) -> 79495
B59: Margin kontribusi ÷ pendapatan bersih | C59: =IF(C50<>0,C57/C50,0) -> 0.21080723 | D59: =IF(D50<>0,D57/D50,0) -> 0.62863362 | E59: =IF(E50<>0,E57/E50,0) -> 0.72026397 | F59: =IF(F50<>0,F57/F50,0) -> 0.42644206 | G59: =IF(G50<>0,G57/G50,0) -> 0.66785873 | H59: =IF(H50<>0,H57/H50,0) -> 0.74512526
B60: Take rate bruto (÷ TOTAL / GMV) | C60: =IF(C18>0,C47/C18,0) -> 0.044554774 | D60: =IF(D18>0,D47/D18,0) -> 0.04451851 | E60: =IF(E18>0,E47/E18,0) -> 0.044471977 | F60: =IF(F18>0,F47/F18,0) -> 0.044465774 | G60: =IF(G18>0,G47/G18,0) -> 0.044529074 | H60: =IF(H18>0,H47/H18,0) -> 0.044550214
B61: Take rate bruto (÷ nilai barang) | C61: =IF(C8>0,C47/C8,0) -> 0.065 | D61: =IF(D8>0,D47/D8,0) -> 0.065 | E61: =IF(E8>0,E47/E8,0) -> 0.065 | F61: =IF(F8>0,F47/F8,0) -> 0.065 | G61: =IF(G8>0,G47/G8,0) -> 0.065 | H61: =IF(H8>0,H47/H8,0) -> 0.065
B62: Take rate bersih (÷ GMV) | C62: =IF(C18>0,C50/C18,0) -> 0.041946504 | D62: =IF(D18>0,D50/D18,0) -> 0.042086535 | E62: =IF(E18>0,E50/E18,0) -> 0.042131851 | F62: =IF(F18>0,F50/F18,0) -> 0.040975764 | G62: =IF(G18>0,G50/G18,0) -> 0.042309007 | H62: =IF(H18>0,H50/H18,0) -> 0.042754266
B63: Biaya per transaksi batal: biaya Xendit hangus + refund via payout (porsi VA) | C63: =ROUND(C34+C114*ROUND((C111+IF(C112>0,MAX(C113,C18*C112),0))*(1+C110),0),0) -> 46968 | D63: =ROUND(D34+D114*ROUND((D111+IF(D112>0,MAX(D113,D18*D112),0))*(1+D110),0),0) -> 41564 | E63: =ROUND(E34+E114*ROUND((E111+IF(E112>0,MAX(E113,E18*E112),0))*(1+E110),0),0) -> 51138 | F63: =ROUND(F34+F114*ROUND((F111+IF(F112>0,MAX(F113,F18*F112),0))*(1+F110),0),0) -> 26868 | G63: =ROUND(G34+G114*ROUND((G111+IF(G112>0,MAX(G113,G18*G112),0))*(1+G110),0),0) -> 48913 | H63: =ROUND(H34+H114*ROUND((H111+IF(H112>0,MAX(H113,H18*H112),0))*(1+H110),0),0) -> 85654 | J63: VA tidak bisa refund → payout (research 02 §4)
B64: Validasi rekening penny-drop per traveler baru (payout Rp1) | C64: =ROUND((C111+IF(C112>0,MAX(C113,1*C112),0))*(1+C110),0) -> 7215 | D64: =ROUND((D111+IF(D112>0,MAX(D113,1*D112),0))*(1+D110),0) -> 4995 | E64: =ROUND((E111+IF(E112>0,MAX(E113,1*E112),0))*(1+E110),0) -> 4995 | F64: =ROUND((F111+IF(F112>0,MAX(F113,1*F112),0))*(1+F110),0) -> 4995 | G64: =ROUND((G111+IF(G112>0,MAX(G113,1*G112),0))*(1+G110),0) -> 4995 | H64: =ROUND((H111+IF(H112>0,MAX(H113,1*H112),0))*(1+H110),0) -> 4995 | J64: alternatif Iluma (biaya bulanan belum diketahui)
B65: Ekonomi proteksi: protection fee − klaim | C65: =C12+C53 -> 9000 | D65: =D12+D53 -> 18000 | E65: =E12+E53 -> 26250 | F65: =F12+F53 -> 9000 | G65: =G12+G53 -> 22500 | H65: =H12+H53 -> 45000 | J65: sebelum biaya mitra asuransi (belum ada, L9)
A66: D. LTV & CAC (indikatif, 12 bulan) — guardrail config referral.buyer.guardrails
B67: Ekspektasi transaksi per pembeli baru dalam 12 bulan | C67: =IF(C127>0,1+C126*(1-C127)*(1-(1-C127)^11)/C127,1+11*C126) -> 1.4940564 | D67: =IF(D127>0,1+D126*(1-D127)*(1-(1-D127)^11)/D127,1+11*D126) -> 1.690417 | E67: =IF(E127>0,1+E126*(1-E127)*(1-(1-E127)^11)/E127,1+11*E126) -> 1.9281594 | F67: =IF(F127>0,1+F126*(1-F127)*(1-(1-F127)^11)/F127,1+11*F126) -> 1.690417 | G67: =IF(G127>0,1+G126*(1-G127)*(1-(1-G127)^11)/G127,1+11*G126) -> 1.690417 | H67: =IF(H127>0,1+H126*(1-H127)*(1-(1-H127)^11)/H127,1+11*H126) -> 1.690417
B68: LTV 12 bulan (margin kontribusi) | C68: =C67*C57 -> 28910.701 | D68: =D67*D57 -> 130598.25 | E68: =E67*E57 -> 213802.16 | F68: =F67*F57 -> 43178.589 | G68: =G67*G57 -> 174309.48 | H68: =H67*H57 -> 392858.51
B69: Batas CAC = guardrail × LTV | C69: =C128*C68 -> 9540.5313 | D69: =D128*D68 -> 43097.423 | E69: =E128*E68 -> 70554.712 | F69: =F128*F68 -> 14248.934 | G69: =G128*G68 -> 57522.127 | H69: =H128*H68 -> 129643.31
B70: CAC blended + OTP per pembeli baru | C70: =C129+ROUND(C130*C131*C123,0) -> 373726 | D70: =D129+ROUND(D130*D131*D123,0) -> 265817 | E70: =E129+ROUND(E130*E131*E123,0) -> 191863 | F70: =F129+ROUND(F130*F131*F123,0) -> 265817 | G70: =G129+ROUND(G130*G131*G123,0) -> 265817 | H70: =H129+ROUND(H130*H131*H123,0) -> 265817
B71: Rasio CAC ÷ LTV | C71: =IF(C68>0,C70/C68,0) -> 12.926909 | D71: =IF(D68>0,D70/D68,0) -> 2.0353795 | E71: =IF(E68>0,E70/E68,0) -> 0.89738571 | F71: =IF(F68>0,F70/F68,0) -> 6.1562225 | G71: =IF(G68>0,G70/G68,0) -> 1.5249716 | H71: =IF(H68>0,H70/H68,0) -> 0.67662274
B72: Status vs guardrail | C72: =IF(C68<=0,"LTV negatif",IF(C71<=C128,"Lolos","Melewati guardrail")) -> Melewati guardrail | D72: =IF(D68<=0,"LTV negatif",IF(D71<=D128,"Lolos","Melewati guardrail")) -> Melewati guardrail | E72: =IF(E68<=0,"LTV negatif",IF(E71<=E128,"Lolos","Melewati guardrail")) -> Melewati guardrail | F72: =IF(F68<=0,"LTV negatif",IF(F71<=F128,"Lolos","Melewati guardrail")) -> Melewati guardrail | G72: =IF(G68<=0,"LTV negatif",IF(G71<=G128,"Lolos","Melewati guardrail")) -> Melewati guardrail | H72: =IF(H68<=0,"LTV negatif",IF(H71<=H128,"Lolos","Melewati guardrail")) -> Melewati guardrail
A73: E. Pemeriksaan batas config (limit dibandingkan dengan TOTAL — asumsi)
B74: Nilai barang ≥ minimum transaksi | C74: =IF(C8>=C132,"OK","Di bawah minimum") -> OK | D74: =IF(D8>=D132,"OK","Di bawah minimum") -> OK | E74: =IF(E8>=E132,"OK","Di bawah minimum") -> OK | F74: =IF(F8>=F132,"OK","Di bawah minimum") -> OK | G74: =IF(G8>=G132,"OK","Di bawah minimum") -> OK | H74: =IF(H8>=H132,"OK","Di bawah minimum") -> OK
B75: TOTAL ≤ limit traveler baru | C75: =IF(C18<=C133,"OK","Butuh traveler ≥ 3 transaksi selesai") -> OK | D75: =IF(D18<=D133,"OK","Butuh traveler ≥ 3 transaksi selesai") -> OK | E75: =IF(E18<=E133,"OK","Butuh traveler ≥ 3 transaksi selesai") -> OK | F75: =IF(F18<=F133,"OK","Butuh traveler ≥ 3 transaksi selesai") -> OK | G75: =IF(G18<=G133,"OK","Butuh traveler ≥ 3 transaksi selesai") -> OK | H75: =IF(H18<=H133,"OK","Butuh traveler ≥ 3 transaksi selesai") -> Butuh traveler ≥ 3 transaksi selesai
B76: TOTAL ≤ batas QRIS | C76: =IF(C18<=C134,"OK","QRIS tidak tersedia") -> OK | D76: =IF(D18<=D134,"OK","QRIS tidak tersedia") -> OK | E76: =IF(E18<=E134,"OK","QRIS tidak tersedia") -> OK | F76: =IF(F18<=F134,"OK","QRIS tidak tersedia") -> OK | G76: =IF(G18<=G134,"OK","QRIS tidak tersedia") -> OK | H76: =IF(H18<=H134,"OK","QRIS tidak tersedia") -> OK
B77: Level KYC pembeli minimum (tanpa trust multiplier) | C77: =IF(C18<=C135,"Level 2",IF(C18<=C136,"Level 3",IF(C18<=C137,"Level 4","Level 5"))) -> Level 2 | D77: =IF(D18<=D135,"Level 2",IF(D18<=D136,"Level 3",IF(D18<=D137,"Level 4","Level 5"))) -> Level 2 | E77: =IF(E18<=E135,"Level 2",IF(E18<=E136,"Level 3",IF(E18<=E137,"Level 4","Level 5"))) -> Level 3 | F77: =IF(F18<=F135,"Level 2",IF(F18<=F136,"Level 3",IF(F18<=F137,"Level 4","Level 5"))) -> Level 2 | G77: =IF(G18<=G135,"Level 2",IF(G18<=G136,"Level 3",IF(G18<=G137,"Level 4","Level 5"))) -> Level 3 | H77: =IF(H18<=H135,"Level 2",IF(H18<=H136,"Level 3",IF(H18<=H137,"Level 4","Level 5"))) -> Level 3
B78: Status traveler fee vs batas config | C78: =IF(ROUND(C8*C80,0)<C81,"Naik ke minimum",IF(ROUND(C8*C80,0)>ROUNDDOWN(C8*C82,0),"Dipotong ke maks","Normal")) -> Normal | D78: =IF(ROUND(D8*D80,0)<D81,"Naik ke minimum",IF(ROUND(D8*D80,0)>ROUNDDOWN(D8*D82,0),"Dipotong ke maks","Normal")) -> Normal | E78: =IF(ROUND(E8*E80,0)<E81,"Naik ke minimum",IF(ROUND(E8*E80,0)>ROUNDDOWN(E8*E82,0),"Dipotong ke maks","Normal")) -> Normal | F78: =IF(ROUND(F8*F80,0)<F81,"Naik ke minimum",IF(ROUND(F8*F80,0)>ROUNDDOWN(F8*F82,0),"Dipotong ke maks","Normal")) -> Normal | G78: =IF(ROUND(G8*G80,0)<G81,"Naik ke minimum",IF(ROUND(G8*G80,0)>ROUNDDOWN(G8*G82,0),"Dipotong ke maks","Normal")) -> Normal | H78: =IF(ROUND(H8*H80,0)<H81,"Naik ke minimum",IF(ROUND(H8*H80,0)>ROUNDDOWN(H8*H82,0),"Dipotong ke maks","Normal")) -> Normal
A79: F. Parameter (tautan ke sheet Asumsi sesuai indeks skenario kolom)
B80: Traveler fee (%) | C80: =INDEX(Asumsi!$D$59:$F$59,C$5) -> 0.1 | D80: =INDEX(Asumsi!$D$59:$F$59,D$5) -> 0.1 | E80: =INDEX(Asumsi!$D$59:$F$59,E$5) -> 0.1 | F80: =INDEX(Asumsi!$D$59:$F$59,F$5) -> 0.1 | G80: =INDEX(Asumsi!$D$59:$F$59,G$5) -> 0.1 | H80: =INDEX(Asumsi!$D$59:$F$59,H$5) -> 0.1
B81: Traveler fee minimum | C81: =INDEX(Asumsi!$D$24:$F$24,C$5) -> 25000 | D81: =INDEX(Asumsi!$D$24:$F$24,D$5) -> 25000 | E81: =INDEX(Asumsi!$D$24:$F$24,E$5) -> 25000 | F81: =INDEX(Asumsi!$D$24:$F$24,F$5) -> 25000 | G81: =INDEX(Asumsi!$D$24:$F$24,G$5) -> 25000 | H81: =INDEX(Asumsi!$D$24:$F$24,H$5) -> 25000
B82: Traveler fee maksimum (%) | C82: =INDEX(Asumsi!$D$25:$F$25,C$5) -> 0.3 | D82: =INDEX(Asumsi!$D$25:$F$25,D$5) -> 0.3 | E82: =INDEX(Asumsi!$D$25:$F$25,E$5) -> 0.3 | F82: =INDEX(Asumsi!$D$25:$F$25,F$5) -> 0.3 | G82: =INDEX(Asumsi!$D$25:$F$25,G$5) -> 0.3 | H82: =INDEX(Asumsi!$D$25:$F$25,H$5) -> 0.3
B83: Bea masuk | C83: =INDEX(Asumsi!$D$60:$F$60,C$5) -> 0.1 | D83: =INDEX(Asumsi!$D$60:$F$60,D$5) -> 0.1 | E83: =INDEX(Asumsi!$D$60:$F$60,E$5) -> 0.1 | F83: =INDEX(Asumsi!$D$60:$F$60,F$5) -> 0.1 | G83: =INDEX(Asumsi!$D$60:$F$60,G$5) -> 0.1 | H83: =INDEX(Asumsi!$D$60:$F$60,H$5) -> 0.1
B84: PPN impor | C84: =INDEX(Asumsi!$D$61:$F$61,C$5) -> 0.12 | D84: =INDEX(Asumsi!$D$61:$F$61,D$5) -> 0.12 | E84: =INDEX(Asumsi!$D$61:$F$61,E$5) -> 0.12 | F84: =INDEX(Asumsi!$D$61:$F$61,F$5) -> 0.12 | G84: =INDEX(Asumsi!$D$61:$F$61,G$5) -> 0.12 | H84: =INDEX(Asumsi!$D$61:$F$61,H$5) -> 0.12
B85: DPP PPN impor | C85: =INDEX(Asumsi!$D$62:$F$62,C$5) -> 0.916667 | D85: =INDEX(Asumsi!$D$62:$F$62,D$5) -> 0.916667 | E85: =INDEX(Asumsi!$D$62:$F$62,E$5) -> 0.916667 | F85: =INDEX(Asumsi!$D$62:$F$62,F$5) -> 0.916667 | G85: =INDEX(Asumsi!$D$62:$F$62,G$5) -> 0.916667 | H85: =INDEX(Asumsi!$D$62:$F$62,H$5) -> 0.916667
B86: PPh 22 impor | C86: =INDEX(Asumsi!$D$63:$F$63,C$5) -> 0.05 | D86: =INDEX(Asumsi!$D$63:$F$63,D$5) -> 0.05 | E86: =INDEX(Asumsi!$D$63:$F$63,E$5) -> 0.05 | F86: =INDEX(Asumsi!$D$63:$F$63,F$5) -> 0.05 | G86: =INDEX(Asumsi!$D$63:$F$63,G$5) -> 0.05 | H86: =INDEX(Asumsi!$D$63:$F$63,H$5) -> 0.05
B87: Protection fee (%) | C87: =INDEX(Asumsi!$D$18:$F$18,C$5) -> 0.015 | D87: =INDEX(Asumsi!$D$18:$F$18,D$5) -> 0.015 | E87: =INDEX(Asumsi!$D$18:$F$18,E$5) -> 0.015 | F87: =INDEX(Asumsi!$D$18:$F$18,F$5) -> 0.015 | G87: =INDEX(Asumsi!$D$18:$F$18,G$5) -> 0.015 | H87: =INDEX(Asumsi!$D$18:$F$18,H$5) -> 0.015
B88: Protection fee min | C88: =INDEX(Asumsi!$D$19:$F$19,C$5) -> 5000 | D88: =INDEX(Asumsi!$D$19:$F$19,D$5) -> 5000 | E88: =INDEX(Asumsi!$D$19:$F$19,E$5) -> 5000 | F88: =INDEX(Asumsi!$D$19:$F$19,F$5) -> 5000 | G88: =INDEX(Asumsi!$D$19:$F$19,G$5) -> 5000 | H88: =INDEX(Asumsi!$D$19:$F$19,H$5) -> 5000
B89: Protection fee maks | C89: =INDEX(Asumsi!$D$20:$F$20,C$5) -> 300000 | D89: =INDEX(Asumsi!$D$20:$F$20,D$5) -> 300000 | E89: =INDEX(Asumsi!$D$20:$F$20,E$5) -> 300000 | F89: =INDEX(Asumsi!$D$20:$F$20,F$5) -> 300000 | G89: =INDEX(Asumsi!$D$20:$F$20,G$5) -> 300000 | H89: =INDEX(Asumsi!$D$20:$F$20,H$5) -> 300000
B90: Platform fee (%) | C90: =INDEX(Asumsi!$D$15:$F$15,C$5) -> 0.05 | D90: =INDEX(Asumsi!$D$15:$F$15,D$5) -> 0.05 | E90: =INDEX(Asumsi!$D$15:$F$15,E$5) -> 0.05 | F90: =INDEX(Asumsi!$D$15:$F$15,F$5) -> 0.05 | G90: =INDEX(Asumsi!$D$15:$F$15,G$5) -> 0.05 | H90: =INDEX(Asumsi!$D$15:$F$15,H$5) -> 0.05
B91: Platform fee min | C91: =INDEX(Asumsi!$D$16:$F$16,C$5) -> 10000 | D91: =INDEX(Asumsi!$D$16:$F$16,D$5) -> 10000 | E91: =INDEX(Asumsi!$D$16:$F$16,E$5) -> 10000 | F91: =INDEX(Asumsi!$D$16:$F$16,F$5) -> 10000 | G91: =INDEX(Asumsi!$D$16:$F$16,G$5) -> 10000 | H91: =INDEX(Asumsi!$D$16:$F$16,H$5) -> 10000
B92: Platform fee maks | C92: =INDEX(Asumsi!$D$17:$F$17,C$5) -> 750000 | D92: =INDEX(Asumsi!$D$17:$F$17,D$5) -> 750000 | E92: =INDEX(Asumsi!$D$17:$F$17,E$5) -> 750000 | F92: =INDEX(Asumsi!$D$17:$F$17,F$5) -> 750000 | G92: =INDEX(Asumsi!$D$17:$F$17,G$5) -> 750000 | H92: =INDEX(Asumsi!$D$17:$F$17,H$5) -> 750000
B93: PPN layanan | C93: =INDEX(Asumsi!$D$21:$F$21,C$5) -> 0.12 | D93: =INDEX(Asumsi!$D$21:$F$21,D$5) -> 0.12 | E93: =INDEX(Asumsi!$D$21:$F$21,E$5) -> 0.12 | F93: =INDEX(Asumsi!$D$21:$F$21,F$5) -> 0.12 | G93: =INDEX(Asumsi!$D$21:$F$21,G$5) -> 0.12 | H93: =INDEX(Asumsi!$D$21:$F$21,H$5) -> 0.12
B94: DPP PPN layanan | C94: =INDEX(Asumsi!$D$22:$F$22,C$5) -> 0.916667 | D94: =INDEX(Asumsi!$D$22:$F$22,D$5) -> 0.916667 | E94: =INDEX(Asumsi!$D$22:$F$22,E$5) -> 0.916667 | F94: =INDEX(Asumsi!$D$22:$F$22,F$5) -> 0.916667 | G94: =INDEX(Asumsi!$D$22:$F$22,G$5) -> 0.916667 | H94: =INDEX(Asumsi!$D$22:$F$22,H$5) -> 0.916667
B95: PPN layanan dipungut (1/0) | C95: =INDEX(Asumsi!$D$23:$F$23,C$5) -> 1 | D95: =INDEX(Asumsi!$D$23:$F$23,D$5) -> 1 | E95: =INDEX(Asumsi!$D$23:$F$23,E$5) -> 1 | F95: =INDEX(Asumsi!$D$23:$F$23,F$5) -> 1 | G95: =INDEX(Asumsi!$D$23:$F$23,G$5) -> 1 | H95: =INDEX(Asumsi!$D$23:$F$23,H$5) -> 1
B96: Config VA tetap | C96: =INDEX(Asumsi!$D$29:$F$29,C$5) -> 4500 | D96: =INDEX(Asumsi!$D$29:$F$29,D$5) -> 4500 | E96: =INDEX(Asumsi!$D$29:$F$29,E$5) -> 4500 | F96: =INDEX(Asumsi!$D$29:$F$29,F$5) -> 4500 | G96: =INDEX(Asumsi!$D$29:$F$29,G$5) -> 4500 | H96: =INDEX(Asumsi!$D$29:$F$29,H$5) -> 4500
B97: Config VA % | C97: =INDEX(Asumsi!$D$30:$F$30,C$5) -> 0 | D97: =INDEX(Asumsi!$D$30:$F$30,D$5) -> 0 | E97: =INDEX(Asumsi!$D$30:$F$30,E$5) -> 0 | F97: =INDEX(Asumsi!$D$30:$F$30,F$5) -> 0 | G97: =INDEX(Asumsi!$D$30:$F$30,G$5) -> 0 | H97: =INDEX(Asumsi!$D$30:$F$30,H$5) -> 0
B98: Config QRIS tetap | C98: =INDEX(Asumsi!$D$31:$F$31,C$5) -> 0 | D98: =INDEX(Asumsi!$D$31:$F$31,D$5) -> 0 | E98: =INDEX(Asumsi!$D$31:$F$31,E$5) -> 0 | F98: =INDEX(Asumsi!$D$31:$F$31,F$5) -> 0 | G98: =INDEX(Asumsi!$D$31:$F$31,G$5) -> 0 | H98: =INDEX(Asumsi!$D$31:$F$31,H$5) -> 0
B99: Config QRIS % | C99: =INDEX(Asumsi!$D$32:$F$32,C$5) -> 0.007 | D99: =INDEX(Asumsi!$D$32:$F$32,D$5) -> 0.007 | E99: =INDEX(Asumsi!$D$32:$F$32,E$5) -> 0.007 | F99: =INDEX(Asumsi!$D$32:$F$32,F$5) -> 0.007 | G99: =INDEX(Asumsi!$D$32:$F$32,G$5) -> 0.007 | H99: =INDEX(Asumsi!$D$32:$F$32,H$5) -> 0.007
B100: Config e-wallet tetap | C100: =INDEX(Asumsi!$D$33:$F$33,C$5) -> 0 | D100: =INDEX(Asumsi!$D$33:$F$33,D$5) -> 0 | E100: =INDEX(Asumsi!$D$33:$F$33,E$5) -> 0 | F100: =INDEX(Asumsi!$D$33:$F$33,F$5) -> 0 | G100: =INDEX(Asumsi!$D$33:$F$33,G$5) -> 0 | H100: =INDEX(Asumsi!$D$33:$F$33,H$5) -> 0
...

Sheet Proyeksi 24 Bulan
A1: Proyeksi 24 Bulan sejak soft launch (Bulan 0 = pra-peluncuran)
A2: Tiga blok skenario dihitung serentak (Konservatif, Dasar, Optimis); ringkasan di atas mengikuti skenario aktif. Satuan Rp kecuali disebut. Kas = kas perusahaan saja — dana escrow pembeli di saldo Xendit bukan kas perusahaan.
A3: ="Skenario aktif: "&Asumsi!$D$4 -> Skenario aktif: Dasar
A5: Bulan ke- | B5: Satuan | C5: 0 | D5: 1 | E5: 2 | F5: 3 | G5: 4 | H5: 5 | I5: 6 | J5: 7 | K5: 8 | L5: 9 | M5: 10 | N5: 11 | O5: 12 | P5: 13 | Q5: 14 | R5: 15 | S5: 16 | T5: 17 | U5: 18 | V5: 19 | W5: 20 | X5: 21 | Y5: 22 | Z5: 23 | AA5: 24 | AB5: Tahun 1 (B1–B12) | AC5: Tahun 2 (B13–B24) | AD5: Total B0–B24
A6: Periode | C6: Pra-launch | D6: =EDATE(Asumsi!$G$10,D$5-1) -> 46419 | E6: =EDATE(Asumsi!$G$10,E$5-1) -> 46447 | F6: =EDATE(Asumsi!$G$10,F$5-1) -> 46478 | G6: =EDATE(Asumsi!$G$10,G$5-1) -> 46508 | H6: =EDATE(Asumsi!$G$10,H$5-1) -> 46539 | I6: =EDATE(Asumsi!$G$10,I$5-1) -> 46569 | J6: =EDATE(Asumsi!$G$10,J$5-1) -> 46600 | K6: =EDATE(Asumsi!$G$10,K$5-1) -> 46631 | ... AA6: =EDATE(Asumsi!$G$10,AA$5-1) -> 47119
A7: RINGKASAN SKENARIO AKTIF (CHOOSE dari blok di bawah)
A8: Transaksi selesai — skenario aktif | B8: trx | C8: =CHOOSE(Asumsi!$D$5,C38,C101,C164) -> 0 | D8: =CHOOSE(Asumsi!$D$5,D38,D101,D164) -> 34.1145 | E8: =CHOOSE(Asumsi!$D$5,E38,E101,E164) -> 48.90942 | F8: =CHOOSE(Asumsi!$D$5,F38,F101,F164) -> 64.405303 | G8: =CHOOSE(Asumsi!$D$5,G38,G101,G164) -> 80.677532 | H8: =CHOOSE(Asumsi!$D$5,H38,H101,H164) -> 97.806747 | I8: =CHOOSE(Asumsi!$D$5,I38,I101,I164) -> 115.8793 | J8: =CHOOSE(Asumsi!$D$5,J38,J101,J164) -> 134.98773 | ... AD8: =CHOOSE(Asumsi!$D$5,AD38,AD101,AD164) -> 6812.5153
A9: GMV bruto — skenario aktif | B9: Rp | C9: =CHOOSE(Asumsi!$D$5,C41,C104,C167) -> 0 | D9: =CHOOSE(Asumsi!$D$5,D41,D104,D167) -> 99618899 | E9: =CHOOSE(Asumsi!$D$5,E41,E104,E167) -> 1.4282204e+08 | F9: =CHOOSE(Asumsi!$D$5,F41,F104,F167) -> 1.8807209e+08 | G9: =CHOOSE(Asumsi!$D$5,G41,G104,G167) -> 2.3558918e+08 | H9: =CHOOSE(Asumsi!$D$5,H41,H104,H167) -> 2.8560877e+08 | I9: =CHOOSE(Asumsi!$D$5,I41,I104,I167) -> 3.3838304e+08 | J9: =CHOOSE(Asumsi!$D$5,J41,J104,J167) -> 3.9418222e+08 | ... AD9: =CHOOSE(Asumsi!$D$5,AD41,AD104,AD167) -> 1.9893455e+10
A10: Pendapatan bersih — skenario aktif | B10: Rp | C10: =CHOOSE(Asumsi!$D$5,C47,C110,C173) -> 0 | D10: =CHOOSE(Asumsi!$D$5,D47,D110,D173) -> 3927823.5 | E10: =CHOOSE(Asumsi!$D$5,E47,E110,E173) -> 5650747.3 | F10: =CHOOSE(Asumsi!$D$5,F47,F110,F173) -> 7449831.6 | G10: =CHOOSE(Asumsi!$D$5,G47,G110,G173) -> 9334908.2 | H10: =CHOOSE(Asumsi!$D$5,H47,H110,H173) -> 11311063 | I10: =CHOOSE(Asumsi!$D$5,I47,I110,I173) -> 13393019 | J10: =CHOOSE(Asumsi!$D$5,J47,J110,J173) -> 16672066 | ... AD10: =CHOOSE(Asumsi!$D$5,AD47,AD110,AD173) -> 8.345434e+08
A11: Margin kontribusi — skenario aktif | B11: Rp | C11: =CHOOSE(Asumsi!$D$5,C60,C123,C186) -> -1090756.4 | D11: =CHOOSE(Asumsi!$D$5,D60,D123,D186) -> 1336870.8 | E11: =CHOOSE(Asumsi!$D$5,E60,E123,E186) -> 2318070.4 | F11: =CHOOSE(Asumsi!$D$5,F60,F123,F186) -> 3335273.8 | G11: =CHOOSE(Asumsi!$D$5,G60,G123,G186) -> 3129729.4 | H11: =CHOOSE(Asumsi!$D$5,H60,H123,H186) -> 4230549.9 | I11: =CHOOSE(Asumsi!$D$5,I60,I123,I186) -> 5385485.3 | J11: =CHOOSE(Asumsi!$D$5,J60,J123,J186) -> 7681457.7 | ... AD11: =CHOOSE(Asumsi!$D$5,AD60,AD123,AD186) -> 4.2455927e+08
A12: Biaya akuisisi & tetap — skenario aktif | B12: Rp | C12: =CHOOSE(Asumsi!$D$5,C71,C134,C197) -> 473195491 | D12: =CHOOSE(Asumsi!$D$5,D71,D134,D197) -> 100741261 | E12: =CHOOSE(Asumsi!$D$5,E71,E134,E197) -> 100741261 | F12: =CHOOSE(Asumsi!$D$5,F71,F134,F197) -> 100741261 | G12: =CHOOSE(Asumsi!$D$5,G71,G134,G197) -> 120741261 | H12: =CHOOSE(Asumsi!$D$5,H71,H134,H197) -> 120741261 | I12: =CHOOSE(Asumsi!$D$5,I71,I134,I197) -> 120741261 | J12: =CHOOSE(Asumsi!$D$5,J71,J134,J197) -> 120741261 | ... AD12: =CHOOSE(Asumsi!$D$5,AD71,AD134,AD197) -> 3865533321
A13: EBITDA — skenario aktif | B13: Rp | C13: =CHOOSE(Asumsi!$D$5,C73,C136,C199) -> -4.7428625e+08 | D13: =CHOOSE(Asumsi!$D$5,D73,D136,D199) -> -99404390 | E13: =CHOOSE(Asumsi!$D$5,E73,E136,E199) -> -98423191 | F13: =CHOOSE(Asumsi!$D$5,F73,F136,F199) -> -97405987 | G13: =CHOOSE(Asumsi!$D$5,G73,G136,G199) -> -1.1761153e+08 | H13: =CHOOSE(Asumsi!$D$5,H73,H136,H199) -> -1.1651071e+08 | I13: =CHOOSE(Asumsi!$D$5,I73,I136,I199) -> -1.1535578e+08 | J13: =CHOOSE(Asumsi!$D$5,J73,J136,J199) -> -1.130598e+08 | ... AD13: =CHOOSE(Asumsi!$D$5,AD73,AD136,AD199) -> -3.4409741e+09
A14: Kas kumulatif — skenario aktif | B14: Rp | C14: =CHOOSE(Asumsi!$D$5,C76,C139,C202) -> -4.7428625e+08 | D14: =CHOOSE(Asumsi!$D$5,D76,D139,D202) -> -5.7761846e+08 | E14: =CHOOSE(Asumsi!$D$5,E76,E139,E202) -> -6.7776458e+08 | F14: =CHOOSE(Asumsi!$D$5,F76,F139,F202) -> -7.7696965e+08 | G14: =CHOOSE(Asumsi!$D$5,G76,G139,G202) -> -8.9646626e+08 | H14: =CHOOSE(Asumsi!$D$5,H76,H139,H202) -> -1.0149531e+09 | I14: =CHOOSE(Asumsi!$D$5,I76,I139,I202) -> -1.1323909e+09 | J14: =CHOOSE(Asumsi!$D$5,J76,J139,J202) -> -1.2487297e+09 | ... AD14: =CHOOSE(Asumsi!$D$5,AD76,AD139,AD202) -> -3.5132508e+09
A17: SKENARIO KONSERVATIF — input dari Asumsi kolom D, unit economics dari kolom C
A18: Pasokan traveler
A19: Traveler terverifikasi baru (B0 = peserta beta) | B19: orang | C19: =Asumsi!$D$74 -> 20 | D19: =Asumsi!$D$75*(1+Asumsi!$D$76)^(D$5-1) -> 10 | E19: =Asumsi!$D$75*(1+Asumsi!$D$76)^(E$5-1) -> 10.4 | F19: =Asumsi!$D$75*(1+Asumsi!$D$76)^(F$5-1) -> 10.816 | G19: =Asumsi!$D$75*(1+Asumsi!$D$76)^(G$5-1) -> 11.24864 | H19: =Asumsi!$D$75*(1+Asumsi!$D$76)^(H$5-1) -> 11.698586 | I19: =Asumsi!$D$75*(1+Asumsi!$D$76)^(I$5-1) -> 12.166529 | J19: =Asumsi!$D$75*(1+Asumsi!$D$76)^(J$5-1) -> 12.65319 | K19: =Asumsi!$D$75*(1+Asumsi!$D$76)^(K$5-1) -> 13.159318 | ... AA19: =Asumsi!$D$75*(1+Asumsi!$D$76)^(AA$5-1) -> 24.647155 | AB19: =SUM(D19:O19) -> 150.25805 | AC19: =SUM(P19:AA19) -> 240.56799 | AD19: =SUM(C19:AA19) -> 410.82604
A20: Basis traveler terverifikasi (akhir bulan) | B20: orang | C20: =C19 -> 20 | D20: =C20*(1-Asumsi!$D$77)+D19 -> 29 | E20: =D20*(1-Asumsi!$D$77)+E19 -> 37.95 | F20: =E20*(1-Asumsi!$D$77)+F19 -> 46.8685 | G20: =F20*(1-Asumsi!$D$77)+G19 -> 55.773715 | H20: =G20*(1-Asumsi!$D$77)+H19 -> 64.683615 | I20: =H20*(1-Asumsi!$D$77)+I19 -> 73.615963 | J20: =I20*(1-Asumsi!$D$77)+J19 -> 82.588355 | K20: =J20*(1-Asumsi!$D$77)+K19 -> 91.618255 | ... AA20: =Z20*(1-Asumsi!$D$77)+AA19 -> 258.20813 | AB20: =O20 -> 128.65966 | AC20: =AA20 -> 258.20813 | AD20: =AA20 -> 258.20813
A21: Traveler aktif (punya trip) | B21: orang | D21: =D20*Asumsi!$D$78 -> 8.7 | E21: =E20*Asumsi!$D$78 -> 11.385 | F21: =F20*Asumsi!$D$78 -> 14.06055 | G21: =G20*Asumsi!$D$78 -> 16.732115 | H21: =H20*Asumsi!$D$78 -> 19.405084 | I21: =I20*Asumsi!$D$78 -> 22.084789 | J21: =J20*Asumsi!$D$78 -> 24.776507 | K21: =K20*Asumsi!$D$78 -> 27.485477 | ... AA21: =AA20*Asumsi!$D$78 -> 77.462439 | AB21: =O21 -> 38.597898 | AC21: =AA21 -> 77.462439 | AD21: =AA21 -> 77.462439
A22: Kapasitas pesanan | B22: pesanan | D22: =D21*Asumsi!$D$79 -> 21.75 | E22: =E21*Asumsi!$D$79 -> 28.4625 | F22: =F21*Asumsi!$D$79 -> 35.151375 | G22: =G21*Asumsi!$D$79 -> 41.830286 | H22: =H21*Asumsi!$D$79 -> 48.512711 | I22: =I21*Asumsi!$D$79 -> 55.211972 | J22: =J21*Asumsi!$D$79 -> 61.941266 | K22: =K21*Asumsi!$D$79 -> 68.713691 | ... AA22: =AA21*Asumsi!$D$79 -> 193.6561 | AB22: =SUM(D22:O22) -> 705.47065 | AC22: =SUM(P22:AA22) -> 1762.4541 | AD22: =SUM(C22:AA22) -> 2467.9248
A23: Permintaan pembeli
A24: Pembeli baru — organik | B24: orang | D24: =Asumsi!$D$82*(1+Asumsi!$D$83)^(D$5-1) -> 20 | E24: =Asumsi!$D$82*(1+Asumsi!$D$83)^(E$5-1) -> 21 | F24: =Asumsi!$D$82*(1+Asumsi!$D$83)^(F$5-1) -> 22.05 | G24: =Asumsi!$D$82*(1+Asumsi!$D$83)^(G$5-1) -> 23.1525 | H24: =Asumsi!$D$82*(1+Asumsi!$D$83)^(H$5-1) -> 24.310125 | I24: =Asumsi!$D$82*(1+Asumsi!$D$83)^(I$5-1) -> 25.525631 | J24: =Asumsi!$D$82*(1+Asumsi!$D$83)^(J$5-1) -> 26.801913 | K24: =Asumsi!$D$82*(1+Asumsi!$D$83)^(K$5-1) -> 28.142008 | ... AA24: =Asumsi!$D$82*(1+Asumsi!$D$83)^(AA$5-1) -> 61.430475 | AB24: =SUM(D24:O24) -> 318.34253 | AC24: =SUM(P24:AA24) -> 571.69745 | AD24: =SUM(C24:AA24) -> 890.03998
A25: Anggaran marketing kas | B25: Rp | D25: =IF(D$5<=3,Asumsi!$D$84,IF(D$5<=12,Asumsi!$D$85,Asumsi!$D$86)) -> 5000000 | E25: =IF(E$5<=3,Asumsi!$D$84,IF(E$5<=12,Asumsi!$D$85,Asumsi!$D$86)) -> 5000000 | F25: =IF(F$5<=3,Asumsi!$D$84,IF(F$5<=12,Asumsi!$D$85,Asumsi!$D$86)) -> 5000000 | G25: =IF(G$5<=3,Asumsi!$D$84,IF(G$5<=12,Asumsi!$D$85,Asumsi!$D$86)) -> 25000000 | H25: =IF(H$5<=3,Asumsi!$D$84,IF(H$5<=12,Asumsi!$D$85,Asumsi!$D$86)) -> 25000000 | I25: =IF(I$5<=3,Asumsi!$D$84,IF(I$5<=12,Asumsi!$D$85,Asumsi!$D$86)) -> 25000000 | J25: =IF(J$5<=3,Asumsi!$D$84,IF(J$5<=12,Asumsi!$D$85,Asumsi!$D$86)) -> 25000000 | K25: =IF(K$5<=3,Asumsi!$D$84,IF(K$5<=12,Asumsi!$D$85,Asumsi!$D$86)) -> 25000000 | ... AA25: =IF(AA$5<=3,Asumsi!$D$84,IF(AA$5<=12,Asumsi!$D$85,Asumsi!$D$86)) -> 35000000 | AB25: =SUM(D25:O25) -> 240000000 | AC25: =SUM(P25:AA25) -> 420000000 | AD25: =SUM(C25:AA25) -> 660000000
A26: Pembeli baru — marketing (anggaran ÷ CAC) | B26: orang | D26: =IF(Asumsi!$D$87>0,D25/Asumsi!$D$87,0) -> 14.285714 | E26: =IF(Asumsi!$D$87>0,E25/Asumsi!$D$87,0) -> 14.285714 | F26: =IF(Asumsi!$D$87>0,F25/Asumsi!$D$87,0) -> 14.285714 | G26: =IF(Asumsi!$D$87>0,G25/Asumsi!$D$87,0) -> 71.428571 | H26: =IF(Asumsi!$D$87>0,H25/Asumsi!$D$87,0) -> 71.428571 | I26: =IF(Asumsi!$D$87>0,I25/Asumsi!$D$87,0) -> 71.428571 | J26: =IF(Asumsi!$D$87>0,J25/Asumsi!$D$87,0) -> 71.428571 | K26: =IF(Asumsi!$D$87>0,K25/Asumsi!$D$87,0) -> 71.428571 | ... AA26: =IF(Asumsi!$D$87>0,AA25/Asumsi!$D$87,0) -> 100 | AB26: =SUM(D26:O26) -> 685.71429 | AC26: =SUM(P26:AA26) -> 1200 | AD26: =SUM(C26:AA26) -> 1885.7143
A27: Basis pembeli retensi (awal bulan) | B27: orang | D27: =C36*(1-Asumsi!$D$88) -> 45 | E27: =D36*(1-Asumsi!$D$88) -> 58.247492 | F27: =E36*(1-Asumsi!$D$88) -> 75.114719 | G27: =F36*(1-Asumsi!$D$88) -> 94.866338 | H27: =G36*(1-Asumsi!$D$88) -> 120.2689 | I27: =H36*(1-Asumsi!$D$88) -> 147.9834 | J27: =I36*(1-Asumsi!$D$88) -> 177.57669 | K27: =J36*(1-Asumsi!$D$88) -> 208.68562 | ... AA27: =Z36*(1-Asumsi!$D$88) -> 826.41833
A28: Pembeli baru — referral (sebelum cap anggaran) | B28: orang | D28: =D27*Asumsi!$D$95 -> 0.675 | E28: =E27*Asumsi!$D$95 -> 0.87371239 | F28: =F27*Asumsi!$D$95 -> 1.1267208 | G28: =G27*Asumsi!$D$95 -> 1.4229951 | H28: =H27*Asumsi!$D$95 -> 1.8040335 | I28: =I27*Asumsi!$D$95 -> 2.2197511 | J28: =J27*Asumsi!$D$95 -> 2.6636503 | K28: =K27*Asumsi!$D$95 -> 3.1302843 | ... AA28: =AA27*Asumsi!$D$95 -> 12.396275 | AB28: =SUM(D28:O28) -> 31.419535 | AC28: =SUM(P28:AA28) -> 107.80941 | AD28: =SUM(C28:AA28) -> 139.22895
A29: Credit referral pembeli sebelum cap anggaran | B29: Rp | D29: =D28*Asumsi!$D$96*(MIN(Asumsi!$D$91,Asumsi!$D$94/Asumsi!$D$98)+Asumsi!$D$92)*Asumsi!$D$97 -> 15356.25 | E29: =E28*Asumsi!$D$96*(MIN(Asumsi!$D$91,Asumsi!$D$94/Asumsi!$D$98)+Asumsi!$D$92)*Asumsi!$D$97 -> 19876.957 | F29: =F28*Asumsi!$D$96*(MIN(Asumsi!$D$91,Asumsi!$D$94/Asumsi!$D$98)+Asumsi!$D$92)*Asumsi!$D$97 -> 25632.898 | G29: =G28*Asumsi!$D$96*(MIN(Asumsi!$D$91,Asumsi!$D$94/Asumsi!$D$98)+Asumsi!$D$92)*Asumsi!$D$97 -> 32373.138 | H29: =H28*Asumsi!$D$96*(MIN(Asumsi!$D$91,Asumsi!$D$94/Asumsi!$D$98)+Asumsi!$D$92)*Asumsi!$D$97 -> 41041.763 | I29: =I28*Asumsi!$D$96*(MIN(Asumsi!$D$91,Asumsi!$D$94/Asumsi!$D$98)+Asumsi!$D$92)*Asumsi!$D$97 -> 50499.337 | J29: =J28*Asumsi!$D$96*(MIN(Asumsi!$D$91,Asumsi!$D$94/Asumsi!$D$98)+Asumsi!$D$92)*Asumsi!$D$97 -> 60598.044 | K29: =K28*Asumsi!$D$96*(MIN(Asumsi!$D$91,Asumsi!$D$94/Asumsi!$D$98)+Asumsi!$D$92)*Asumsi!$D$97 -> 71213.969 | ... AA29: =AA28*Asumsi!$D$96*(MIN(Asumsi!$D$91,Asumsi!$D$94/Asumsi!$D$98)+Asumsi!$D$92)*Asumsi!$D$97 -> 282015.26 | AB29: =SUM(D29:O29) -> 714794.43 | AC29: =SUM(P29:AA29) -> 2452664.1 | AD29: =SUM(C29:AA29) -> 3167458.5
A30: Faktor cap anggaran referral global | B30: faktor | D30: =IF(AND(Asumsi!$D$103=1,D29>0),MIN(1,Asumsi!$D$104/D29),1) -> 1 | E30: =IF(AND(Asumsi!$D$103=1,E29>0),MIN(1,Asumsi!$D$104/E29),1) -> 1 | F30: =IF(AND(Asumsi!$D$103=1,F29>0),MIN(1,Asumsi!$D$104/F29),1) -> 1 | G30: =IF(AND(Asumsi!$D$103=1,G29>0),MIN(1,Asumsi!$D$104/G29),1) -> 1 | H30: =IF(AND(Asumsi!$D$103=1,H29>0),MIN(1,Asumsi!$D$104/H29),1) -> 1 | I30: =IF(AND(Asumsi!$D$103=1,I29>0),MIN(1,Asumsi!$D$104/I29),1) -> 1 | J30: =IF(AND(Asumsi!$D$103=1,J29>0),MIN(1,Asumsi!$D$104/J29),1) -> 1 | K30: =IF(AND(Asumsi!$D$103=1,K29>0),MIN(1,Asumsi!$D$104/K29),1) -> 1 | ... AA30: =IF(AND(Asumsi!$D$103=1,AA29>0),MIN(1,Asumsi!$D$104/AA29),1) -> 1
A31: Pembeli baru — referral (efektif) | B31: orang | D31: =D28*D30 -> 0.675 | E31: =E28*E30 -> 0.87371239 | F31: =F28*F30 -> 1.1267208 | G31: =G28*G30 -> 1.4229951 | H31: =H28*H30 -> 1.8040335 | I31: =I28*I30 -> 2.2197511 | J31: =J28*J30 -> 2.6636503 | K31: =K28*K30 -> 3.1302843 | ... AA31: =AA28*AA30 -> 12.396275 | AB31: =SUM(D31:O31) -> 31.419535 | AC31: =SUM(P31:AA31) -> 107.80941 | AD31: =SUM(C31:AA31) -> 139.22895
A32: Total pembeli baru (permintaan) | B32: orang | D32: =D24+D26+D31 -> 34.960714 | E32: =E24+E26+E31 -> 36.159427 | F32: =F24+F26+F31 -> 37.462435 | G32: =G24+G26+G31 -> 96.004066 | H32: =H24+H26+H31 -> 97.54273 | I32: =I24+I26+I31 -> 99.173954 | J32: =J24+J26+J31 -> 100.89413 | K32: =K24+K26+K31 -> 102.70086 | ... AA32: =AA24+AA26+AA31 -> 173.82675 | AB32: =SUM(D32:O32) -> 1035.4764 | AC32: =SUM(P32:AA32) -> 1879.5069 | AD32: =SUM(C32:AA32) -> 2914.9832
A33: Permintaan transaksi | B33: transaksi | D33: =D32+D27*Asumsi!$D$89 -> 38.560714 | E33: =E32+E27*Asumsi!$D$89 -> 40.819226 | F33: =F32+F27*Asumsi!$D$89 -> 43.471613 | G33: =G32+G27*Asumsi!$D$89 -> 103.59337 | H33: =H32+H27*Asumsi!$D$89 -> 107.16424 | I33: =I32+I27*Asumsi!$D$89 -> 111.01263 | J33: =J32+J27*Asumsi!$D$89 -> 115.10027 | K33: =K32+K27*Asumsi!$D$89 -> 119.39571 | ... AA33: =AA32+AA27*Asumsi!$D$89 -> 239.94022 | AB33: =SUM(D33:O33) -> 1203.0472 | AC33: =SUM(P33:AA33) -> 2454.4904 | AD33: =SUM(C33:AA33) -> 3657.5376
A34: Transaksi dibayar = MIN(permintaan, kapasitas) | B34: transaksi | D34: =MIN(D33,D22) -> 21.75 | E34: =MIN(E33,E22) -> 28.4625 | F34: =MIN(F33,F22) -> 35.151375 | G34: =MIN(G33,G22) -> 41.830286 | H34: =MIN(H33,H22) -> 48.512711 | I34: =MIN(I33,I22) -> 55.211972 | J34: =MIN(J33,J22) -> 61.941266 | K34: =MIN(K33,K22) -> 68.713691 | ... AA34: =MIN(AA33,AA22) -> 193.6561 | AB34: =SUM(D34:O34) -> 705.47065 | AC34: =SUM(P34:AA34) -> 1762.4541 | AD34: =SUM(C34:AA34) -> 2467.9248
A35: Fill rate (likuiditas) | B35: % | D35: =IF(D33>0,D34/D33,0) -> 0.56404557 | E35: =IF(E33>0,E34/E33,0) -> 0.69728172 | F35: =IF(F33>0,F34/F33,0) -> 0.80860527 | G35: =IF(G33>0,G34/G33,0) -> 0.40379307 | H35: =IF(H33>0,H34/H33,0) -> 0.45269495 | I35: =IF(I33>0,I34/I33,0) -> 0.49734858 | J35: =IF(J33>0,J34/J33,0) -> 0.53815049 | K35: =IF(K33>0,K34/K33,0) -> 0.57551221 | ... AD35: =IF(AD33>0,AD34/AD33,0) -> 0.67475035
A36: Basis pembeli (akhir bulan) | B36: orang | C36: =Asumsi!$D$81 -> 50 | D36: =D27+D32*D35 -> 64.719436 | E36: =E27+E32*E35 -> 83.460799 | F36: =F27+F32*F35 -> 105.40704 | G36: =G27+G32*G35 -> 133.63211 | H36: =H27+H32*H35 -> 164.426 | I36: =I27+I32*I35 -> 197.30743 | J36: =J27+J32*J35 -> 231.87291 | K36: =K27+K32*K35 -> 267.79122 | ... AA36: =AA27+AA32*AA35 -> 966.71415 | AB36: =O36 -> 420.4844 | AC36: =AA36 -> 966.71415 | AD36: =AA36 -> 966.71415
A37: Transaksi batal setelah bayar | B37: transaksi | D37: =D34*Asumsi!$D$65 -> 1.74 | E37: =E34*Asumsi!$D$65 -> 2.277 | F37: =F34*Asumsi!$D$65 -> 2.81211 | G37: =G34*Asumsi!$D$65 -> 3.3464229 | H37: =H34*Asumsi!$D$65 -> 3.8810169 | I37: =I34*Asumsi!$D$65 -> 4.4169578 | J37: =J34*Asumsi!$D$65 -> 4.9553013 | K37: =K34*Asumsi!$D$65 -> 5.4970953 | ... AA37: =AA34*Asumsi!$D$65 -> 15.492488 | AB37: =SUM(D37:O37) -> 56.437652 | AC37: =SUM(P37:AA37) -> 140.99633 | AD37: =SUM(C37:AA37) -> 197.43398
A38: Transaksi selesai (COMPLETED) | B38: transaksi | D38: =D34-D37 -> 20.01 | E38: =E34-E37 -> 26.1855 | F38: =F34-F37 -> 32.339265 | G38: =G34-G37 -> 38.483863 | H38: =H34-H37 -> 44.631694 | I38: =I34-I37 -> 50.795015 | J38: =J34-J37 -> 56.985965 | K38: =K34-K37 -> 63.216596 | ... AA38: =AA34-AA37 -> 178.16361 | AB38: =SUM(D38:O38) -> 649.033 | AC38: =SUM(P38:AA38) -> 1621.4578 | AD38: =SUM(C38:AA38) -> 2270.4908
A39: Sisi pembatas | B39: teks | D39: =IF(D33>D22,"Pasokan","Permintaan") -> Pasokan | E39: =IF(E33>E22,"Pasokan","Permintaan") -> Pasokan | F39: =IF(F33>F22,"Pasokan","Permintaan") -> Pasokan | G39: =IF(G33>G22,"Pasokan","Permintaan") -> Pasokan | H39: =IF(H33>H22,"Pasokan","Permintaan") -> Pasokan | I39: =IF(I33>I22,"Pasokan","Permintaan") -> Pasokan | J39: =IF(J33>J22,"Pasokan","Permintaan") -> Pasokan | K39: =IF(K33>K22,"Pasokan","Permintaan") -> Pasokan | ... AA39: =IF(AA33>AA22,"Pasokan","Permintaan") -> Pasokan
A40: Nilai & pendapatan
A41: GMV bruto (Σ TOTAL transaksi selesai) | B41: Rp | D41: =D38*'Unit Economics'!$C$18 -> 43788237 | E41: =E38*'Unit Economics'!$C$18 -> 57302193 | F41: =F38*'Unit Economics'!$C$18 -> 70768585 | G41: =G38*'Unit Economics'!$C$18 -> 84214919 | H41: =H38*'Unit Economics'!$C$18 -> 97668326 | I41: =I38*'Unit Economics'!$C$18 -> 1.1115563e+08 | J41: =J38*'Unit Economics'!$C$18 -> 1.2470339e+08 | K41: =K38*'Unit Economics'!$C$18 -> 1.3833799e+08 | ... AA41: =AA38*'Unit Economics'!$C$18 -> 3.8987858e+08 | AB41: =SUM(D41:O41) -> 1.4202904e+09 | AC41: =SUM(P41:AA41) -> 3.5482647e+09 | AD41: =SUM(C41:AA41) -> 4.9685551e+09
A42: Nilai barang (pass-through) | B42: Rp | D42: =D38*'Unit Economics'!$C$8 -> 30015000 | E42: =E38*'Unit Economics'!$C$8 -> 39278250 | F42: =F38*'Unit Economics'!$C$8 -> 48508898 | G42: =G38*'Unit Economics'!$C$8 -> 57725795 | H42: =H38*'Unit Economics'!$C$8 -> 66947541 | I42: =I38*'Unit Economics'!$C$8 -> 76192522 | J42: =J38*'Unit Economics'!$C$8 -> 85478948 | K42: =K38*'Unit Economics'!$C$8 -> 94824894 | ... AA42: =AA38*'Unit Economics'!$C$8 -> 2.6724541e+08 | AB42: =SUM(D42:O42) -> 9.735495e+08 | AC42: =SUM(P42:AA42) -> 2.4321867e+09 | AD42: =SUM(C42:AA42) -> 3.4057362e+09
A43: Pendapatan bruto platform (platform + protection fee) | B43: Rp | D43: =D38*'Unit Economics'!$C$47 -> 1950975 | E43: =E38*'Unit Economics'!$C$47 -> 2553086.2 | F43: =F38*'Unit Economics'!$C$47 -> 3153078.3 | G43: =G38*'Unit Economics'!$C$47 -> 3752176.7 | H43: =H38*'Unit Economics'!$C$47 -> 4351590.2 | I43: =I38*'Unit Economics'!$C$47 -> 4952513.9 | J43: =J38*'Unit Economics'!$C$47 -> 5556131.6 | K43: =K38*'Unit Economics'!$C$47 -> 6163618.1 | ... AA43: =AA38*'Unit Economics'!$C$47 -> 17370952 | AB43: =SUM(D43:O43) -> 63280718 | AC43: =SUM(P43:AA43) -> 1.5809213e+08 | AD43: =SUM(C43:AA43) -> 2.2137285e+08
A44: (−) Promo platform fee gratis | B44: Rp | D44: =-D38*IF(D$5<=6,Asumsi!$D$68,Asumsi!$D$69)*'Unit Economics'!$C$13 -> -225112.5 | E44: =-E38*IF(E$5<=6,Asumsi!$D$68,Asumsi!$D$69)*'Unit Economics'!$C$13 -> -294586.88 | F44: =-F38*IF(F$5<=6,Asumsi!$D$68,Asumsi!$D$69)*'Unit Economics'!$C$13 -> -363816.73 | G44: =-G38*IF(G$5<=6,Asumsi!$D$68,Asumsi!$D$69)*'Unit Economics'!$C$13 -> -432943.46 | H44: =-H38*IF(H$5<=6,Asumsi!$D$68,Asumsi!$D$69)*'Unit Economics'!$C$13 -> -502106.56 | I44: =-I38*IF(I$5<=6,Asumsi!$D$68,Asumsi!$D$69)*'Unit Economics'!$C$13 -> -571443.91 | J44: =-J38*IF(J$5<=6,Asumsi!$D$68,Asumsi!$D$69)*'Unit Economics'!$C$13 -> -213697.37 | K44: =-K38*IF(K$5<=6,Asumsi!$D$68,Asumsi!$D$69)*'Unit Economics'!$C$13 -> -237062.24 | ... AA44: =-AA38*IF(AA$5<=6,Asumsi!$D$68,Asumsi!$D$69)*'Unit Economics'!$C$13 -> -668113.53 | AB44: =SUM(D44:O44) -> -4027213.8 | AC44: =SUM(P44:AA44) -> -6080466.7 | AD44: =SUM(C44:AA44) -> -10107680
A45: (−) Credit referral pembeli ditebus (cap per perujuk) | B45: Rp | D45: =-D29*D30 -> -15356.25 | E45: =-E29*E30 -> -19876.957 | F45: =-F29*F30 -> -25632.898 | G45: =-G29*G30 -> -32373.138 | H45: =-H29*H30 -> -41041.763 | I45: =-I29*I30 -> -50499.337 | J45: =-J29*J30 -> -60598.044 | K45: =-K29*K30 -> -71213.969 | ... AA45: =-AA29*AA30 -> -282015.26 | AB45: =SUM(D45:O45) -> -714794.43 | AC45: =SUM(P45:AA45) -> -2452664.1 | AD45: =SUM(C45:AA45) -> -3167458.5
A46: (−) Credit referral traveler ditebus | B46: Rp | D46: =-D19*Asumsi!$D$100*Asumsi!$D$101*MIN(Asumsi!$D$99,Asumsi!$D$94/Asumsi!$D$98)*Asumsi!$D$102 -> -30000 | E46: =-E19*Asumsi!$D$100*Asumsi!$D$101*MIN(Asumsi!$D$99,Asumsi!$D$94/Asumsi!$D$98)*Asumsi!$D$102 -> -31200 | F46: =-F19*Asumsi!$D$100*Asumsi!$D$101*MIN(Asumsi!$D$99,Asumsi!$D$94/Asumsi!$D$98)*Asumsi!$D$102 -> -32448 | G46: =-G19*Asumsi!$D$100*Asumsi!$D$101*MIN(Asumsi!$D$99,Asumsi!$D$94/Asumsi!$D$98)*Asumsi!$D$102 -> -33745.92 | H46: =-H19*Asumsi!$D$100*Asumsi!$D$101*MIN(Asumsi!$D$99,Asumsi!$D$94/Asumsi!$D$98)*Asumsi!$D$102 -> -35095.757 | I46: =-I19*Asumsi!$D$100*Asumsi!$D$101*MIN(Asumsi!$D$99,Asumsi!$D$94/Asumsi!$D$98)*Asumsi!$D$102 -> -36499.587 | J46: =-J19*Asumsi!$D$100*Asumsi!$D$101*MIN(Asumsi!$D$99,Asumsi!$D$94/Asumsi!$D$98)*Asumsi!$D$102 -> -37959.571 | K46: =-K19*Asumsi!$D$100*Asumsi!$D$101*MIN(Asumsi!$D$99,Asumsi!$D$94/Asumsi!$D$98)*Asumsi!$D$102 -> -39477.953 | ... AA46: =-AA19*Asumsi!$D$100*Asumsi!$D$101*MIN(Asumsi!$D$99,Asumsi!$D$94/Asumsi!$D$98)*Asumsi!$D$102 -> -73941.466 | AB46: =SUM(D46:O46) -> -450774.16 | AC46: =SUM(P46:AA46) -> -721703.96 | AD46: =SUM(C46:AA46) -> -1172478.1
A47: Pendapatan bersih | B47: Rp | C47: =SUM(C43:C46) -> 0 | D47: =SUM(D43:D46) -> 1680506.2 | E47: =SUM(E43:E46) -> 2207422.4 | F47: =SUM(F43:F46) -> 2731180.7 | G47: =SUM(G43:G46) -> 3253114.2 | H47: =SUM(H43:H46) -> 3773346.1 | I47: =SUM(I43:I46) -> 4294071.1 | J47: =SUM(J43:J46) -> 5243876.6 | ... AA47: =SUM(AA43:AA46) -> 16346882 | AB47: =SUM(D47:O47) -> 58087935 | AC47: =SUM(P47:AA47) -> 1.488373e+08 | AD47: =SUM(C47:AA47) -> 2.0692524e+08
A48: Take rate bruto (÷ GMV) | B48: % | D48: =IF(D41>0,D43/D41,0) -> 0.044554774 | E48: =IF(E41>0,E43/E41,0) -> 0.044554774 | F48: =IF(F41>0,F43/F41,0) -> 0.044554774 | G48: =IF(G41>0,G43/G41,0) -> 0.044554774 | H48: =IF(H41>0,H43/H41,0) -> 0.044554774 | I48: =IF(I41>0,I43/I41,0) -> 0.044554774 | J48: =IF(J41>0,J43/J41,0) -> 0.044554774 | K48: =IF(K41>0,K43/K41,0) -> 0.044554774 | ... AD48: =IF(AD41>0,AD43/AD41,0) -> 0.044554774
A49: Take rate bersih (÷ GMV) | B49: % | D49: =IF(D41>0,D47/D41,0) -> 0.03837803 | E49: =IF(E41>0,E47/E41,0) -> 0.038522477 | F49: =IF(F41>0,F47/F41,0) -> 0.038593123 | G49: =IF(G41>0,G47/G41,0) -> 0.038628716 | H49: =IF(H41>0,H47/H41,0) -> 0.038634287 | I49: =IF(I41>0,I47/I41,0) -> 0.038631162 | J49: =IF(J41>0,J47/J41,0) -> 0.042050793 | K49: =IF(K41>0,K47/K41,0) -> 0.042040973 | ... AD49: =IF(AD41>0,AD47/AD41,0) -> 0.041646964
A50: Credit referral per transaksi selesai | B50: Rp/trx | D50: =IF(D38>0,-(D45+D46)/D38,0) -> 2266.6792 | E50: =IF(E38>0,-(E45+E46)/E38,0) -> 1950.5817 | F50: =IF(F38>0,-(F45+F46)/F38,0) -> 1795.987 | G50: =IF(G38>0,-(G45+G46)/G38,0) -> 1718.0982 | H50: =IF(H38>0,-(H45+H46)/H38,0) -> 1705.907 | I50: =IF(I38>0,-(I45+I46)/I38,0) -> 1712.7453 | J50: =IF(J38>0,-(J45+J46)/J38,0) -> 1729.5068 | K50: =IF(K38>0,-(K45+K46)/K38,0) -> 1750.9947 | ... AD50: =IF(AD38>0,-(AD45+AD46)/AD38,0) -> 1911.4531
A51: Biaya variabel
A52: Subsidi kanal pembayaran (biaya Xendit − dibebankan) | B52: Rp | D52: =D38*'Unit Economics'!$C$35 -> 292902.38 | E52: =E38*'Unit Economics'!$C$35 -> 383298.11 | F52: =F38*'Unit Economics'!$C$35 -> 473375.69 | G52: =G38*'Unit Economics'!$C$35 -> 563319.09 | H52: =H38*'Unit Economics'!$C$35 -> 653309.81 | I52: =I38*'Unit Economics'!$C$35 -> 743527.26 | J52: =J38*'Unit Economics'!$C$35 -> 834149.16 | K52: =K38*'Unit Economics'!$C$35 -> 925351.89 | ... AA52: =AA38*'Unit Economics'!$C$35 -> 2607923.3 | AB52: =SUM(D52:O52) -> 9500415.3 | AC52: =SUM(P52:AA52) -> 23734575 | AD52: =SUM(C52:AA52) -> 33234990
A53: Biaya payout ke traveler | B53: Rp | D53: =-D38*'Unit Economics'!$C$52 -> 547513.62 | E53: =-E38*'Unit Economics'!$C$52 -> 716487.65 | F53: =-F38*'Unit Economics'!$C$52 -> 884866.97 | G53: =-G38*'Unit Economics'!$C$52 -> 1052995.5 | H53: =-H38*'Unit Economics'!$C$52 -> 1221212.4 | I53: =-I38*'Unit Economics'!$C$52 -> 1389853.2 | J53: =-J38*'Unit Economics'!$C$52 -> 1559250 | K53: =-K38*'Unit Economics'!$C$52 -> 1729732.5 | ... AA53: =-AA38*'Unit Economics'!$C$52 -> 4874912.7 | AB53: =SUM(D53:O53) -> 17758841 | AC53: =SUM(P53:AA53) -> 44366328 | AD53: =SUM(C53:AA53) -> 62125169
A54: Klaim JastipKita Protection | B54: Rp | D54: =-D38*'Unit Economics'!$C$53 -> 270135 | E54: =-E38*'Unit Economics'!$C$53 -> 353504.25 | F54: =-F38*'Unit Economics'!$C$53 -> 436580.08 | G54: =-G38*'Unit Economics'!$C$53 -> 519532.16 | H54: =-H38*'Unit Economics'!$C$53 -> 602527.87 | I54: =-I38*'Unit Economics'!$C$53 -> 685732.7 | J54: =-J38*'Unit Economics'!$C$53 -> 769310.53 | K54: =-K38*'Unit Economics'!$C$53 -> 853424.05 | ... AA54: =-AA38*'Unit Economics'!$C$53 -> 2405208.7 | AB54: =SUM(D54:O54) -> 8761945.5 | AC54: =SUM(P54:AA54) -> 21889680 | AD54: =SUM(C54:AA54) -> 30651626
A55: CS & operasional variabel | B55: Rp | D55: =-D38*'Unit Economics'!$C$54 -> 250125 | E55: =-E38*'Unit Economics'!$C$54 -> 327318.75 | F55: =-F38*'Unit Economics'!$C$54 -> 404240.81 | G55: =-G38*'Unit Economics'!$C$54 -> 481048.29 | H55: =-H38*'Unit Economics'!$C$54 -> 557896.18 | I55: =-I38*'Unit Economics'!$C$54 -> 634937.68 | J55: =-J38*'Unit Economics'!$C$54 -> 712324.56 | K55: =-K38*'Unit Economics'!$C$54 -> 790207.45 | ... AA55: =-AA38*'Unit Economics'!$C$54 -> 2227045.1 | AB55: =SUM(D55:O55) -> 8112912.5 | AC55: =SUM(P55:AA55) -> 20268222 | AD55: =SUM(C55:AA55) -> 28381135
A56: Chargeback kartu | B56: Rp | D56: =-D38*'Unit Economics'!$C$55 -> 7163.58 | E56: =-E38*'Unit Economics'!$C$55 -> 9374.409 | F56: =-F38*'Unit Economics'!$C$55 -> 11577.457 | G56: =-G38*'Unit Economics'!$C$55 -> 13777.223 | H56: =-H38*'Unit Economics'!$C$55 -> 15978.147 | I56: =-I38*'Unit Economics'!$C$55 -> 18184.615 | J56: =-J38*'Unit Economics'!$C$55 -> 20400.975 | K56: =-K38*'Unit Economics'!$C$55 -> 22631.541 | ... AA56: =-AA38*'Unit Economics'!$C$55 -> 63782.572 | AB56: =SUM(D56:O56) -> 232353.81 | AC56: =SUM(P56:AA56) -> 580481.89 | AD56: =SUM(C56:AA56) -> 812835.7
A57: Biaya transaksi batal (Xendit hangus + refund via payout) | B57: Rp | D57: =D37*'Unit Economics'!$C$63 -> 81724.32 | E57: =E37*'Unit Economics'!$C$63 -> 106946.14 | F57: =F37*'Unit Economics'!$C$63 -> 132079.18 | G57: =G37*'Unit Economics'!$C$63 -> 157174.79 | H57: =H37*'Unit Economics'!$C$63 -> 182283.6 | I57: =I37*'Unit Economics'!$C$63 -> 207455.67 | J57: =J37*'Unit Economics'!$C$63 -> 232740.59 | K57: =K37*'Unit Economics'!$C$63 -> 258187.57 | ... AA57: =AA37*'Unit Economics'!$C$63 -> 727651.17 | AB57: =SUM(D57:O57) -> 2650763.7 | AC57: =SUM(P57:AA57) -> 6622315.6 | AD57: =SUM(C57:AA57) -> 9273079.3
A58: Onboarding (OTP pembeli baru, e-KYC + penny-drop traveler baru) | B58: Rp | C58: =C36*Asumsi!$D$71*Asumsi!$D$70*Asumsi!$D$12+C19*(Asumsi!$D$72+'Unit Economics'!$C$64) -> 1530584.6 | D58: =D32*Asumsi!$D$71*Asumsi!$D$70*Asumsi!$D$12+D19*(Asumsi!$D$72+'Unit Economics'!$C$64) -> 1001617.1 | E58: =E32*Asumsi!$D$71*Asumsi!$D$70*Asumsi!$D$12+E19*(Asumsi!$D$72+'Unit Economics'!$C$64) -> 1036943.4 | F58: =F32*Asumsi!$D$71*Asumsi!$D$70*Asumsi!$D$12+F19*(Asumsi!$D$72+'Unit Economics'!$C$64) -> 1075019.6 | G58: =G32*Asumsi!$D$71*Asumsi!$D$70*Asumsi!$D$12+G19*(Asumsi!$D$72+'Unit Economics'!$C$64) -> 2471408.2 | H58: =H32*Asumsi!$D$71*Asumsi!$D$70*Asumsi!$D$12+H19*(Asumsi!$D$72+'Unit Economics'!$C$64) -> 2515659.9 | I58: =I32*Asumsi!$D$71*Asumsi!$D$70*Asumsi!$D$12+I19*(Asumsi!$D$72+'Unit Economics'!$C$64) -> 2562417.4 | J58: =J32*Asumsi!$D$71*Asumsi!$D$70*Asumsi!$D$12+J19*(Asumsi!$D$72+'Unit Economics'!$C$64) -> 2611607.8 | K58: =K32*Asumsi!$D$71*Asumsi!$D$70*Asumsi!$D$12+K19*(Asumsi!$D$72+'Unit Economics'!$C$64) -> 2663186.7 | ... AA58: =AA32*Asumsi!$D$71*Asumsi!$D$70*Asumsi!$D$12+AA19*(Asumsi!$D$72+'Unit Economics'!$C$64) -> 4548460.6 | AB58: =SUM(D58:O58) -> 27154085 | AC58: =SUM(P58:AA58) -> 48733978 | AD58: =SUM(C58:AA58) -> 77418647
A59: Total biaya variabel | B59: Rp | C59: =SUM(C52:C58) -> 1530584.6 | D59: =SUM(D52:D58) -> 2451181 | E59: =SUM(E52:E58) -> 2933872.7 | F59: =SUM(F52:F58) -> 3417739.8 | G59: =SUM(G52:G58) -> 5259255.2 | H59: =SUM(H52:H58) -> 5748867.9 | I59: =SUM(I52:I58) -> 6242108.5 | J59: =SUM(J52:J58) -> 6739783.6 | ... AA59: =SUM(AA52:AA58) -> 17454984 | AB59: =SUM(D59:O59) -> 74171317 | AC59: =SUM(P59:AA59) -> 1.6619558e+08 | AD59: =SUM(C59:AA59) -> 2.4189748e+08
A60: Margin kontribusi | B60: Rp | C60: =C47-C59 -> -1530584.6 | D60: =D47-D59 -> -770674.77 | E60: =E47-E59 -> -726450.29 | F60: =F47-F59 -> -686559.1 | G60: =G47-G59 -> -2006141.1 | H60: =H47-H59 -> -1975521.8 | I60: =I47-I59 -> -1948037.5 | J60: =J47-J59 -> -1495907 | ... AA60: =AA47-AA59 -> -1108102.5 | AB60: =SUM(D60:O60) -> -16083381 | AC60: =SUM(P60:AA60) -> -17358281 | AD60: =SUM(C60:AA60) -> -34972247
A61: Margin kontribusi per transaksi selesai | B61: Rp/trx | D61: =IF(D38>0,D60/D38,0) -> -38514.481 | E61: =IF(E38>0,E60/E38,0) -> -27742.464 | F61: =IF(F38>0,F60/F38,0) -> -21229.892 | G61: =IF(G38>0,G60/G38,0) -> -52129.409 | H61: =IF(H38>0,H60/H38,0) -> -44262.756 | I61: =IF(I38>0,I60/I38,0) -> -38350.958 | J61: =IF(J38>0,J60/J38,0) -> -26250.445 | K61: =IF(K38>0,K60/K38,0) -> -22570.935 | ... AD61: =IF(AD38>0,AD60/AD38,0) -> -15402.946
A62: Biaya akuisisi & tetap
A63: Marketing (kas) | B63: Rp | D63: =D25 -> 5000000 | E63: =E25 -> 5000000 | F63: =F25 -> 5000000 | G63: =G25 -> 25000000 | H63: =H25 -> 25000000 | I63: =I25 -> 25000000 | J63: =J25 -> 25000000 | K63: =K25 -> 25000000 | ... AA63: =AA25 -> 35000000 | AB63: =SUM(D63:O63) -> 240000000 | AC63: =SUM(P63:AA63) -> 420000000 | AD63: =SUM(C63:AA63) -> 660000000
A64: SDM inti (termasuk overhead) | B64: Rp | C64: =Asumsi!$D$114*(1+Asumsi!$D$116)*Asumsi!$D$11 -> 216000000 | D64: =IF(D$5<=12,Asumsi!$D$114,Asumsi!$D$115)*(1+Asumsi!$D$116) -> 72000000 | E64: =IF(E$5<=12,Asumsi!$D$114,Asumsi!$D$115)*(1+Asumsi!$D$116) -> 72000000 | F64: =IF(F$5<=12,Asumsi!$D$114,Asumsi!$D$115)*(1+Asumsi!$D$116) -> 72000000 | G64: =IF(G$5<=12,Asumsi!$D$114,Asumsi!$D$115)*(1+Asumsi!$D$116) -> 72000000 | H64: =IF(H$5<=12,Asumsi!$D$114,Asumsi!$D$115)*(1+Asumsi!$D$116) -> 72000000 | I64: =IF(I$5<=12,Asumsi!$D$114,Asumsi!$D$115)*(1+Asumsi!$D$116) -> 72000000 | J64: =IF(J$5<=12,Asumsi!$D$114,Asumsi!$D$115)*(1+Asumsi!$D$116) -> 72000000 | K64: =IF(K$5<=12,Asumsi!$D$114,Asumsi!$D$115)*(1+Asumsi!$D$116) -> 72000000 | ... AA64: =IF(AA$5<=12,Asumsi!$D$114,Asumsi!$D$115)*(1+Asumsi!$D$116) -> 102000000 | AB64: =SUM(D64:O64) -> 864000000 | AC64: =SUM(P64:AA64) -> 1224000000 | AD64: =SUM(C64:AA64) -> 2304000000
A65: Infrastruktur & SaaS | B65: Rp | C65: =(Asumsi!$D$108*Asumsi!$D$12+Asumsi!$D$113)*Asumsi!$D$11 -> 7612530 | D65: =(Asumsi!$D$108+IF(D38>=Asumsi!$D$110,Asumsi!$D$109,0)+IF(D38>=Asumsi!$D$112,Asumsi!$D$111,0))*Asumsi!$D$12+Asumsi!$D$113 -> 2537510 | E65: =(Asumsi!$D$108+IF(E38>=Asumsi!$D$110,Asumsi!$D$109,0)+IF(E38>=Asumsi!$D$112,Asumsi!$D$111,0))*Asumsi!$D$12+Asumsi!$D$113 -> 2537510 | F65: =(Asumsi!$D$108+IF(F38>=Asumsi!$D$110,Asumsi!$D$109,0)+IF(F38>=Asumsi!$D$112,Asumsi!$D$111,0))*Asumsi!$D$12+Asumsi!$D$113 -> 2537510 | G65: =(Asumsi!$D$108+IF(G38>=Asumsi!$D$110,Asumsi!$D$109,0)+IF(G38>=Asumsi!$D$112,Asumsi!$D$111,0))*Asumsi!$D$12+Asumsi!$D$113 -> 2537510 | H65: =(Asumsi!$D$108+IF(H38>=Asumsi!$D$110,Asumsi!$D$109,0)+IF(H38>=Asumsi!$D$112,Asumsi!$D$111,0))*Asumsi!$D$12+Asumsi!$D$113 -> 2537510 | I65: =(Asumsi!$D$108+IF(I38>=Asumsi!$D$110,Asumsi!$D$109,0)+IF(I38>=Asumsi!$D$112,Asumsi!$D$111,0))*Asumsi!$D$12+Asumsi!$D$113 -> 2537510 | J65: =(Asumsi!$D$108+IF(J38>=Asumsi!$D$110,Asumsi!$D$109,0)+IF(J38>=Asumsi!$D$112,Asumsi!$D$111,0))*Asumsi!$D$12+Asumsi!$D$113 -> 2537510 | K65: =(Asumsi!$D$108+IF(K38>=Asumsi!$D$110,Asumsi!$D$109,0)+IF(K38>=Asumsi!$D$112,Asumsi!$D$111,0))*Asumsi!$D$12+Asumsi!$D$113 -> 2537510 | ... AA65: =(Asumsi!$D$108+IF(AA38>=Asumsi!$D$110,Asumsi!$D$109,0)+IF(AA38>=Asumsi!$D$112,Asumsi!$D$111,0))*Asumsi!$D$12+Asumsi!$D$113 -> 2537510 | AB65: =SUM(D65:O65) -> 30450120 | AC65: =SUM(P65:AA65) -> 30450120 | AD65: =SUM(C65:AA65) -> 68512770
A66: Kepatuhan berulang | B66: Rp | D66: =Asumsi!$D$117 -> 10000000 | E66: =Asumsi!$D$117 -> 10000000 | F66: =Asumsi!$D$117 -> 10000000 | G66: =Asumsi!$D$117 -> 10000000 | H66: =Asumsi!$D$117 -> 10000000 | I66: =Asumsi!$D$117 -> 10000000 | J66: =Asumsi!$D$117 -> 10000000 | K66: =Asumsi!$D$117 -> 10000000 | ... AA66: =Asumsi!$D$117 -> 10000000 | AB66: =SUM(D66:O66) -> 120000000 | AC66: =SUM(P66:AA66) -> 120000000 | AD66: =SUM(C66:AA66) -> 240000000
A67: Kantor & umum | B67: Rp | D67: =Asumsi!$D$118 -> 2500000 | E67: =Asumsi!$D$118 -> 2500000 | F67: =Asumsi!$D$118 -> 2500000 | G67: =Asumsi!$D$118 -> 2500000 | H67: =Asumsi!$D$118 -> 2500000 | I67: =Asumsi!$D$118 -> 2500000 | J67: =Asumsi!$D$118 -> 2500000 | K67: =Asumsi!$D$118 -> 2500000 | ... AA67: =Asumsi!$D$118 -> 2500000 | AB67: =SUM(D67:O67) -> 30000000 | AC67: =SUM(P67:AA67) -> 30000000 | AD67: =SUM(C67:AA67) -> 60000000
A68: Akun toko aplikasi | B68: Rp | C68: =(Asumsi!$D$120+Asumsi!$D$121)*Asumsi!$D$12 -> 2221708 | D68: =IF(MOD(D$5,12)=0,Asumsi!$D$121*Asumsi!$D$12,0) -> 0 | E68: =IF(MOD(E$5,12)=0,Asumsi!$D$121*Asumsi!$D$12,0) -> 0 | F68: =IF(MOD(F$5,12)=0,Asumsi!$D$121*Asumsi!$D$12,0) -> 0 | G68: =IF(MOD(G$5,12)=0,Asumsi!$D$121*Asumsi!$D$12,0) -> 0 | H68: =IF(MOD(H$5,12)=0,Asumsi!$D$121*Asumsi!$D$12,0) -> 0 | I68: =IF(MOD(I$5,12)=0,Asumsi!$D$121*Asumsi!$D$12,0) -> 0 | J68: =IF(MOD(J$5,12)=0,Asumsi!$D$121*Asumsi!$D$12,0) -> 0 | K68: =IF(MOD(K$5,12)=0,Asumsi!$D$121*Asumsi!$D$12,0) -> 0 | ... AA68: =IF(MOD(AA$5,12)=0,Asumsi!$D$121*Asumsi!$D$12,0) -> 1773783 | AB68: =SUM(D68:O68) -> 1773783 | AC68: =SUM(P68:AA68) -> 1773783 | AD68: =SUM(C68:AA68) -> 5769274
A69: Pendirian, legal, pentest (sekali) | B69: Rp | C69: =Asumsi!$D$123+Asumsi!$D$124+Asumsi!$D$125+Asumsi!$D$126+Asumsi!$D$127+Asumsi!$D$128+Asumsi!$D$129+Asumsi!$D$130 -> 225000000 | D69: =IF(D$5=13,Asumsi!$D$131,0) -> 0 | E69: =IF(E$5=13,Asumsi!$D$131,0) -> 0 | F69: =IF(F$5=13,Asumsi!$D$131,0) -> 0 | G69: =IF(G$5=13,Asumsi!$D$131,0) -> 0 | H69: =IF(H$5=13,Asumsi!$D$131,0) -> 0 | I69: =IF(I$5=13,Asumsi!$D$131,0) -> 0 | J69: =IF(J$5=13,Asumsi!$D$131,0) -> 0 | K69: =IF(K$5=13,Asumsi!$D$131,0) -> 0 | ... AA69: =IF(AA$5=13,Asumsi!$D$131,0) -> 0 | AB69: =SUM(D69:O69) -> 0 | AC69: =SUM(P69:AA69) -> 35000000 | AD69: =SUM(C69:AA69) -> 260000000
A70: Cadangan tak terduga | B70: Rp | C70: =Asumsi!$D$119*(C64+C65+C66+C67) -> 22361253 | D70: =Asumsi!$D$119*(D64+D65+D66+D67) -> 8703751 | E70: =Asumsi!$D$119*(E64+E65+E66+E67) -> 8703751 | F70: =Asumsi!$D$119*(F64+F65+F66+F67) -> 8703751 | G70: =Asumsi!$D$119*(G64+G65+G66+G67) -> 8703751 | H70: =Asumsi!$D$119*(H64+H65+H66+H67) -> 8703751 | I70: =Asumsi!$D$119*(I64+I65+I66+I67) -> 8703751 | J70: =Asumsi!$D$119*(J64+J65+J66+J67) -> 8703751 | ... AA70: =Asumsi!$D$119*(AA64+AA65+AA66+AA67) -> 11703751 | AB70: =SUM(D70:O70) -> 104445012 | AC70: =SUM(P70:AA70) -> 140445012 | AD70: =SUM(C70:AA70) -> 267251277
A71: Total biaya akuisisi & tetap | B71: Rp | C71: =SUM(C63:C70) -> 473195491 | D71: =SUM(D63:D70) -> 100741261 | E71: =SUM(E63:E70) -> 100741261 | F71: =SUM(F63:F70) -> 100741261 | G71: =SUM(G63:G70) -> 120741261 | H71: =SUM(H63:H70) -> 120741261 | I71: =SUM(I63:I70) -> 120741261 | J71: =SUM(J63:J70) -> 120741261 | ... AA71: =SUM(AA63:AA70) -> 165515044 | AB71: =SUM(D71:O71) -> 1390668915 | AC71: =SUM(P71:AA71) -> 2001668915 | AD71: =SUM(C71:AA71) -> 3865533321
A72: Laba & kas
A73: EBITDA (laba operasi sebelum pajak) | B73: Rp | C73: =C60-C71 -> -4.7472608e+08 | D73: =D60-D71 -> -1.0151194e+08 | E73: =E60-E71 -> -1.0146771e+08 | F73: =F60-F71 -> -1.0142782e+08 | G73: =G60-G71 -> -1.227474e+08 | H73: =H60-H71 -> -1.2271678e+08 | I73: =I60-I71 -> -1.226893e+08 | J73: =J60-J71 -> -1.2223717e+08 | ... AA73: =AA60-AA71 -> -1.6662315e+08 | AB73: =SUM(D73:O73) -> -1.4067523e+09 | AC73: =SUM(P73:AA73) -> -2.0190272e+09 | AD73: =SUM(C73:AA73) -> -3.9005056e+09
A74: Penyesuaian lag penerimaan fee | B74: Rp | D74: =IF(Asumsi!$D$13>=1,C47-D47,0) -> -1680506.2 | E74: =IF(Asumsi!$D$13>=1,D47-E47,0) -> -526916.17 | F74: =IF(Asumsi!$D$13>=1,E47-F47,0) -> -523758.29 | G74: =IF(Asumsi!$D$13>=1,F47-G47,0) -> -521933.45 | H74: =IF(Asumsi!$D$13>=1,G47-H47,0) -> -520231.95 | I74: =IF(Asumsi!$D$13>=1,H47-I47,0) -> -520724.97 | J74: =IF(Asumsi!$D$13>=1,I47-J47,0) -> -949805.53 | K74: =IF(Asumsi!$D$13>=1,J47-K47,0) -> -571987.35 | ... AA74: =IF(Asumsi!$D$13>=1,Z47-AA47,0) -> -781679.09 | AB74: =SUM(D74:O74) -> -8159387.3 | AC74: =SUM(P74:AA74) -> -8187494.3 | AD74: =SUM(C74:AA74) -> -16346882
A75: Arus kas operasi | B75: Rp | C75: =C73+C74 -> -4.7472608e+08 | D75: =D73+D74 -> -1.0319244e+08 | E75: =E73+E74 -> -1.0199463e+08 | F75: =F73+F74 -> -1.0195158e+08 | G75: =G73+G74 -> -1.2326934e+08 | H75: =H73+H74 -> -1.2323701e+08 | I75: =I73+I74 -> -1.2321002e+08 | J75: =J73+J74 -> -1.2318697e+08 | ... AA75: =AA73+AA74 -> -1.6740483e+08 | AB75: =SUM(D75:O75) -> -1.4149117e+09 | AC75: =SUM(P75:AA75) -> -2.0272147e+09 | AD75: =SUM(C75:AA75) -> -3.9168524e+09
A76: Kas kumulatif (mulai 0 = kebutuhan dana) | B76: Rp | C76: =C75 -> -4.7472608e+08 | D76: =C76+D75 -> -5.7791852e+08 | E76: =D76+E75 -> -6.7991315e+08 | F76: =E76+F75 -> -7.8186472e+08 | G76: =F76+G75 -> -9.0513406e+08 | H76: =G76+H75 -> -1.0283711e+09 | I76: =H76+I75 -> -1.1515811e+09 | J76: =I76+J75 -> -1.2747681e+09 | K76: =J76+K75 -> -1.3975082e+09 | ... AA76: =Z76+AA75 -> -3.9168524e+09 | AB76: =O76 -> -1.8896378e+09 | AC76: =AA76 -> -3.9168524e+09 | AD76: =AA76 -> -3.9168524e+09
A77: Penanda bulan EBITDA ≥ 0 (999 = belum) | B77: bulan | D77: =IF(D73>=0,D$5,999) -> 999 | E77: =IF(E73>=0,E$5,999) -> 999 | F77: =IF(F73>=0,F$5,999) -> 999 | G77: =IF(G73>=0,G$5,999) -> 999 | H77: =IF(H73>=0,H$5,999) -> 999 | I77: =IF(I73>=0,I$5,999) -> 999 | J77: =IF(J73>=0,J$5,999) -> 999 | K77: =IF(K73>=0,K$5,999) -> 999 | ... AA77: =IF(AA73>=0,AA$5,999) -> 999
A80: SKENARIO DASAR — input dari Asumsi kolom E, unit economics dari kolom D
A81: Pasokan traveler
A82: Traveler terverifikasi baru (B0 = peserta beta) | B82: orang | C82: =Asumsi!$E$74 -> 20 | D82: =Asumsi!$E$75*(1+Asumsi!$E$76)^(D$5-1) -> 15 | E82: =Asumsi!$E$75*(1+Asumsi!$E$76)^(E$5-1) -> 16.2 | F82: =Asumsi!$E$75*(1+Asumsi!$E$76)^(F$5-1) -> 17.496 | G82: =Asumsi!$E$75*(1+Asumsi!$E$76)^(G$5-1) -> 18.89568 | H82: =Asumsi!$E$75*(1+Asumsi!$E$76)^(H$5-1) -> 20.407334 | I82: =Asumsi!$E$75*(1+Asumsi!$E$76)^(I$5-1) -> 22.039921 | J82: =Asumsi!$E$75*(1+Asumsi!$E$76)^(J$5-1) -> 23.803115 | K82: =Asumsi!$E$75*(1+Asumsi!$E$76)^(K$5-1) -> 25.707364 | ... AA82: =Asumsi!$E$75*(1+Asumsi!$E$76)^(AA$5-1) -> 88.071955 | AB82: =SUM(D82:O82) -> 284.6569 | AC82: =SUM(P82:AA82) -> 716.81449 | AD82: =SUM(C82:AA82) -> 1021.4714
A83: Basis traveler terverifikasi (akhir bulan) | B83: orang | C83: =C82 -> 20 | D83: =C83*(1-Asumsi!$E$77)+D82 -> 34.2 | E83: =D83*(1-Asumsi!$E$77)+E82 -> 49.032 | F83: =E83*(1-Asumsi!$E$77)+F82 -> 64.56672 | G83: =F83*(1-Asumsi!$E$77)+G82 -> 80.879731 | H83: =G83*(1-Asumsi!$E$77)+H82 -> 98.051876 | I83: =H83*(1-Asumsi!$E$77)+I82 -> 116.16972 | J83: =I83*(1-Asumsi!$E$77)+J82 -> 135.32605 | K83: =J83*(1-Asumsi!$E$77)+K82 -> 155.62037 | ... AA83: =Z83*(1-Asumsi!$E$77)+AA82 -> 753.2292 | AB83: =O83 -> 250.43674 | AC83: =AA83 -> 753.2292 | AD83: =AA83 -> 753.2292
A84: Traveler aktif (punya trip) | B84: orang | D84: =D83*Asumsi!$E$78 -> 11.97 | E84: =E83*Asumsi!$E$78 -> 17.1612 | F84: =F83*Asumsi!$E$78 -> 22.598352 | G84: =G83*Asumsi!$E$78 -> 28.307906 | H84: =H83*Asumsi!$E$78 -> 34.318157 | I84: =I83*Asumsi!$E$78 -> 40.659403 | J84: =J83*Asumsi!$E$78 -> 47.364117 | K84: =K83*Asumsi!$E$78 -> 54.46713 | ... AA84: =AA83*Asumsi!$E$78 -> 263.63022 | AB84: =O84 -> 87.652859 | AC84: =AA84 -> 263.63022 | AD84: =AA84 -> 263.63022
A85: Kapasitas pesanan | B85: pesanan | D85: =D84*Asumsi!$E$79 -> 35.91 | E85: =E84*Asumsi!$E$79 -> 51.4836 | F85: =F84*Asumsi!$E$79 -> 67.795056 | G85: =G84*Asumsi!$E$79 -> 84.923718 | H85: =H84*Asumsi!$E$79 -> 102.95447 | I85: =I84*Asumsi!$E$79 -> 121.97821 | J85: =J84*Asumsi!$E$79 -> 142.09235 | K85: =K84*Asumsi!$E$79 -> 163.40139 | ... AA85: =AA84*Asumsi!$E$79 -> 790.89066 | AB85: =SUM(D85:O85) -> 1665.2377 | AC85: =SUM(P85:AA85) -> 6146.0104 | AD85: =SUM(C85:AA85) -> 7811.2481
A86: Permintaan pembeli
A87: Pembeli baru — organik | B87: orang | D87: =Asumsi!$E$82*(1+Asumsi!$E$83)^(D$5-1) -> 30 | E87: =Asumsi!$E$82*(1+Asumsi!$E$83)^(E$5-1) -> 32.4 | F87: =Asumsi!$E$82*(1+Asumsi!$E$83)^(F$5-1) -> 34.992 | G87: =Asumsi!$E$82*(1+Asumsi!$E$83)^(G$5-1) -> 37.79136 | H87: =Asumsi!$E$82*(1+Asumsi!$E$83)^(H$5-1) -> 40.814669 | I87: =Asumsi!$E$82*(1+Asumsi!$E$83)^(I$5-1) -> 44.079842 | J87: =Asumsi!$E$82*(1+Asumsi!$E$83)^(J$5-1) -> 47.60623 | K87: =Asumsi!$E$82*(1+Asumsi!$E$83)^(K$5-1) -> 51.414728 | ... AA87: =Asumsi!$E$82*(1+Asumsi!$E$83)^(AA$5-1) -> 176.14391 | AB87: =SUM(D87:O87) -> 569.31379 | AC87: =SUM(P87:AA87) -> 1433.629 | AD87: =SUM(C87:AA87) -> 2002.9428
A88: Anggaran marketing kas | B88: Rp | D88: =IF(D$5<=3,Asumsi!$E$84,IF(D$5<=12,Asumsi!$E$85,Asumsi!$E$86)) -> 5000000 | E88: =IF(E$5<=3,Asumsi!$E$84,IF(E$5<=12,Asumsi!$E$85,Asumsi!$E$86)) -> 5000000 | F88: =IF(F$5<=3,Asumsi!$E$84,IF(F$5<=12,Asumsi!$E$85,Asumsi!$E$86)) -> 5000000 | G88: =IF(G$5<=3,Asumsi!$E$84,IF(G$5<=12,Asumsi!$E$85,Asumsi!$E$86)) -> 25000000 | H88: =IF(H$5<=3,Asumsi!$E$84,IF(H$5<=12,Asumsi!$E$85,Asumsi!$E$86)) -> 25000000 | I88: =IF(I$5<=3,Asumsi!$E$84,IF(I$5<=12,Asumsi!$E$85,Asumsi!$E$86)) -> 25000000 | J88: =IF(J$5<=3,Asumsi!$E$84,IF(J$5<=12,Asumsi!$E$85,Asumsi!$E$86)) -> 25000000 | K88: =IF(K$5<=3,Asumsi!$E$84,IF(K$5<=12,Asumsi!$E$85,Asumsi!$E$86)) -> 25000000 | ... AA88: =IF(AA$5<=3,Asumsi!$E$84,IF(AA$5<=12,Asumsi!$E$85,Asumsi!$E$86)) -> 35000000 | AB88: =SUM(D88:O88) -> 240000000 | AC88: =SUM(P88:AA88) -> 420000000 | AD88: =SUM(C88:AA88) -> 660000000
A89: Pembeli baru — marketing (anggaran ÷ CAC) | B89: orang | D89: =IF(Asumsi!$E$87>0,D88/Asumsi!$E$87,0) -> 20 | E89: =IF(Asumsi!$E$87>0,E88/Asumsi!$E$87,0) -> 20 | F89: =IF(Asumsi!$E$87>0,F88/Asumsi!$E$87,0) -> 20 | G89: =IF(Asumsi!$E$87>0,G88/Asumsi!$E$87,0) -> 100 | H89: =IF(Asumsi!$E$87>0,H88/Asumsi!$E$87,0) -> 100 | I89: =IF(Asumsi!$E$87>0,I88/Asumsi!$E$87,0) -> 100 | J89: =IF(Asumsi!$E$87>0,J88/Asumsi!$E$87,0) -> 100 | K89: =IF(Asumsi!$E$87>0,K88/Asumsi!$E$87,0) -> 100 | ... AA89: =IF(Asumsi!$E$87>0,AA88/Asumsi!$E$87,0) -> 140 | AB89: =SUM(D89:O89) -> 960 | AC89: =SUM(P89:AA89) -> 1680 | AD89: =SUM(C89:AA89) -> 2640
A90: Basis pembeli retensi (awal bulan) | B90: orang | D90: =C99*(1-Asumsi!$E$88) -> 46 | E90: =D99*(1-Asumsi!$E$88) -> 72.631261 | F90: =E99*(1-Asumsi!$E$88) -> 108.58997 | G90: =F99*(1-Asumsi!$E$88) -> 152.39624 | H90: =G99*(1-Asumsi!$E$88) -> 210.74279 | I90: =H99*(1-Asumsi!$E$88) -> 276.65995 | J90: =I99*(1-Asumsi!$E$88) -> 349.36977 | K90: =J99*(1-Asumsi!$E$88) -> 428.26813 | ... AA90: =Z99*(1-Asumsi!$E$88) -> 2434.6479
A91: Pembeli baru — referral (sebelum cap anggaran) | B91: orang | D91: =D90*Asumsi!$E$95 -> 1.15 | E91: =E90*Asumsi!$E$95 -> 1.8157815 | F91: =F90*Asumsi!$E$95 -> 2.7147494 | G91: =G90*Asumsi!$E$95 -> 3.8099061 | H91: =H90*Asumsi!$E$95 -> 5.2685698 | I91: =I90*Asumsi!$E$95 -> 6.9164988 | J91: =J90*Asumsi!$E$95 -> 8.7342442 | K91: =K90*Asumsi!$E$95 -> 10.706703 | ... AA91: =AA90*Asumsi!$E$95 -> 60.866198 | AB91: =SUM(D91:O91) -> 106.46476 | AC91: =SUM(P91:AA91) -> 495.1565 | AD91: =SUM(C91:AA91) -> 601.62126
A92: Credit referral pembeli sebelum cap anggaran | B92: Rp | D92: =D91*Asumsi!$E$96*(MIN(Asumsi!$E$91,Asumsi!$E$94/Asumsi!$E$98)+Asumsi!$E$92)*Asumsi!$E$97 -> 30187.5 | E92: =E91*Asumsi!$E$96*(MIN(Asumsi!$E$91,Asumsi!$E$94/Asumsi!$E$98)+Asumsi!$E$92)*Asumsi!$E$97 -> 47664.265 | F92: =F91*Asumsi!$E$96*(MIN(Asumsi!$E$91,Asumsi!$E$94/Asumsi!$E$98)+Asumsi!$E$92)*Asumsi!$E$97 -> 71262.171 | G92: =G91*Asumsi!$E$96*(MIN(Asumsi!$E$91,Asumsi!$E$94/Asumsi!$E$98)+Asumsi!$E$92)*Asumsi!$E$97 -> 100010.03 | H92: =H91*Asumsi!$E$96*(MIN(Asumsi!$E$91,Asumsi!$E$94/Asumsi!$E$98)+Asumsi!$E$92)*Asumsi!$E$97 -> 138299.96 | I92: =I91*Asumsi!$E$96*(MIN(Asumsi!$E$91,Asumsi!$E$94/Asumsi!$E$98)+Asumsi!$E$92)*Asumsi!$E$97 -> 181558.09 | J92: =J91*Asumsi!$E$96*(MIN(Asumsi!$E$91,Asumsi!$E$94/Asumsi!$E$98)+Asumsi!$E$92)*Asumsi!$E$97 -> 229273.91 | K92: =K91*Asumsi!$E$96*(MIN(Asumsi!$E$91,Asumsi!$E$94/Asumsi!$E$98)+Asumsi!$E$92)*Asumsi!$E$97 -> 281050.96 | ... AA92: =AA91*Asumsi!$E$96*(MIN(Asumsi!$E$91,Asumsi!$E$94/Asumsi!$E$98)+Asumsi!$E$92)*Asumsi!$E$97 -> 1597737.7 | AB92: =SUM(D92:O92) -> 2794700.1 | AC92: =SUM(P92:AA92) -> 12997858 | AD92: =SUM(C92:AA92) -> 15792558
A93: Faktor cap anggaran referral global | B93: faktor | D93: =IF(AND(Asumsi!$E$103=1,D92>0),MIN(1,Asumsi!$E$104/D92),1) -> 1 | E93: =IF(AND(Asumsi!$E$103=1,E92>0),MIN(1,Asumsi!$E$104/E92),1) -> 1 | F93: =IF(AND(Asumsi!$E$103=1,F92>0),MIN(1,Asumsi!$E$104/F92),1) -> 1 | G93: =IF(AND(Asumsi!$E$103=1,G92>0),MIN(1,Asumsi!$E$104/G92),1) -> 1 | H93: =IF(AND(Asumsi!$E$103=1,H92>0),MIN(1,Asumsi!$E$104/H92),1) -> 1 | I93: =IF(AND(Asumsi!$E$103=1,I92>0),MIN(1,Asumsi!$E$104/I92),1) -> 1 | J93: =IF(AND(Asumsi!$E$103=1,J92>0),MIN(1,Asumsi!$E$104/J92),1) -> 1 | K93: =IF(AND(Asumsi!$E$103=1,K92>0),MIN(1,Asumsi!$E$104/K92),1) -> 1 | ... AA93: =IF(AND(Asumsi!$E$103=1,AA92>0),MIN(1,Asumsi!$E$104/AA92),1) -> 1
A94: Pembeli baru — referral (efektif) | B94: orang | D94: =D91*D93 -> 1.15 | E94: =E91*E93 -> 1.8157815 | F94: =F91*F93 -> 2.7147494 | G94: =G91*G93 -> 3.8099061 | H94: =H91*H93 -> 5.2685698 | I94: =I91*I93 -> 6.9164988 | J94: =J91*J93 -> 8.7342442 | K94: =K91*K93 -> 10.706703 | ... AA94: =AA91*AA93 -> 60.866198 | AB94: =SUM(D94:O94) -> 106.46476 | AC94: =SUM(P94:AA94) -> 495.1565 | AD94: =SUM(C94:AA94) -> 601.62126
A95: Total pembeli baru (permintaan) | B95: orang | D95: =D87+D89+D94 -> 51.15 | E95: =E87+E89+E94 -> 54.215782 | F95: =F87+F89+F94 -> 57.706749 | G95: =G87+G89+G94 -> 141.60127 | H95: =H87+H89+H94 -> 146.08324 | I95: =I87+I89+I94 -> 150.99634 | J95: =J87+J89+J94 -> 156.34047 | K95: =K87+K89+K94 -> 162.12143 | ... AA95: =AA87+AA89+AA94 -> 377.01011 | AB95: =SUM(D95:O95) -> 1635.7786 | AC95: =SUM(P95:AA95) -> 3608.7855 | AD95: =SUM(C95:AA95) -> 5244.564
A96: Permintaan transaksi | B96: transaksi | D96: =D95+D90*Asumsi!$E$89 -> 55.75 | E96: =E95+E90*Asumsi!$E$89 -> 61.478908 | F96: =F95+F90*Asumsi!$E$89 -> 68.565747 | G96: =G95+G90*Asumsi!$E$89 -> 156.84089 | H96: =H95+H90*Asumsi!$E$89 -> 167.15752 | I96: =I95+I90*Asumsi!$E$89 -> 178.66234 | J96: =J95+J90*Asumsi!$E$89 -> 191.27745 | K96: =K95+K90*Asumsi!$E$89 -> 204.94824 | ... AA96: =AA95+AA90*Asumsi!$E$89 -> 620.4749 | AB96: =SUM(D96:O96) -> 2061.6376 | AC96: =SUM(P96:AA96) -> 5589.4115 | AD96: =SUM(C96:AA96) -> 7651.0491
A97: Transaksi dibayar = MIN(permintaan, kapasitas) | B97: transaksi | D97: =MIN(D96,D85) -> 35.91 | E97: =MIN(E96,E85) -> 51.4836 | F97: =MIN(F96,F85) -> 67.795056 | G97: =MIN(G96,G85) -> 84.923718 | H97: =MIN(H96,H85) -> 102.95447 | I97: =MIN(I96,I85) -> 121.97821 | J97: =MIN(J96,J85) -> 142.09235 | K97: =MIN(K96,K85) -> 163.40139 | ... AA97: =MIN(AA96,AA85) -> 620.4749 | AB97: =SUM(D97:O97) -> 1665.2377 | AC97: =SUM(P97:AA97) -> 5505.831 | AD97: =SUM(C97:AA97) -> 7171.0687
A98: Fill rate (likuiditas) | B98: % | D98: =IF(D96>0,D97/D96,0) -> 0.64412556 | E98: =IF(E96>0,E97/E96,0) -> 0.83741891 | F98: =IF(F96>0,F97/F96,0) -> 0.98875983 | G98: =IF(G96>0,G97/G96,0) -> 0.54146414 | H98: =IF(H96>0,H97/H96,0) -> 0.61591289 | I98: =IF(I96>0,I97/I96,0) -> 0.6827304 | J98: =IF(J96>0,J97/J96,0) -> 0.74285992 | K98: =IF(K96>0,K97/K96,0) -> 0.79728123 | ... AD98: =IF(AD96>0,AD97/AD96,0) -> 0.93726607
A99: Basis pembeli (akhir bulan) | B99: orang | C99: =Asumsi!$E$81 -> 50 | D99: =D90+D95*D98 -> 78.947022 | E99: =E90+E95*E98 -> 118.03258 | F99: =F90+F95*F98 -> 165.64809 | G99: =G90+G95*G98 -> 229.06825 | H99: =H90+H95*H98 -> 300.71734 | I99: =I90+I95*I98 -> 379.74975 | J99: =J90+J95*J98 -> 465.50884 | K99: =K90+K95*K98 -> 557.52451 | ... AA99: =AA90+AA95*AA98 -> 2811.658 | AB99: =O99 -> 984.46467 | AC99: =AA99 -> 2811.658 | AD99: =AA99 -> 2811.658
A100: Transaksi batal setelah bayar | B100: transaksi | D100: =D97*Asumsi!$E$65 -> 1.7955 | E100: =E97*Asumsi!$E$65 -> 2.57418 | F100: =F97*Asumsi!$E$65 -> 3.3897528 | G100: =G97*Asumsi!$E$65 -> 4.2461859 | H100: =H97*Asumsi!$E$65 -> 5.1477235 | I100: =I97*Asumsi!$E$65 -> 6.0989104 | J100: =J97*Asumsi!$E$65 -> 7.1046175 | K100: =K97*Asumsi!$E$65 -> 8.1700695 | ... AA100: =AA97*Asumsi!$E$65 -> 31.023745 | AB100: =SUM(D100:O100) -> 83.261885 | AC100: =SUM(P100:AA100) -> 275.29155 | AD100: =SUM(C100:AA100) -> 358.55343
A101: Transaksi selesai (COMPLETED) | B101: transaksi | D101: =D97-D100 -> 34.1145 | E101: =E97-E100 -> 48.90942 | F101: =F97-F100 -> 64.405303 | G101: =G97-G100 -> 80.677532 | H101: =H97-H100 -> 97.806747 | I101: =I97-I100 -> 115.8793 | J101: =J97-J100 -> 134.98773 | K101: =K97-K100 -> 155.23132 | ... AA101: =AA97-AA100 -> 589.45116 | AB101: =SUM(D101:O101) -> 1581.9758 | AC101: =SUM(P101:AA101) -> 5230.5395 | AD101: =SUM(C101:AA101) -> 6812.5153
A102: Sisi pembatas | B102: teks | D102: =IF(D96>D85,"Pasokan","Permintaan") -> Pasokan | E102: =IF(E96>E85,"Pasokan","Permintaan") -> Pasokan | F102: =IF(F96>F85,"Pasokan","Permintaan") -> Pasokan | G102: =IF(G96>G85,"Pasokan","Permintaan") -> Pasokan | H102: =IF(H96>H85,"Pasokan","Permintaan") -> Pasokan | I102: =IF(I96>I85,"Pasokan","Permintaan") -> Pasokan | J102: =IF(J96>J85,"Pasokan","Permintaan") -> Pasokan | K102: =IF(K96>K85,"Pasokan","Permintaan") -> Pasokan | ... AA102: =IF(AA96>AA85,"Pasokan","Permintaan") -> Permintaan
A103: Nilai & pendapatan
A104: GMV bruto (Σ TOTAL transaksi selesai) | B104: Rp | D104: =D101*'Unit Economics'!$D$18 -> 99618899 | E104: =E101*'Unit Economics'!$D$18 -> 1.4282204e+08 | F104: =F101*'Unit Economics'!$D$18 -> 1.8807209e+08 | G104: =G101*'Unit Economics'!$D$18 -> 2.3558918e+08 | H104: =H101*'Unit Economics'!$D$18 -> 2.8560877e+08 | I104: =I101*'Unit Economics'!$D$18 -> 3.3838304e+08 | J104: =J101*'Unit Economics'!$D$18 -> 3.9418222e+08 | K104: =K101*'Unit Economics'!$D$18 -> 4.532962e+08 | ... AA104: =AA101*'Unit Economics'!$D$18 -> 1.7212762e+09 | AB104: =SUM(D104:O104) -> 4.6195808e+09 | AC104: =SUM(P104:AA104) -> 1.5273874e+10 | AD104: =SUM(C104:AA104) -> 1.9893455e+10
A105: Nilai barang (pass-through) | B105: Rp | D105: =D101*'Unit Economics'!$D$8 -> 68229000 | E105: =E101*'Unit Economics'!$D$8 -> 97818840 | F105: =F101*'Unit Economics'!$D$8 -> 1.2881061e+08 | G105: =G101*'Unit Economics'!$D$8 -> 1.6135506e+08 | H105: =H101*'Unit Economics'!$D$8 -> 1.9561349e+08 | I105: =I101*'Unit Economics'!$D$8 -> 2.317586e+08 | J105: =J101*'Unit Economics'!$D$8 -> 2.6997547e+08 | K105: =K101*'Unit Economics'!$D$8 -> 3.1046264e+08 | ... AA105: =AA101*'Unit Economics'!$D$8 -> 1.1789023e+09 | AB105: =SUM(D105:O105) -> 3.1639516e+09 | AC105: =SUM(P105:AA105) -> 1.0461079e+10 | AD105: =SUM(C105:AA105) -> 1.3625031e+10
...

Sheet Sensitivitas
A1: Analisis Sensitivitas — skenario aktif
A2: ="Semua tabel memakai skenario aktif: "&Asumsi!$D$4&" (ubah di Asumsi!D4). Sel biru = sumbu yang boleh diubah." -> Semua tabel memakai skenario aktif: Dasar (ubah di Asumsi!D4). Sel biru = sumbu yang boleh diubah.
A4: Basis dari skenario aktif
B5: GMV per transaksi (TOTAL) | C5: =INDEX('Unit Economics'!$C$18:$E$18,Asumsi!$D$5) -> 2920133.6
B6: Nilai barang per transaksi | C6: =INDEX('Unit Economics'!$C$8:$E$8,Asumsi!$D$5) -> 2000000
B7: Biaya variabel per transaksi (subsidi bayar, payout, klaim, CS, chargeback, batal) | C7: =INDEX('Unit Economics'!$C$58:$E$58,Asumsi!$D$5) -> 45640.3
B8: Biaya tetap + marketing per bulan (rata-rata Th2, tanpa biaya sekali) | C8: =CHOOSE(Asumsi!$D$5,('Proyeksi 24 Bulan'!$AC$71-'Proyeksi 24 Bulan'!$AC$69)/12,('Proyeksi 24 Bulan'!$AC$134-'Proyeksi 24 Bulan'!$AC$132)/12,('Proyeksi 24 Bulan'!$AC$197-'Proyeksi 24 Bulan'!$AC$195)/12) -> 1.6388908e+08
B9: Take rate bersih saat ini (pendapatan bersih ÷ GMV) | C9: =INDEX('Unit Economics'!$C$62:$E$62,Asumsi!$D$5) -> 0.042086535
B10: Pendapatan bersih per transaksi saat ini | C10: =INDEX('Unit Economics'!$C$50:$E$50,Asumsi!$D$5) -> 122898.31
B11: Margin kontribusi per transaksi saat ini | C11: =INDEX('Unit Economics'!$C$57:$E$57,Asumsi!$D$5) -> 77258.008
B12: BEP transaksi/bulan saat ini | C12: =IF(C11>0,ROUNDUP(C8/C11,0),"CM ≤ 0") -> 2122
A14: 1. EBITDA bulanan (Rp juta) = transaksi × (take rate bersih × GMV/trx − biaya variabel/trx) − biaya tetap & marketing
B15: Take rate bersih ↓ · transaksi selesai/bulan → | C15: 250 | D15: 500 | E15: 1000 | F15: 1500 | G15: 2000 | H15: 3000 | I15: 5000 | J15: 7500 | K15: 10000 | L15: Setara % nilai barang
B16: 0.03 | C16: =(C$15*($B16*$C$5-$C$7)-$C$8)/1000000 -> -153.39815 | D16: =(D$15*($B16*$C$5-$C$7)-$C$8)/1000000 -> -142.90722 | E16: =(E$15*($B16*$C$5-$C$7)-$C$8)/1000000 -> -121.92537 | F16: =(F$15*($B16*$C$5-$C$7)-$C$8)/1000000 -> -100.94351 | G16: =(G$15*($B16*$C$5-$C$7)-$C$8)/1000000 -> -79.961657 | H16: =(H$15*($B16*$C$5-$C$7)-$C$8)/1000000 -> -37.997948 | I16: =(I$15*($B16*$C$5-$C$7)-$C$8)/1000000 -> 45.929471 | J16: =(J$15*($B16*$C$5-$C$7)-$C$8)/1000000 -> 150.83874 | K16: =(K$15*($B16*$C$5-$C$7)-$C$8)/1000000 -> 255.74802 | L16: =IF($C$6>0,$B16*$C$5/$C$6,0) -> 0.043802005
B17: 0.035 | C17: =(C$15*($B17*$C$5-$C$7)-$C$8)/1000000 -> -149.74798 | D17: =(D$15*($B17*$C$5-$C$7)-$C$8)/1000000 -> -135.60689 | E17: =(E$15*($B17*$C$5-$C$7)-$C$8)/1000000 -> -107.3247 | F17: =(F$15*($B17*$C$5-$C$7)-$C$8)/1000000 -> -79.04251 | G17: =(G$15*($B17*$C$5-$C$7)-$C$8)/1000000 -> -50.760321 | H17: =(H$15*($B17*$C$5-$C$7)-$C$8)/1000000 -> 5.804057 | I17: =(I$15*($B17*$C$5-$C$7)-$C$8)/1000000 -> 118.93281 | J17: =(J$15*($B17*$C$5-$C$7)-$C$8)/1000000 -> 260.34376 | K17: =(K$15*($B17*$C$5-$C$7)-$C$8)/1000000 -> 401.7547 | L17: =IF($C$6>0,$B17*$C$5/$C$6,0) -> 0.051102339
B18: 0.04 | C18: =(C$15*($B18*$C$5-$C$7)-$C$8)/1000000 -> -146.09781 | D18: =(D$15*($B18*$C$5-$C$7)-$C$8)/1000000 -> -128.30655 | E18: =(E$15*($B18*$C$5-$C$7)-$C$8)/1000000 -> -92.72403 | F18: =(F$15*($B18*$C$5-$C$7)-$C$8)/1000000 -> -57.141507 | G18: =(G$15*($B18*$C$5-$C$7)-$C$8)/1000000 -> -21.558984 | H18: =(H$15*($B18*$C$5-$C$7)-$C$8)/1000000 -> 49.606062 | I18: =(I$15*($B18*$C$5-$C$7)-$C$8)/1000000 -> 191.93615 | J18: =(J$15*($B18*$C$5-$C$7)-$C$8)/1000000 -> 369.84877 | K18: =(K$15*($B18*$C$5-$C$7)-$C$8)/1000000 -> 547.76138 | L18: =IF($C$6>0,$B18*$C$5/$C$6,0) -> 0.058402673
B19: 0.045 | C19: =(C$15*($B19*$C$5-$C$7)-$C$8)/1000000 -> -142.44765 | D19: =(D$15*($B19*$C$5-$C$7)-$C$8)/1000000 -> -121.00622 | E19: =(E$15*($B19*$C$5-$C$7)-$C$8)/1000000 -> -78.123362 | F19: =(F$15*($B19*$C$5-$C$7)-$C$8)/1000000 -> -35.240505 | G19: =(G$15*($B19*$C$5-$C$7)-$C$8)/1000000 -> 7.6423522 | H19: =(H$15*($B19*$C$5-$C$7)-$C$8)/1000000 -> 93.408067 | I19: =(I$15*($B19*$C$5-$C$7)-$C$8)/1000000 -> 264.9395 | J19: =(J$15*($B19*$C$5-$C$7)-$C$8)/1000000 -> 479.35378 | K19: =(K$15*($B19*$C$5-$C$7)-$C$8)/1000000 -> 693.76807 | L19: =IF($C$6>0,$B19*$C$5/$C$6,0) -> 0.065703007
B20: 0.05 | C20: =(C$15*($B20*$C$5-$C$7)-$C$8)/1000000 -> -138.79748 | D20: =(D$15*($B20*$C$5-$C$7)-$C$8)/1000000 -> -113.70588 | E20: =(E$15*($B20*$C$5-$C$7)-$C$8)/1000000 -> -63.522694 | F20: =(F$15*($B20*$C$5-$C$7)-$C$8)/1000000 -> -13.339503 | G20: =(G$15*($B20*$C$5-$C$7)-$C$8)/1000000 -> 36.843689 | H20: =(H$15*($B20*$C$5-$C$7)-$C$8)/1000000 -> 137.21007 | I20: =(I$15*($B20*$C$5-$C$7)-$C$8)/1000000 -> 337.94284 | J20: =(J$15*($B20*$C$5-$C$7)-$C$8)/1000000 -> 588.85879 | K20: =(K$15*($B20*$C$5-$C$7)-$C$8)/1000000 -> 839.77475 | L20: =IF($C$6>0,$B20*$C$5/$C$6,0) -> 0.073003341
B21: 0.055 | C21: =(C$15*($B21*$C$5-$C$7)-$C$8)/1000000 -> -135.14731 | D21: =(D$15*($B21*$C$5-$C$7)-$C$8)/1000000 -> -106.40555 | E21: =(E$15*($B21*$C$5-$C$7)-$C$8)/1000000 -> -48.922025 | F21: =(F$15*($B21*$C$5-$C$7)-$C$8)/1000000 -> 8.5614999 | G21: =(G$15*($B21*$C$5-$C$7)-$C$8)/1000000 -> 66.045025 | H21: =(H$15*($B21*$C$5-$C$7)-$C$8)/1000000 -> 181.01208 | I21: =(I$15*($B21*$C$5-$C$7)-$C$8)/1000000 -> 410.94618 | J21: =(J$15*($B21*$C$5-$C$7)-$C$8)/1000000 -> 698.3638 | K21: =(K$15*($B21*$C$5-$C$7)-$C$8)/1000000 -> 985.78143 | L21: =IF($C$6>0,$B21*$C$5/$C$6,0) -> 0.080303675
B22: 0.06 | C22: =(C$15*($B22*$C$5-$C$7)-$C$8)/1000000 -> -131.49715 | D22: =(D$15*($B22*$C$5-$C$7)-$C$8)/1000000 -> -99.105217 | E22: =(E$15*($B22*$C$5-$C$7)-$C$8)/1000000 -> -34.321357 | F22: =(F$15*($B22*$C$5-$C$7)-$C$8)/1000000 -> 30.462502 | G22: =(G$15*($B22*$C$5-$C$7)-$C$8)/1000000 -> 95.246362 | H22: =(H$15*($B22*$C$5-$C$7)-$C$8)/1000000 -> 224.81408 | I22: =(I$15*($B22*$C$5-$C$7)-$C$8)/1000000 -> 483.94952 | J22: =(J$15*($B22*$C$5-$C$7)-$C$8)/1000000 -> 807.86882 | K22: =(K$15*($B22*$C$5-$C$7)-$C$8)/1000000 -> 1131.7881 | L22: =IF($C$6>0,$B22*$C$5/$C$6,0) -> 0.087604009
B23: 0.07 | C23: =(C$15*($B23*$C$5-$C$7)-$C$8)/1000000 -> -124.19681 | D23: =(D$15*($B23*$C$5-$C$7)-$C$8)/1000000 -> -84.504548 | E23: =(E$15*($B23*$C$5-$C$7)-$C$8)/1000000 -> -5.1200207 | F23: =(F$15*($B23*$C$5-$C$7)-$C$8)/1000000 -> 74.264507 | G23: =(G$15*($B23*$C$5-$C$7)-$C$8)/1000000 -> 153.64903 | H23: =(H$15*($B23*$C$5-$C$7)-$C$8)/1000000 -> 312.41809 | I23: =(I$15*($B23*$C$5-$C$7)-$C$8)/1000000 -> 629.9562 | J23: =(J$15*($B23*$C$5-$C$7)-$C$8)/1000000 -> 1026.8788 | K23: =(K$15*($B23*$C$5-$C$7)-$C$8)/1000000 -> 1423.8015 | L23: =IF($C$6>0,$B23*$C$5/$C$6,0) -> 0.10220468
B24: Penyederhanaan: biaya variabel per transaksi dianggap tetap terhadap take rate (klaim proteksi sebenarnya ikut protection fee).
A26: 2. Subsidi kanal pembayaran: biaya VA yang dibebankan ke pembeli × porsi VA (skenario aktif)
B27: Biaya Xendit per transaksi VA | C27: =INDEX('Unit Economics'!$C$22:$E$22,Asumsi!$D$5) -> 14430
B28: VA dibebankan saat ini (config) | C28: =INDEX('Unit Economics'!$C$21:$E$21,Asumsi!$D$5) -> 4500
B29: Porsi VA saat ini | C29: =INDEX('Unit Economics'!$C$114:$E$114,Asumsi!$D$5) -> 0.5
B30: Subsidi rata-rata saat ini (bauran) | C30: =INDEX('Unit Economics'!$C$35:$E$35,Asumsi!$D$5) -> 16233.3
B31: Biaya bayar rata-rata yang dibebankan ke pembeli (bauran) | C31: =INDEX('Unit Economics'!$C$33:$E$33,Asumsi!$D$5) -> 22833.65
B32: TOTAL dibayar pembeli saat ini | C32: =INDEX('Unit Economics'!$C$18:$E$18,Asumsi!$D$5) -> 2920133.6
B33: Subsidi rata-rata per transaksi non-VA | C33: =IF(1-C29>0,(C30-C29*(C27-C28))/(1-C29),0) -> 22536.6
B35: Tabel 2a — Margin kontribusi per transaksi (Rp)
B36: VA dibebankan (Rp) ↓ · porsi VA → | C36: 0.3 | D36: 0.4 | E36: 0.5 | F36: 0.6 | G36: 0.7
B37: 0 | C37: =$C$11+$C$30-(C$36*($C$27-$B37)+(1-C$36)*$C$33) -> 73386.688 | D37: =$C$11+$C$30-(D$36*($C$27-$B37)+(1-D$36)*$C$33) -> 74197.348 | E37: =$C$11+$C$30-(E$36*($C$27-$B37)+(1-E$36)*$C$33) -> 75008.008 | F37: =$C$11+$C$30-(F$36*($C$27-$B37)+(1-F$36)*$C$33) -> 75818.668 | G37: =$C$11+$C$30-(G$36*($C$27-$B37)+(1-G$36)*$C$33) -> 76629.328
B38: 4500 | C38: =$C$11+$C$30-(C$36*($C$27-$B38)+(1-C$36)*$C$33) -> 74736.688 | D38: =$C$11+$C$30-(D$36*($C$27-$B38)+(1-D$36)*$C$33) -> 75997.348 | E38: =$C$11+$C$30-(E$36*($C$27-$B38)+(1-E$36)*$C$33) -> 77258.008 | F38: =$C$11+$C$30-(F$36*($C$27-$B38)+(1-F$36)*$C$33) -> 78518.668 | G38: =$C$11+$C$30-(G$36*($C$27-$B38)+(1-G$36)*$C$33) -> 79779.328
B39: 7500 | C39: =$C$11+$C$30-(C$36*($C$27-$B39)+(1-C$36)*$C$33) -> 75636.688 | D39: =$C$11+$C$30-(D$36*($C$27-$B39)+(1-D$36)*$C$33) -> 77197.348 | E39: =$C$11+$C$30-(E$36*($C$27-$B39)+(1-E$36)*$C$33) -> 78758.008 | F39: =$C$11+$C$30-(F$36*($C$27-$B39)+(1-F$36)*$C$33) -> 80318.668 | G39: =$C$11+$C$30-(G$36*($C$27-$B39)+(1-G$36)*$C$33) -> 81879.328
B40: 10000 | C40: =$C$11+$C$30-(C$36*($C$27-$B40)+(1-C$36)*$C$33) -> 76386.688 | D40: =$C$11+$C$30-(D$36*($C$27-$B40)+(1-D$36)*$C$33) -> 78197.348 | E40: =$C$11+$C$30-(E$36*($C$27-$B40)+(1-E$36)*$C$33) -> 80008.008 | F40: =$C$11+$C$30-(F$36*($C$27-$B40)+(1-F$36)*$C$33) -> 81818.668 | G40: =$C$11+$C$30-(G$36*($C$27-$B40)+(1-G$36)*$C$33) -> 83629.328
B41: 14430 | C41: =$C$11+$C$30-(C$36*($C$27-$B41)+(1-C$36)*$C$33) -> 77715.688 | D41: =$C$11+$C$30-(D$36*($C$27-$B41)+(1-D$36)*$C$33) -> 79969.348 | E41: =$C$11+$C$30-(E$36*($C$27-$B41)+(1-E$36)*$C$33) -> 82223.008 | F41: =$C$11+$C$30-(F$36*($C$27-$B41)+(1-F$36)*$C$33) -> 84476.668 | G41: =$C$11+$C$30-(G$36*($C$27-$B41)+(1-G$36)*$C$33) -> 86730.328
B43: Tabel 2b — BEP transaksi selesai per bulan (biaya tetap + marketing Th2 ÷ CM)
B44: VA dibebankan (Rp) ↓ · porsi VA → | C44: =C36 -> 0.3 | D44: =D36 -> 0.4 | E44: =E36 -> 0.5 | F44: =F36 -> 0.6 | G44: =G36 -> 0.7
B45: =B37 -> 0 | C45: =IF(C37>0,ROUNDUP($C$8/C37,0),"CM ≤ 0") -> 2234 | D45: =IF(D37>0,ROUNDUP($C$8/D37,0),"CM ≤ 0") -> 2209 | E45: =IF(E37>0,ROUNDUP($C$8/E37,0),"CM ≤ 0") -> 2185 | F45: =IF(F37>0,ROUNDUP($C$8/F37,0),"CM ≤ 0") -> 2162 | G45: =IF(G37>0,ROUNDUP($C$8/G37,0),"CM ≤ 0") -> 2139
B46: =B38 -> 4500 | C46: =IF(C38>0,ROUNDUP($C$8/C38,0),"CM ≤ 0") -> 2193 | D46: =IF(D38>0,ROUNDUP($C$8/D38,0),"CM ≤ 0") -> 2157 | E46: =IF(E38>0,ROUNDUP($C$8/E38,0),"CM ≤ 0") -> 2122 | F46: =IF(F38>0,ROUNDUP($C$8/F38,0),"CM ≤ 0") -> 2088 | G46: =IF(G38>0,ROUNDUP($C$8/G38,0),"CM ≤ 0") -> 2055
B47: =B39 -> 7500 | C47: =IF(C39>0,ROUNDUP($C$8/C39,0),"CM ≤ 0") -> 2167 | D47: =IF(D39>0,ROUNDUP($C$8/D39,0),"CM ≤ 0") -> 2123 | E47: =IF(E39>0,ROUNDUP($C$8/E39,0),"CM ≤ 0") -> 2081 | F47: =IF(F39>0,ROUNDUP($C$8/F39,0),"CM ≤ 0") -> 2041 | G47: =IF(G39>0,ROUNDUP($C$8/G39,0),"CM ≤ 0") -> 2002
B48: =B40 -> 10000 | C48: =IF(C40>0,ROUNDUP($C$8/C40,0),"CM ≤ 0") -> 2146 | D48: =IF(D40>0,ROUNDUP($C$8/D40,0),"CM ≤ 0") -> 2096 | E48: =IF(E40>0,ROUNDUP($C$8/E40,0),"CM ≤ 0") -> 2049 | F48: =IF(F40>0,ROUNDUP($C$8/F40,0),"CM ≤ 0") -> 2004 | G48: =IF(G40>0,ROUNDUP($C$8/G40,0),"CM ≤ 0") -> 1960
B49: =B41 -> 14430 | C49: =IF(C41>0,ROUNDUP($C$8/C41,0),"CM ≤ 0") -> 2109 | D49: =IF(D41>0,ROUNDUP($C$8/D41,0),"CM ≤ 0") -> 2050 | E49: =IF(E41>0,ROUNDUP($C$8/E41,0),"CM ≤ 0") -> 1994 | F49: =IF(F41>0,ROUNDUP($C$8/F41,0),"CM ≤ 0") -> 1941 | G49: =IF(G41>0,ROUNDUP($C$8/G41,0),"CM ≤ 0") -> 1890
B50: Rp14.430 = biaya VA Xendit penuh (pass-through). Penyederhanaan: biaya pembatalan tidak dihitung ulang; perubahan biaya bisa menggeser bauran kanal (gunakan sumbu porsi VA).
B52: Tabel 2c — Kebijakan biaya kanal pembayaran (bauran kanal skenario aktif)
B53: Kebijakan | C53: Subsidi / biaya bayar ditanggung platform per trx (Rp) | D53: Margin kontribusi per trx (Rp) | E53: BEP trx/bulan | F53: TOTAL dibayar pembeli (Rp)
B54: (a) Config saat ini (bearer BUYER, tarif config) | C54: =$C$30 -> 16233.3 | D54: =$C$11 -> 77258.008 | E54: =IF(D54>0,ROUNDUP($C$8/D54,0),"CM ≤ 0") -> 2122 | F54: =$C$32 -> 2920133.6
B55: (b) VA dibebankan penuh sesuai biaya Xendit; kanal lain tetap | C55: =$C$30-$C$29*($C$27-$C$28) -> 11268.3 | D55: =$C$11+$C$29*($C$27-$C$28) -> 82223.008 | E55: =IF(D55>0,ROUNDUP($C$8/D55,0),"CM ≤ 0") -> 1994 | F55: =$C$32+$C$29*($C$27-$C$28) -> 2925098.6
B56: (c) Semua kanal dibebankan sesuai biaya Xendit (subsidi 0) | C56: =0 -> 0 | D56: =$C$11+$C$30 -> 93491.308 | E56: =IF(D56>0,ROUNDUP($C$8/D56,0),"CM ≤ 0") -> 1753 | F56: =$C$32+$C$30 -> 2936367
B57: (d) Platform menanggung seluruh biaya bayar (tanpa PAYMENT_FEE) | C57: =$C$30+$C$31 -> 39066.95 | D57: =$C$11-$C$31 -> 54424.358 | E57: =IF(D57>0,ROUNDUP($C$8/D57,0),"CM ≤ 0") -> 3012 | F57: =$C$32-$C$31 -> 2897300
B58: Penyederhanaan: biaya berbasis persen atas TOTAL dan biaya pembatalan tidak dihitung ulang setelah perubahan biaya bayar (selisih kecil).
A60: 3. Rata-rata nilai barang (keranjang) — skenario aktif; rincian perhitungan di bawah
B61: Komponen per transaksi | C61: Rp0,5 jt | D61: Rp1 jt | E61: Rp1,5 jt | F61: Rp2 jt | G61: Rp2,5 jt | H61: Rp3 jt | I61: Rp4 jt | J61: Rp5 jt | K61: Rp7,5 jt | L61: Rp10 jt
B62: Nilai barang | C62: =C80 -> 500000 | D62: =D80 -> 1000000 | E62: =E80 -> 1500000 | F62: =F80 -> 2000000 | G62: =G80 -> 2500000 | H62: =H80 -> 3000000 | I62: =I80 -> 4000000 | J62: =J80 -> 5000000 | ... L62: =L80 -> 10000000
B63: TOTAL dibayar pembeli | C63: =C92 -> 732630.8 | D63: =D92 -> 1461798.4 | E63: =E92 -> 2190965.9 | F63: =F92 -> 2920133.6 | G63: =G92 -> 3649301.1 | H63: =H92 -> 4378468.7 | I63: =I92 -> 5836804 | J63: =J92 -> 7295139 | ... L63: =L92 -> 14586815
B64: Pendapatan bruto platform | C64: =C121 -> 32500 | D64: =D121 -> 65000 | E64: =E121 -> 97500 | F64: =F121 -> 130000 | G64: =G121 -> 162500 | H64: =H121 -> 195000 | I64: =I121 -> 260000 | J64: =J121 -> 325000 | ... L64: =L121 -> 650000
B65: Take rate bruto (÷ GMV) | C65: =C134 -> 0.044360679 | D65: =D134 -> 0.044465774 | E65: =E134 -> 0.044500922 | F65: =F134 -> 0.04451851 | G65: =G134 -> 0.044529074 | H65: =H134 -> 0.044536118 | I65: =I134 -> 0.044544926 | J65: =J134 -> 0.044550214 | ... L65: =L134 -> 0.044560791
B66: Subsidi kanal pembayaran | C66: =C109 -> 9466.3 | D66: =D109 -> 11722.15 | E66: =E109 -> 13977.85 | F66: =F109 -> 16233.3 | G66: =G109 -> 18489.05 | H66: =H109 -> 20745 | I66: =I109 -> 25256.2 | J66: =J109 -> 29768 | ... L66: =L109 -> 52325
B67: Biaya payout ke traveler | C67: =-C126 -> 4995 | D67: =-D126 -> 4995 | E67: =-E126 -> 4995 | F67: =-F126 -> 4995 | G67: =-G126 -> 4995 | H67: =-H126 -> 4995 | I67: =-I126 -> 4995 | J67: =-J126 -> 4995 | ... L67: =-L126 -> 4995
B68: Klaim proteksi | C68: =-C127 -> 3000 | D68: =-D127 -> 6000 | E68: =-E127 -> 9000 | F68: =-F127 -> 12000 | G68: =-G127 -> 15000 | H68: =-H127 -> 18000 | I68: =-I127 -> 24000 | J68: =-J127 -> 30000 | ... L68: =-L127 -> 60000
B69: Margin kontribusi per transaksi | C69: =C131 -> -313.99217 | D69: =D131 -> 25543.158 | E69: =E131 -> 51400.458 | F69: =F131 -> 77258.008 | G69: =G131 -> 103116.26 | H69: =H131 -> 128973.31 | I69: =I131 -> 180688.11 | J69: =J131 -> 232403.31 | ... L69: =L131 -> 490978.31
B70: BEP transaksi/bulan | C70: =IF(C131>0,ROUNDUP($C$8/C131,0),"CM ≤ 0") -> CM ≤ 0 | D70: =IF(D131>0,ROUNDUP($C$8/D131,0),"CM ≤ 0") -> 6417 | E70: =IF(E131>0,ROUNDUP($C$8/E131,0),"CM ≤ 0") -> 3189 | F70: =IF(F131>0,ROUNDUP($C$8/F131,0),"CM ≤ 0") -> 2122 | G70: =IF(G131>0,ROUNDUP($C$8/G131,0),"CM ≤ 0") -> 1590 | H70: =IF(H131>0,ROUNDUP($C$8/H131,0),"CM ≤ 0") -> 1271 | I70: =IF(I131>0,ROUNDUP($C$8/I131,0),"CM ≤ 0") -> 908 | J70: =IF(J131>0,ROUNDUP($C$8/J131,0),"CM ≤ 0") -> 706 | ... L70: =IF(L131>0,ROUNDUP($C$8/L131,0),"CM ≤ 0") -> 334
B71: GMV pada BEP (Rp juta/bulan) | C71: =IF(ISNUMBER(C70),C70*C92/1000000,0) -> 0 | D71: =IF(ISNUMBER(D70),D70*D92/1000000,0) -> 9380.3607 | E71: =IF(ISNUMBER(E70),E70*E92/1000000,0) -> 6986.9901 | F71: =IF(ISNUMBER(F70),F70*F92/1000000,0) -> 6196.5236 | G71: =IF(ISNUMBER(G70),G70*G92/1000000,0) -> 5802.3888 | H71: =IF(ISNUMBER(H70),H70*H92/1000000,0) -> 5565.0337 | I71: =IF(ISNUMBER(I70),I70*I92/1000000,0) -> 5299.818 | J71: =IF(ISNUMBER(J70),J70*J92/1000000,0) -> 5150.3681 | ... L71: =IF(ISNUMBER(L70),L70*L92/1000000,0) -> 4871.9961
B72: TOTAL ≤ batas QRIS Rp10 jt | C72: =C150 -> OK | D72: =D150 -> OK | E72: =E150 -> OK | F72: =F150 -> OK | G72: =G150 -> OK | H72: =H150 -> OK | I72: =I150 -> OK | J72: =J150 -> OK | ... L72: =L150 -> QRIS tidak tersedia
B73: TOTAL ≤ limit traveler baru | C73: =C149 -> OK | D73: =D149 -> OK | E73: =E149 -> OK | F73: =F149 -> OK | G73: =G149 -> OK | H73: =H149 -> OK | I73: =I149 -> Butuh traveler ≥ 3 transaksi selesai | J73: =J149 -> Butuh traveler ≥ 3 transaksi selesai | ... L73: =L149 -> Butuh traveler ≥ 3 transaksi selesai
B74: Level KYC pembeli minimum | C74: =C151 -> Level 2 | D74: =D151 -> Level 2 | E74: =E151 -> Level 2 | F74: =F151 -> Level 2 | G74: =G151 -> Level 3 | H74: =H151 -> Level 3 | I74: =I151 -> Level 3 | J74: =J151 -> Level 3 | ... L74: =L151 -> Level 3
A75: Keranjang dengan TOTAL > Rp10 jt tidak bisa memakai QRIS (bauran kanal tidak disesuaikan otomatis); BEP memakai biaya tetap + marketing Th2 skenario aktif.
A77: Rincian perhitungan (struktur identik dengan sheet Unit Economics)
B78: Baris / komponen | C78: Rp0,5 jt | D78: Rp1 jt | E78: Rp1,5 jt | F78: Rp2 jt | G78: Rp2,5 jt | H78: Rp3 jt | I78: Rp4 jt | J78: Rp5 jt | K78: Rp7,5 jt | L78: Rp10 jt
B79: Indeks skenario (aktif) | C79: =Asumsi!$D$5 -> 2 | D79: =Asumsi!$D$5 -> 2 | E79: =Asumsi!$D$5 -> 2 | F79: =Asumsi!$D$5 -> 2 | G79: =Asumsi!$D$5 -> 2 | H79: =Asumsi!$D$5 -> 2 | I79: =Asumsi!$D$5 -> 2 | J79: =Asumsi!$D$5 -> 2 | ... L79: =Asumsi!$D$5 -> 2
B80: Nilai barang (Rp) | C80: 500000 | D80: 1000000 | E80: 1500000 | F80: 2000000 | G80: 2500000 | H80: 3000000 | I80: 4000000 | J80: 5000000 | K80: 7500000 | L80: 10000000
A81: A. Rincian 11 baris harga per transaksi (dibayar pembeli) — urutan docs/00-domain-model.md §10
B82: 1. ITEM_PRICE — Harga Barang | C82: =C80 -> 500000 | D82: =D80 -> 1000000 | E82: =E80 -> 1500000 | F82: =F80 -> 2000000 | G82: =G80 -> 2500000 | H82: =H80 -> 3000000 | I82: =I80 -> 4000000 | J82: =J80 -> 5000000 | ... L82: =L80 -> 10000000
B83: 2. TRAVELER_FEE — Traveler Fee | C83: =MAX(C155,MIN(ROUND(C82*C154,0),ROUNDDOWN(C82*C156,0))) -> 50000 | D83: =MAX(D155,MIN(ROUND(D82*D154,0),ROUNDDOWN(D82*D156,0))) -> 100000 | E83: =MAX(E155,MIN(ROUND(E82*E154,0),ROUNDDOWN(E82*E156,0))) -> 150000 | F83: =MAX(F155,MIN(ROUND(F82*F154,0),ROUNDDOWN(F82*F156,0))) -> 200000 | G83: =MAX(G155,MIN(ROUND(G82*G154,0),ROUNDDOWN(G82*G156,0))) -> 250000 | H83: =MAX(H155,MIN(ROUND(H82*H154,0),ROUNDDOWN(H82*H156,0))) -> 300000 | I83: =MAX(I155,MIN(ROUND(I82*I154,0),ROUNDDOWN(I82*I156,0))) -> 400000 | J83: =MAX(J155,MIN(ROUND(J82*J154,0),ROUNDDOWN(J82*J156,0))) -> 500000 | ... L83: =MAX(L155,MIN(ROUND(L82*L154,0),ROUNDDOWN(L82*L156,0))) -> 1000000
B84: 3. CUSTOMS_DUTY — Bea Masuk (estimasi) | C84: =CEILING(C82*C157,1000) -> 50000 | D84: =CEILING(D82*D157,1000) -> 100000 | E84: =CEILING(E82*E157,1000) -> 150000 | F84: =CEILING(F82*F157,1000) -> 200000 | G84: =CEILING(G82*G157,1000) -> 250000 | H84: =CEILING(H82*H157,1000) -> 300000 | I84: =CEILING(I82*I157,1000) -> 400000 | J84: =CEILING(J82*J157,1000) -> 500000 | ... L84: =CEILING(L82*L157,1000) -> 1000000
B85: 4. IMPORT_TAX — PPN impor + PPh 22 (estimasi) | C85: =CEILING((C82+C84)*C158*C159,1000)+CEILING((C82+C84)*C160,1000) -> 89000 | D85: =CEILING((D82+D84)*D158*D159,1000)+CEILING((D82+D84)*D160,1000) -> 177000 | E85: =CEILING((E82+E84)*E158*E159,1000)+CEILING((E82+E84)*E160,1000) -> 265000 | F85: =CEILING((F82+F84)*F158*F159,1000)+CEILING((F82+F84)*F160,1000) -> 353000 | G85: =CEILING((G82+G84)*G158*G159,1000)+CEILING((G82+G84)*G160,1000) -> 441000 | H85: =CEILING((H82+H84)*H158*H159,1000)+CEILING((H82+H84)*H160,1000) -> 529000 | I85: =CEILING((I82+I84)*I158*I159,1000)+CEILING((I82+I84)*I160,1000) -> 705000 | J85: =CEILING((J82+J84)*J158*J159,1000)+CEILING((J82+J84)*J160,1000) -> 881000 | ... L85: =CEILING((L82+L84)*L158*L159,1000)+CEILING((L82+L84)*L160,1000) -> 1761000
B86: 5. PROTECTION_FEE — JastipKita Protection | C86: =MIN(C163,MAX(C162,ROUND(C82*C161,0))) -> 7500 | D86: =MIN(D163,MAX(D162,ROUND(D82*D161,0))) -> 15000 | E86: =MIN(E163,MAX(E162,ROUND(E82*E161,0))) -> 22500 | F86: =MIN(F163,MAX(F162,ROUND(F82*F161,0))) -> 30000 | G86: =MIN(G163,MAX(G162,ROUND(G82*G161,0))) -> 37500 | H86: =MIN(H163,MAX(H162,ROUND(H82*H161,0))) -> 45000 | I86: =MIN(I163,MAX(I162,ROUND(I82*I161,0))) -> 60000 | J86: =MIN(J163,MAX(J162,ROUND(J82*J161,0))) -> 75000 | ... L86: =MIN(L163,MAX(L162,ROUND(L82*L161,0))) -> 150000
B87: 6. PLATFORM_FEE — Platform Fee | C87: =MIN(C166,MAX(C165,ROUND(C82*C164,0))) -> 25000 | D87: =MIN(D166,MAX(D165,ROUND(D82*D164,0))) -> 50000 | E87: =MIN(E166,MAX(E165,ROUND(E82*E164,0))) -> 75000 | F87: =MIN(F166,MAX(F165,ROUND(F82*F164,0))) -> 100000 | G87: =MIN(G166,MAX(G165,ROUND(G82*G164,0))) -> 125000 | H87: =MIN(H166,MAX(H165,ROUND(H82*H164,0))) -> 150000 | I87: =MIN(I166,MAX(I165,ROUND(I82*I164,0))) -> 200000 | J87: =MIN(J166,MAX(J165,ROUND(J82*J164,0))) -> 250000 | ... L87: =MIN(L166,MAX(L165,ROUND(L82*L164,0))) -> 500000
B88: 7. SERVICE_TAX — PPN atas layanan | C88: =C169*ROUND((C86+C87)*C168*C167,0) -> 3575 | D88: =D169*ROUND((D86+D87)*D168*D167,0) -> 7150 | E88: =E169*ROUND((E86+E87)*E168*E167,0) -> 10725 | F88: =F169*ROUND((F86+F87)*F168*F167,0) -> 14300 | G88: =G169*ROUND((G86+G87)*G168*G167,0) -> 17875 | H88: =H169*ROUND((H86+H87)*H168*H167,0) -> 21450 | I88: =I169*ROUND((I86+I87)*I168*I167,0) -> 28600 | J88: =J169*ROUND((J86+J87)*J168*J167,0) -> 35750 | ... L88: =L169*ROUND((L86+L87)*L168*L167,0) -> 71500
B89: 8. PAYMENT_FEE — rata-rata tertimbang bauran kanal | C89: =C107 -> 7555.8 | D89: =D107 -> 12648.45 | E89: =E107 -> 17740.85 | F89: =F107 -> 22833.65 | G89: =G107 -> 27926.15 | H89: =H107 -> 33018.7 | I89: =I107 -> 43204 | J89: =J107 -> 53388.95 | ... L89: =L107 -> 104314.75
B90: 9. DISCOUNT — Diskon promo (negatif) | C90: 0 | D90: 0 | E90: 0 | F90: 0 | G90: 0 | H90: 0 | I90: 0 | J90: 0 | K90: 0 | L90: 0
B91: 10. REFERRAL_CREDIT — JastipKita Credit (negatif) | C91: 0 | D91: 0 | E91: 0 | F91: 0 | G91: 0 | H91: 0 | I91: 0 | J91: 0 | K91: 0 | L91: 0
B92: 11. TOTAL — Total Landed Cost (= GMV per transaksi) | C92: =SUM(C82:C88)+C89+C90+C91 -> 732630.8 | D92: =SUM(D82:D88)+D89+D90+D91 -> 1461798.4 | E92: =SUM(E82:E88)+E89+E90+E91 -> 2190965.9 | F92: =SUM(F82:F88)+F89+F90+F91 -> 2920133.6 | G92: =SUM(G82:G88)+G89+G90+G91 -> 3649301.1 | H92: =SUM(H82:H88)+H89+H90+H91 -> 4378468.7 | I92: =SUM(I82:I88)+I89+I90+I91 -> 5836804 | J92: =SUM(J82:J88)+J89+J90+J91 -> 7295139 | ... L92: =SUM(L82:L88)+L89+L90+L91 -> 14586815
A93: A2. Biaya kanal pembayaran — dibebankan ke pembeli (config) vs biaya Xendit (tarif publik); lihat launch-checklist B4
B94: Dasar sebelum biaya bayar (P = baris 1–7 + 9 + 10) | C94: =SUM(C82:C88)+C90+C91 -> 725075 | D94: =SUM(D82:D88)+D90+D91 -> 1449150 | E94: =SUM(E82:E88)+E90+E91 -> 2173225 | F94: =SUM(F82:F88)+F90+F91 -> 2897300 | G94: =SUM(G82:G88)+G90+G91 -> 3621375 | H94: =SUM(H82:H88)+H90+H91 -> 4345450 | I94: =SUM(I82:I88)+I90+I91 -> 5793600 | J94: =SUM(J82:J88)+J90+J91 -> 7241750 | ... L94: =SUM(L82:L88)+L90+L91 -> 14482500
B95: VA — dibebankan ke pembeli | C95: =IF(C94>0,ROUNDUP(ROUND((C94+C170)/(1-C171),6),0)-C94,0) -> 4500 | D95: =IF(D94>0,ROUNDUP(ROUND((D94+D170)/(1-D171),6),0)-D94,0) -> 4500 | E95: =IF(E94>0,ROUNDUP(ROUND((E94+E170)/(1-E171),6),0)-E94,0) -> 4500 | F95: =IF(F94>0,ROUNDUP(ROUND((F94+F170)/(1-F171),6),0)-F94,0) -> 4500 | G95: =IF(G94>0,ROUNDUP(ROUND((G94+G170)/(1-G171),6),0)-G94,0) -> 4500 | H95: =IF(H94>0,ROUNDUP(ROUND((H94+H170)/(1-H171),6),0)-H94,0) -> 4500 | I95: =IF(I94>0,ROUNDUP(ROUND((I94+I170)/(1-I171),6),0)-I94,0) -> 4500 | J95: =IF(J94>0,ROUNDUP(ROUND((J94+J170)/(1-J171),6),0)-J94,0) -> 4500 | ... L95: =IF(L94>0,ROUNDUP(ROUND((L94+L170)/(1-L171),6),0)-L94,0) -> 4500
B96: VA — biaya Xendit ((Rp9.000 + Rp4.000) × 1,11) | C96: =ROUND((C178+C179)*(1+C184),0) -> 14430 | D96: =ROUND((D178+D179)*(1+D184),0) -> 14430 | E96: =ROUND((E178+E179)*(1+E184),0) -> 14430 | F96: =ROUND((F178+F179)*(1+F184),0) -> 14430 | G96: =ROUND((G178+G179)*(1+G184),0) -> 14430 | H96: =ROUND((H178+H179)*(1+H184),0) -> 14430 | I96: =ROUND((I178+I179)*(1+I184),0) -> 14430 | J96: =ROUND((J178+J179)*(1+J184),0) -> 14430 | ... L96: =ROUND((L178+L179)*(1+L184),0) -> 14430
B97: VA — subsidi platform | C97: =C96-C95 -> 9930 | D97: =D96-D95 -> 9930 | E97: =E96-E95 -> 9930 | F97: =F96-F95 -> 9930 | G97: =G96-G95 -> 9930 | H97: =H96-H95 -> 9930 | I97: =I96-I95 -> 9930 | J97: =J96-J95 -> 9930 | ... L97: =L96-L95 -> 9930
B98: QRIS — dibebankan ke pembeli | C98: =IF(C94>0,ROUNDUP(ROUND((C94+C172)/(1-C173),6),0)-C94,0) -> 5112 | D98: =IF(D94>0,ROUNDUP(ROUND((D94+D172)/(1-D173),6),0)-D94,0) -> 10216 | E98: =IF(E94>0,ROUNDUP(ROUND((E94+E172)/(1-E173),6),0)-E94,0) -> 15320 | F98: =IF(F94>0,ROUNDUP(ROUND((F94+F172)/(1-F173),6),0)-F94,0) -> 20425 | G98: =IF(G94>0,ROUNDUP(ROUND((G94+G172)/(1-G173),6),0)-G94,0) -> 25529 | H98: =IF(H94>0,ROUNDUP(ROUND((H94+H172)/(1-H173),6),0)-H94,0) -> 30633 | I98: =IF(I94>0,ROUNDUP(ROUND((I94+I172)/(1-I173),6),0)-I94,0) -> 40842 | J98: =IF(J94>0,ROUNDUP(ROUND((J94+J172)/(1-J173),6),0)-J94,0) -> 51050 | ... L98: =IF(L94>0,ROUNDUP(ROUND((L94+L172)/(1-L173),6),0)-L94,0) -> 102093
B99: QRIS — biaya Xendit (0,70% incl. PPN + Rp4.000 × 1,11) | C99: =ROUND((C94+C98)*C180+C179*(1+C184),0) -> 9551 | D99: =ROUND((D94+D98)*D180+D179*(1+D184),0) -> 14656 | E99: =ROUND((E94+E98)*E180+E179*(1+E184),0) -> 19760 | F99: =ROUND((F94+F98)*F180+F179*(1+F184),0) -> 24864 | G99: =ROUND((G94+G98)*G180+G179*(1+G184),0) -> 29968 | H99: =ROUND((H94+H98)*H180+H179*(1+H184),0) -> 35073 | I99: =ROUND((I94+I98)*I180+I179*(1+I184),0) -> 45281 | J99: =ROUND((J94+J98)*J180+J179*(1+J184),0) -> 55490 | ... L99: =ROUND((L94+L98)*L180+L179*(1+L184),0) -> 106532
B100: QRIS — subsidi platform | C100: =C99-C98 -> 4439 | D100: =D99-D98 -> 4440 | E100: =E99-E98 -> 4440 | F100: =F99-F98 -> 4439 | G100: =G99-G98 -> 4439 | H100: =H99-H98 -> 4440 | I100: =I99-I98 -> 4439 | J100: =J99-J98 -> 4440 | ... L100: =L99-L98 -> 4439
B101: E-wallet — dibebankan ke pembeli | C101: =IF(C94>0,ROUNDUP(ROUND((C94+C174)/(1-C175),6),0)-C94,0) -> 11042 | D101: =IF(D94>0,ROUNDUP(ROUND((D94+D174)/(1-D175),6),0)-D94,0) -> 22069 | E101: =IF(E94>0,ROUNDUP(ROUND((E94+E174)/(1-E175),6),0)-E94,0) -> 33095 | F101: =IF(F94>0,ROUNDUP(ROUND((F94+F174)/(1-F175),6),0)-F94,0) -> 44122 | G101: =IF(G94>0,ROUNDUP(ROUND((G94+G174)/(1-G175),6),0)-G94,0) -> 55148 | H101: =IF(H94>0,ROUNDUP(ROUND((H94+H174)/(1-H175),6),0)-H94,0) -> 66175 | I101: =IF(I94>0,ROUNDUP(ROUND((I94+I174)/(1-I175),6),0)-I94,0) -> 88228 | J101: =IF(J94>0,ROUNDUP(ROUND((J94+J174)/(1-J175),6),0)-J94,0) -> 110281 | ... L101: =IF(L94>0,ROUNDUP(ROUND((L94+L174)/(1-L175),6),0)-L94,0) -> 220546
B102: E-wallet — biaya Xendit ((tarif × TOTAL + Rp4.000) × 1,11) | C102: =ROUND(((C94+C101)*C181+C179)*(1+C184),0) -> 28953 | D102: =ROUND(((D94+D101)*D181+D179)*(1+D184),0) -> 53432 | E102: =ROUND(((E94+E101)*E181+E179)*(1+E184),0) -> 77910 | F102: =ROUND(((F94+F101)*F181+F179)*(1+F184),0) -> 102389 | G102: =ROUND(((G94+G101)*G181+G179)*(1+G184),0) -> 126868 | H102: =ROUND(((H94+H101)*H181+H179)*(1+H184),0) -> 151347 | I102: =ROUND(((I94+I101)*I181+I179)*(1+I184),0) -> 200305 | J102: =ROUND(((J94+J101)*J181+J179)*(1+J184),0) -> 249263 | ... L102: =ROUND(((L94+L101)*L181+L179)*(1+L184),0) -> 494051
B103: E-wallet — subsidi platform | C103: =C102-C101 -> 17911 | D103: =D102-D101 -> 31363 | E103: =E102-E101 -> 44815 | F103: =F102-F101 -> 58267 | G103: =G102-G101 -> 71720 | H103: =H102-H101 -> 85172 | I103: =I102-I101 -> 112077 | J103: =J102-J101 -> 138982 | ... L103: =L102-L101 -> 273505
B104: Kartu — dibebankan ke pembeli | C104: =IF(C94>0,ROUNDUP(ROUND((C94+C176)/(1-C177),6),0)-C94,0) -> 23715 | D104: =IF(D94>0,ROUNDUP(ROUND((D94+D176)/(1-D177),6),0)-D94,0) -> 45341 | E104: =IF(E94>0,ROUNDUP(ROUND((E94+E176)/(1-E177),6),0)-E94,0) -> 66966 | F104: =IF(F94>0,ROUNDUP(ROUND((F94+F176)/(1-F177),6),0)-F94,0) -> 88591 | G104: =IF(G94>0,ROUNDUP(ROUND((G94+G176)/(1-G177),6),0)-G94,0) -> 110217 | H104: =IF(H94>0,ROUNDUP(ROUND((H94+H176)/(1-H177),6),0)-H94,0) -> 131842 | I104: =IF(I94>0,ROUNDUP(ROUND((I94+I176)/(1-I177),6),0)-I94,0) -> 175093 | J104: =IF(J94>0,ROUNDUP(ROUND((J94+J176)/(1-J177),6),0)-J94,0) -> 218343 | ... L104: =IF(L94>0,ROUNDUP(ROUND((L94+L176)/(1-L177),6),0)-L94,0) -> 434596
B105: Kartu — biaya Xendit ((2,90% × TOTAL + Rp2.000 + Rp4.000) × 1,11) | C105: =ROUND(((C94+C104)*C182+C183+C179)*(1+C184),0) -> 30764 | D105: =ROUND(((D94+D104)*D182+D183+D179)*(1+D184),0) -> 54768 | E105: =ROUND(((E94+E104)*E182+E183+E179)*(1+E184),0) -> 78772 | F105: =ROUND(((F94+F104)*F182+F183+F179)*(1+F184),0) -> 102776 | G105: =ROUND(((G94+G104)*G182+G183+G179)*(1+G184),0) -> 126780 | H105: =ROUND(((H94+H104)*H182+H183+H179)*(1+H184),0) -> 150784 | I105: =ROUND(((I94+I104)*I182+I183+I179)*(1+I184),0) -> 198792 | J105: =ROUND(((J94+J104)*J182+J183+J179)*(1+J184),0) -> 246800 | ... L105: =ROUND(((L94+L104)*L182+L183+L179)*(1+L184),0) -> 486841
B106: Kartu — subsidi platform | C106: =C105-C104 -> 7049 | D106: =D105-D104 -> 9427 | E106: =E105-E104 -> 11806 | F106: =F105-F104 -> 14185 | G106: =G105-G104 -> 16563 | H106: =H105-H104 -> 18942 | I106: =I105-I104 -> 23699 | J106: =J105-J104 -> 28457 | ... L106: =L105-L104 -> 52245
B107: Rata-rata dibebankan ke pembeli (bauran) | C107: =C188*C95+C189*C98+C190*C101+C191*C104 -> 7555.8 | D107: =D188*D95+D189*D98+D190*D101+D191*D104 -> 12648.45 | E107: =E188*E95+E189*E98+E190*E101+E191*E104 -> 17740.85 | F107: =F188*F95+F189*F98+F190*F101+F191*F104 -> 22833.65 | G107: =G188*G95+G189*G98+G190*G101+G191*G104 -> 27926.15 | H107: =H188*H95+H189*H98+H190*H101+H191*H104 -> 33018.7 | I107: =I188*I95+I189*I98+I190*I101+I191*I104 -> 43204 | J107: =J188*J95+J189*J98+J190*J101+J191*J104 -> 53388.95 | ... L107: =L188*L95+L189*L98+L190*L101+L191*L104 -> 104314.75
B108: Rata-rata biaya Xendit (bauran) | C108: =C188*C96+C189*C99+C190*C102+C191*C105 -> 17022.1 | D108: =D188*D96+D189*D99+D190*D102+D191*D105 -> 24370.6 | E108: =E188*E96+E189*E99+E190*E102+E191*E105 -> 31718.7 | F108: =F188*F96+F189*F99+F190*F102+F191*F105 -> 39066.95 | G108: =G188*G96+G189*G99+G190*G102+G191*G105 -> 46415.2 | H108: =H188*H96+H189*H99+H190*H102+H191*H105 -> 53763.7 | I108: =I188*I96+I189*I99+I190*I102+I191*I105 -> 68460.2 | J108: =J188*J96+J189*J99+J190*J102+J191*J105 -> 83156.95 | ... L108: =L188*L96+L189*L99+L190*L102+L191*L105 -> 156639.75
...

Sheet Sumber
A1: Sumber & Catatan Keterbatasan Data
A2: Repo: /home/claude/jastipkita (dibaca 2026-10-04). URL publik diakses 2026-10-04 kecuali disebut lain.
A4: No | B4: Sumber | C4: Lokasi (path repo / URL) | D4: Dipakai untuk | E4: Tanggal akses / verifikasi | F4: Status
A5: 1 | B5: Business config default v1 | C5: packages/core/src/config/business-config.defaults.json | D5: Platform fee 5% (Rp10 rb–750 rb), protection 1,5% (Rp5 rb–300 rb), PPN layanan 12% × 0,916667, traveler fee min Rp25 rb & maks 30%, biaya kanal dibebankan (VA Rp4.500, QRIS 0,7%, e-wallet 1,5%, kartu Rp2.000 + 2,9%), referral (Rp25 rb/25 rb, min Rp500 rb, cap Rp250 rb/bln, traveler Rp50 rb), limit transaksi, payoutFeeIdr 0, markup FX | E5: 2026-10-04 | F5: Repo (config bertanda asumsi untuk payment_fees, service_tax, limits)
A6: 2 | B6: Pricing engine | C6: packages/core/src/pricing/index.ts | D6: Urutan hitung 11 baris, clamp fee, batas traveler fee (cap lalu min), gross-up biaya bayar T = ceil((P + fixed)/(1 − r)), PPN atas platform + protection, alokasi bucket | E6: 2026-10-04 | F6: Repo
A7: 3 | B7: Domain model | C7: docs/00-domain-model.md §9–§10 | D7: Daftar & urutan 11 baris harga; bucket ledger | E7: 2026-10-04 | F7: Repo
A8: 4 | B8: Payments & ledger | C8: docs/04-payments-ledger.md | D8: COMPLETION_RELEASE: traveler menerima harga aktual + bea dibayar + traveler fee; sisa dana barang/bea dikembalikan ke pembeli (markup FX bukan pendapatan); refund VA via payout | E8: 2026-10-04 | F8: Repo
A9: 5 | B9: Seed aturan bea | C9: db/seeds/0100_customs_rules.sql (ID_PAX_NON_PERSONAL v1) | D9: BM 10%, PPN 12% × 0,916667, PPh 5%, pembulatan CEIL_1000 semua komponen | E9: 2026-10-04 | F9: Repo — status DRAFT sampai verifikasi konsultan (L7)
A10: 6 | B10: Riset kepabeanan & pajak | C10: docs/research/01-customs-tax-indonesia.md | D10: PMK 34/2025 (jastip = non-pribadi), PMK 131/2024, beban ±27,6%, kurs JISDOR 17.917 (25–27 Sep 2026) | E10: diverifikasi 2026-09-27 | F10: Riset desk, bukan opini ahli
A11: 7 | B11: Riset Xendit | C11: docs/research/02-xendit-integration.md §1.3, §4, §8 | D11: Tarif publik Xendit, contoh PPN 11% atas fee, batas QRIS Rp10 jt, VA tidak bisa refund, chargeback USD 25 | E11: diverifikasi 2026-09-27 | F11: Harga publik, bukan kontrak
A12: 8 | B12: Xendit — halaman harga Indonesia | C12: https://www.xendit.co/en-id/pricing/ | D12: VA Rp9.000 + Rp4.000; QRIS 0,70% incl. VAT + Rp4.000; OVO 3,00–5,50%, DANA 2,00–3,50%, ShopeePay 2,50–3,60%, GoPay 3,00–5,00% (+Rp4.000); kartu 2,90% + Rp2.000 + Rp4.000; payout 1,00% (min Rp2.500) + Rp4.000; 'exclusive of taxes' | E12: 2026-10-04 | F12: Diverifikasi web; DANA berubah dari 3,00–3,50% (research 02)
A13: 9 | B13: Riset pasar & nama | C13: docs/research/04-market-and-naming.md | D13: Traveler fee lazim 5–15%; pesaing; tidak ada data ukuran pasar kredibel; risiko merek TINGGI | E13: diverifikasi 2026-09-27 | F13: Riset desk
A14: 10 | B14: Riset legal & regulasi | C14: docs/research/05-legal-regulatory.md | D14: Ambang PKP Rp4,8 M; PMK 37/2025 PPh 22 marketplace; PSE & PPMSE via OSS tanpa biaya | E14: diverifikasi 2026-09-27 | F14: Bukan nasihat hukum
A15: 11 | B15: Arsitektur — tier infrastruktur | C15: docs/01-architecture.md §10–§11 | D15: Tahap 0 US$0; tahap 1 ≈ US$5 + US$19–30/bulan; tahap 2 +US$20–50; tahap 3 case by case; risiko W1–W10 | E15: 2026-10-04 | F15: Repo (biaya bertanda ASUMSI)
A16: 12 | B16: Status serah terima | C16: docs/STATUS.md §2, §5b | D16: Semua integrasi MOCK/SANDBOX; daftar biaya owner (Play ±US$25, Apple US$99/thn, infra); vendor e-KYC belum dipilih | E16: 2026-10-04 | F16: Repo
... A25: 21 | B25: PP 20/2026 (PPh final UMKM) | C25: https://news.ddtc.co.id/berita/nasional/1819737/pp-direvisi-pph-final-umkm-cuma-untuk-op-pt-perorangan-dan-koperasi ; https://www.pajak.go.id/en/node/119954 | D25: PT (non-perorangan) tidak lagi dapat PPh final 0,5% → PPh Badan atas laba; model disajikan pra-pajak | E25: 2026-10-04 | F25: Sumber sekunder; tanggal berlaku berbeda antar-sumber (22 Apr vs 2 Jun 2026) — NEEDS_VERIFICATION konsultan pajak
A27: Catatan keterbatasan data
A28: 1. Pra-launch: belum ada transaksi nyata; semua integrasi MOCK/SANDBOX (docs/STATUS.md). Seluruh volume (traveler, pembeli, frekuensi, churn), CAC, bauran kanal, tingkat batal, loss ratio proteksi dan biaya CS adalah ASUMSI.
A29: 2. Tidak ada data ukuran pasar jastip yang kredibel (research 04) — model dibangun bottom-up dari kapasitas traveler & funnel pembeli, bukan dari TAM.
A30: 3. Tarif Xendit = harga publik (2026-10-04), bukan kontrak. Biaya payout (1% + Rp4.000) dan biaya xenPlatform NEEDS_VERIFICATION; PPN atas fee diperlakukan sebagai biaya (asumsi tidak dikreditkan).
A31: 4. Bea masuk & pajak impor adalah estimasi pass-through (seed DRAFT, PMK 34/2025); PPh tanpa NPWP (10%) dan praktik pembulatan CD belum diverifikasi. Bukan pendapatan platform.
A32: 5. PPN layanan hanya boleh dipungut bila PT sudah PKP (L8); di model diperlakukan pass-through sehingga tidak mengubah pendapatan bersih.
A33: 6. JastipKita Protection belum punya mitra asuransi (L9); bila diasuransikan, protection fee dapat berubah menjadi premi (pass-through) dikurangi komisi.
A34: 7. Credit referral diakui saat ditebus pada bulan yang sama (penyederhanaan); cap per perujuk (config) ditegakkan via MIN(); cap anggaran global Rp2 jt adalah USULAN (sakelar default 0).
A35: 8. Biaya SDM, kepatuhan dan biaya sekali (PT, legal, kepabeanan, pajak, merek, pentest, DPIA) adalah ASUMSI — minta penawaran (STATUS §5b). Rencana biaya sama di ketiga skenario agar skenario hanya mencerminkan ketidakpastian pasar & tarif.
A36: 9. Model pra-pajak: PPh Badan tidak dimodelkan (PT baru tidak dapat PPh final 0,5% per PP 20/2026 — sumber sekunder; rugi fiskal dapat dikompensasikan). Dana escrow pembeli di saldo Xendit bukan kas perusahaan dan tidak masuk arus kas.
A37: 10. Regulasi yang dapat mengubah model: status traveler sebagai 'pedagang' (Permendag 19/2026), FOB USD 100 Pasal 23, penunjukan pemungut PPh 22 (PMK 37/2025), kelayakan escrow (PBI 23/6/2021), status merek 'JastipKita'.
A38: 11. Dokumen ini bukan nasihat keuangan, investasi, hukum, atau pajak.
